Workbook
Name _Hlk49843120: 'RESULTS Eversource'!#REF!
Name _Hlk50967569: 'RESULTS Eversource'!$A$8

Sheet INSTRUCTIONS
A1: INSTRUCTIONS - INDIVIDUAL EEMS | B1: INSTRUCTIONS - PACKAGE OF EEMS
A2: 1) Enter all EEM data ine the "EEM Data Entry" tab, including title, capital cost, estimated kWh savings for electric and MMBtu savings for each fuel type, and measure lifetime | B2: 1) Enter all EEM data FOR PACKAGE ONLY, including title, capital cost, estimated savings percent for each fuel type, and measure lifetime. ENTER PACKAGE TITLE WHERE INDICATED
A3: 2) Follow the instructions on the "Interest Rate" tab to determine the interest rate for this project | B3: 2) Follow the instructions on the "Interest Rate" tab to determine the interest rate for this project
A4: 3) Copy and paste tables from the appropriate "RESULTS" tab to audit report | B4: 3) Copy and paste THE PACKAGE TABLE to report as appropriate
A6: Cell Color-Coding Key
A7: Data Entry
A8: Formula (optional override but should not be necessary)
A10: Tab Color-Coding Key
A11: Reference
A12: Data Entry
A13: Results
A14: Backend - Individual EEMs
A15: Backend - Package & Cascading

Sheet EEM Data Entry
H1: ENTER KWH AND MMBTU SAVINGS VALUES NOT PERCENTAGES
A2: EEM Info | D2: Capital Cost | H2: Energy Savings | S2: 3.412142 | U2: 137.381 | W2: 100 | Y2: 91.5 | AC2: 16400 | AE2: 9500
A3: EEM # | B3: EEM Title | C3: Lifetime of Measure | D3: Capital Cost | E3: Incentive/ Rebate (ENTER "0" IF N/A) | F3: Final Installed Cost | G3: Incentive Reference | H3: Electric kWh | I3: Oil MMBtu | J3: Natural Gas MMBtu | K3: Propane MMBtu | L3: District Steam | M3: Wood Pellets MMBtu | N3: Wood Chips MMBtu | O3: Water | Q3: ENTER ASSUMPTIONS HERE
B4: Envelope | R4: Assumptions | S4: Electricity | U4: Fuel Oil | W4: Natural Gas | Y4: Propane | AA4: District Steam | AC4: Wood Pellets | AE4: Wood Chips | AG4: Water / Sewer | AI4: Total Energy
F5: =IF(AND(COUNT(D5)>0,COUNT(E5)>0),D5-E5,"") | G5: N/A | R5: Baseline Energy Usage: | S5: 0 | T5: kWh | U5: 0 | V5: Gallons | W5: 0 | X5: Therms | Y5: 0 | Z5: gallons | AA5: 0 | AB5: kPounds | AC5: 0 | AD5: tons | AE5: 0 | AF5: tons | AG5: 0 | AH5: kGallons | AI5: =SUM((S5*S2),(U2*U5),(W2*W5),(Y2*Y5),(AC2*AC5),(AE2*AE5)) -> 0 | AJ5: kBTU
F6: =IF(AND(COUNT(D6)>0,COUNT(E6)>0),D6-E6,"") | G6: N/A | R6: Baseline Annual Energy Cost: | S6: 0 | T6: Cost | U6: 0 | V6: Cost | W6: 0 | X6: Cost | Y6: 0 | Z6: Cost | AA6: 0 | AB6: Cost | AC6: 0 | AD6: Cost | AE6: 0 | AF6: Cost | AG6: 0 | AH6: Cost | AI6: =S6+U6+W6+Y6+AA6+AE6+AG6+AC6 -> 0 | AJ6: Total Cost
F7: =IF(AND(COUNT(D7)>0,COUNT(E7)>0),D7-E7,"") | G7: N/A | R7: Baseline Unit Cost: | S7: =IF(S5=0,0,S6/S5) -> 0 | T7: ($/kWh) | U7: =IF(U5=0,0,U6/U5) -> 0 | V7: ($/gal.) | W7: =IF(W5=0,0,W6/W5) -> 0 | X7: ($/therm) | Y7: =IF(Y5=0,0,Y6/Y5) -> 0 | Z7: ($/gal.) | AA7: =IF(AA5=0,0,AA6/AA5) -> 0 | AB7: ($/kLbs..) | AC7: =IF(AC5=0,0,AC6/AC5) -> 0 | AD7: ($/ton) | AE7: =IF(AE5=0,0,AE6/AE5) -> 0 | AF7: ($/ton) | AG7: =IF(AG5=0,0,AG6/AG5) -> 0 | AH7: ($/gal.)
F8: =IF(AND(COUNT(D8)>0,COUNT(E8)>0),D8-E8,"") | G8: N/A | R8: MMBtus | S8: =S5*0.003412142 -> 0 | T8: MMBtu | U8: =U5*0.137381 -> 0 | V8: MMBtu | W8: =W5*0.1 -> 0 | X8: MMBtu | Y8: =Y5*0.0915 -> 0 | Z8: MMBtu | AA8: =AA5*1.194 -> 0 | AB8: MMBtu | AC8: =AC5*16.4 -> 0 | AD8: MMBtu | AE8: =AE5*9.5 -> 0 | AF8: MMBtu
F9: =IF(AND(COUNT(D9)>0,COUNT(E9)>0),D9-E9,"") | G9: N/A | Q9: IF THIS IS AN EEM PACKAGE… | R9: $/MMBtu | S9: =S6/S8 -> #DIV/0! | T9: $/MMBtu | U9: =U6/U8 -> #DIV/0! | V9: $/MMBtu | W9: =W6/W8 -> #DIV/0! | X9: $/MMBtu | Y9: =Y6/Y8 -> #DIV/0! | Z9: $/MMBtu | AA9: =AA6/AA8 -> #DIV/0! | AB9: $/MMBtu | AC9: =AC6/AC8 -> #DIV/0! | AD9: $/MMBtu | AE9: =AE6/AE8 -> #DIV/0! | AF9: $/MMBtu
F10: =IF(AND(COUNT(D10)>0,COUNT(E10)>0),D10-E10,"") | G10: N/A
F11: =IF(AND(COUNT(D11)>0,COUNT(E11)>0),D11-E11,"") | G11: N/A
F12: =IF(AND(COUNT(D12)>0,COUNT(E12)>0),D12-E12,"") | G12: N/A
F13: =IF(AND(COUNT(D13)>0,COUNT(E13)>0),D13-E13,"") | G13: N/A | Q13: ENTER NAME OF PACKAGE IN THE BOX BELOW
F14: =IF(AND(COUNT(D14)>0,COUNT(E14)>0),D14-E14,"") | G14: N/A
F15: =IF(AND(COUNT(D15)>0,COUNT(E15)>0),D15-E15,"") | G15: N/A
F16: =IF(AND(COUNT(D16)>0,COUNT(E16)>0),D16-E16,"") | G16: N/A
F17: =IF(AND(COUNT(D17)>0,COUNT(E17)>0),D17-E17,"") | G17: N/A | Q17: RECOMMENDED PACKAGE: Example
F18: =IF(AND(COUNT(D18)>0,COUNT(E18)>0),D18-E18,"") | G18: N/A
F19: =IF(AND(COUNT(D19)>0,COUNT(E19)>0),D19-E19,"") | G19: N/A | Q19: AVERAGE BUILDING LIFESPAN ASSUMPTION
F20: =IF(AND(COUNT(D20)>0,COUNT(E20)>0),D20-E20,"") | G20: N/A
F21: =IF(AND(COUNT(D21)>0,COUNT(E21)>0),D21-E21,"") | G21: N/A
F22: =IF(AND(COUNT(D22)>0,COUNT(E22)>0),D22-E22,"") | G22: N/A | Q22: Average building lifespan = | R22: 63 | S22: SOURCE
F23: =IF(AND(COUNT(D23)>0,COUNT(E23)>0),D23-E23,"") | G23: N/A
F24: =IF(AND(COUNT(D24)>0,COUNT(E24)>0),D24-E24,"") | G24: N/A
F25: =IF(AND(COUNT(D25)>0,COUNT(E25)>0),D25-E25,"") | G25: N/A
F26: =IF(AND(COUNT(D26)>0,COUNT(E26)>0),D26-E26,"") | G26: N/A
F27: =IF(AND(COUNT(D27)>0,COUNT(E27)>0),D27-E27,"") | G27: N/A
F28: =IF(AND(COUNT(D28)>0,COUNT(E28)>0),D28-E28,"") | G28: N/A
B29: Mechanical
F30: =IF(AND(COUNT(D30)>0,COUNT(E30)>0),D30-E30,"") | G30: N/A
F31: =IF(AND(COUNT(D31)>0,COUNT(E31)>0),D31-E31,"") | G31: N/A
F32: =IF(AND(COUNT(D32)>0,COUNT(E32)>0),D32-E32,"") | G32: N/A
F33: =IF(AND(COUNT(D33)>0,COUNT(E33)>0),D33-E33,"") | G33: N/A
F34: =IF(AND(COUNT(D34)>0,COUNT(E34)>0),D34-E34,"") | G34: N/A
F35: =IF(AND(COUNT(D35)>0,COUNT(E35)>0),D35-E35,"") | G35: N/A
F36: =IF(AND(COUNT(D36)>0,COUNT(E36)>0),D36-E36,"") | G36: N/A
F37: =IF(AND(COUNT(D37)>0,COUNT(E37)>0),D37-E37,"") | G37: N/A
F38: =IF(AND(COUNT(D38)>0,COUNT(E38)>0),D38-E38,"") | G38: N/A
F39: =IF(AND(COUNT(D39)>0,COUNT(E39)>0),D39-E39,"") | G39: N/A
F40: =IF(AND(COUNT(D40)>0,COUNT(E40)>0),D40-E40,"") | G40: N/A
F41: =IF(AND(COUNT(D41)>0,COUNT(E41)>0),D41-E41,"") | G41: N/A
... F43: =IF(AND(COUNT(D43)>0,COUNT(E43)>0),D43-E43,"") | G43: N/A
B44: Appliances & Lighting
F45: =IF(AND(COUNT(D45)>0,COUNT(E45)>0),D45-E45,"") | G45: N/A
F46: =IF(AND(COUNT(D46)>0,COUNT(E46)>0),D46-E46,"") | G46: N/A
F47: =IF(AND(COUNT(D47)>0,COUNT(E47)>0),D47-E47,"") | G47: N/A
F48: =IF(AND(COUNT(D48)>0,COUNT(E48)>0),D48-E48,"") | G48: N/A
F49: =IF(AND(COUNT(D49)>0,COUNT(E49)>0),D49-E49,"") | G49: N/A
F50: =IF(AND(COUNT(D50)>0,COUNT(E50)>0),D50-E50,"") | G50: N/A
F51: =IF(AND(COUNT(D51)>0,COUNT(E51)>0),D51-E51,"") | G51: N/A
F52: =IF(AND(COUNT(D52)>0,COUNT(E52)>0),D52-E52,"") | G52: N/A
F53: =IF(AND(COUNT(D53)>0,COUNT(E53)>0),D53-E53,"") | G53: N/A
F54: =IF(AND(COUNT(D54)>0,COUNT(E54)>0),D54-E54,"") | G54: N/A
F55: =IF(AND(COUNT(D55)>0,COUNT(E55)>0),D55-E55,"") | G55: N/A
F56: =IF(AND(COUNT(D56)>0,COUNT(E56)>0),D56-E56,"") | G56: N/A
... F59: =IF(AND(COUNT(D59)>0,COUNT(E59)>0),D59-E59,"") | G59: N/A
B60: Renewable
F61: =IF(AND(COUNT(D61)>0,COUNT(E61)>0),D61-E61,"") | G61: N/A
F62: =IF(AND(COUNT(D62)>0,COUNT(E62)>0),D62-E62,"") | G62: N/A
F63: =IF(AND(COUNT(D63)>0,COUNT(E63)>0),D63-E63,"") | G63: N/A
F64: =IF(AND(COUNT(D64)>0,COUNT(E64)>0),D64-E64,"") | G64: N/A
F65: =IF(AND(COUNT(D65)>0,COUNT(E65)>0),D65-E65,"") | G65: N/A
F66: =IF(AND(COUNT(D66)>0,COUNT(E66)>0),D66-E66,"") | G66: N/A
F67: =IF(AND(COUNT(D67)>0,COUNT(E67)>0),D67-E67,"") | G67: N/A
F68: =IF(AND(COUNT(D68)>0,COUNT(E68)>0),D68-E68,"") | G68: N/A
F69: =IF(AND(COUNT(D69)>0,COUNT(E69)>0),D69-E69,"") | G69: N/A
F70: =IF(AND(COUNT(D70)>0,COUNT(E70)>0),D70-E70,"") | G70: N/A
F71: =IF(AND(COUNT(D71)>0,COUNT(E71)>0),D71-E71,"") | G71: N/A
F72: =IF(AND(COUNT(D72)>0,COUNT(E72)>0),D72-E72,"") | G72: N/A
... F74: =IF(AND(COUNT(D74)>0,COUNT(E74)>0),D74-E74,"") | G74: N/A
A82: EEM Info | D82: Capital Cost | H82: Energy Savings Percent
A83: EEM # | B83: EEM Title | C83: Lifetime of Measure | D83: Capital Cost | E83: Incentive/ Rebate (ENTER "0" IF N/A) | F83: Final Installed Cost | G83: Incentive Reference | H83: Electric | I83: Oil | J83: Natural Gas | K83: Propane | L83: District Steam | M83: Wood Pellets | N83: Wood Chips | O83: Water
B84: Envelope
A85: =IF(ISTEXT(A5)=TRUE,A5,"") | B85: =IF(ISTEXT(B5)=TRUE,B5,"") | C85: =IF(ISNUMBER(C5)=TRUE,C5,"") | D85: =IF(ISNUMBER(D5)=TRUE,D5,"") | E85: =IF(ISNUMBER(E5)=TRUE,E5,"") | F85: =IF(ISNUMBER(F5)=TRUE,F5,"") | G85: =IF(ISTEXT(G5)=TRUE,G5,"") -> N/A | H85: =IFERROR(H5/$S$5,0) -> 0 | I85: =IFERROR(I5/$U$8,0) -> 0 | J85: =IFERROR(J5/$W$8,0) -> 0 | K85: =IFERROR(K5/$Y$8,0) -> 0 | L85: =IFERROR(L5/$AA$8,0) -> 0 | M85: =IFERROR(M5/$AC$8,0) -> 0 | N85: =IFERROR(N5/$AE$8,0) -> 0 | O85: =IFERROR(O5/$AG$8,0) -> 0
A86: =IF(ISTEXT(A6)=TRUE,A6,"") | B86: =IF(ISTEXT(B6)=TRUE,B6,"") | C86: =IF(ISNUMBER(C6)=TRUE,C6,"") | D86: =IF(ISNUMBER(D6)=TRUE,D6,"") | E86: =IF(ISNUMBER(E6)=TRUE,E6,"") | F86: =IF(ISNUMBER(F6)=TRUE,F6,"") | G86: =IF(ISTEXT(G6)=TRUE,G6,"") -> N/A | H86: =IFERROR(H6/$S$5,0) -> 0 | I86: =IFERROR(I6/$U$8,0) -> 0 | J86: =IFERROR(J6/$W$8,0) -> 0 | K86: =IFERROR(K6/$Y$8,0) -> 0 | L86: =IFERROR(L6/$AA$8,0) -> 0 | M86: =IFERROR(M6/$AC$8,0) -> 0 | N86: =IFERROR(N6/$AE$8,0) -> 0 | O86: =IFERROR(O6/$AG$8,0) -> 0
A87: =IF(ISTEXT(A7)=TRUE,A7,"") | B87: =IF(ISTEXT(B7)=TRUE,B7,"") | C87: =IF(ISNUMBER(C7)=TRUE,C7,"") | D87: =IF(ISNUMBER(D7)=TRUE,D7,"") | E87: =IF(ISNUMBER(E7)=TRUE,E7,"") | F87: =IF(ISNUMBER(F7)=TRUE,F7,"") | G87: =IF(ISTEXT(G7)=TRUE,G7,"") -> N/A | H87: =IFERROR(H7/$S$5,0) -> 0 | I87: =IFERROR(I7/$U$8,0) -> 0 | J87: =IFERROR(J7/$W$8,0) -> 0 | K87: =IFERROR(K7/$Y$8,0) -> 0 | L87: =IFERROR(L7/$AA$8,0) -> 0 | M87: =IFERROR(M7/$AC$8,0) -> 0 | N87: =IFERROR(N7/$AE$8,0) -> 0 | O87: =IFERROR(O7/$AG$8,0) -> 0
A88: =IF(ISTEXT(A8)=TRUE,A8,"") | B88: =IF(ISTEXT(B8)=TRUE,B8,"") | C88: =IF(ISNUMBER(C8)=TRUE,C8,"") | D88: =IF(ISNUMBER(D8)=TRUE,D8,"") | E88: =IF(ISNUMBER(E8)=TRUE,E8,"") | F88: =IF(ISNUMBER(F8)=TRUE,F8,"") | G88: =IF(ISTEXT(G8)=TRUE,G8,"") -> N/A | H88: =IFERROR(H8/$S$5,0) -> 0 | I88: =IFERROR(I8/$U$8,0) -> 0 | J88: =IFERROR(J8/$W$8,0) -> 0 | K88: =IFERROR(K8/$Y$8,0) -> 0 | L88: =IFERROR(L8/$AA$8,0) -> 0 | M88: =IFERROR(M8/$AC$8,0) -> 0 | N88: =IFERROR(N8/$AE$8,0) -> 0 | O88: =IFERROR(O8/$AG$8,0) -> 0
A89: =IF(ISTEXT(A9)=TRUE,A9,"") | B89: =IF(ISTEXT(B9)=TRUE,B9,"") | C89: =IF(ISNUMBER(C9)=TRUE,C9,"") | D89: =IF(ISNUMBER(D9)=TRUE,D9,"") | E89: =IF(ISNUMBER(E9)=TRUE,E9,"") | F89: =IF(ISNUMBER(F9)=TRUE,F9,"") | G89: =IF(ISTEXT(G9)=TRUE,G9,"") -> N/A | H89: =IFERROR(H9/$S$5,0) -> 0 | I89: =IFERROR(I9/$U$8,0) -> 0 | J89: =IFERROR(J9/$W$8,0) -> 0 | K89: =IFERROR(K9/$Y$8,0) -> 0 | L89: =IFERROR(L9/$AA$8,0) -> 0 | M89: =IFERROR(M9/$AC$8,0) -> 0 | N89: =IFERROR(N9/$AE$8,0) -> 0 | O89: =IFERROR(O9/$AG$8,0) -> 0
A90: =IF(ISTEXT(A10)=TRUE,A10,"") | B90: =IF(ISTEXT(B10)=TRUE,B10,"") | C90: =IF(ISNUMBER(C10)=TRUE,C10,"") | D90: =IF(ISNUMBER(D10)=TRUE,D10,"") | E90: =IF(ISNUMBER(E10)=TRUE,E10,"") | F90: =IF(ISNUMBER(F10)=TRUE,F10,"") | G90: =IF(ISTEXT(G10)=TRUE,G10,"") -> N/A | H90: =IFERROR(H10/$S$5,0) -> 0 | I90: =IFERROR(I10/$U$8,0) -> 0 | J90: =IFERROR(J10/$W$8,0) -> 0 | K90: =IFERROR(K10/$Y$8,0) -> 0 | L90: =IFERROR(L10/$AA$8,0) -> 0 | M90: =IFERROR(M10/$AC$8,0) -> 0 | N90: =IFERROR(N10/$AE$8,0) -> 0 | O90: =IFERROR(O10/$AG$8,0) -> 0
A91: =IF(ISTEXT(A11)=TRUE,A11,"") | B91: =IF(ISTEXT(B11)=TRUE,B11,"") | C91: =IF(ISNUMBER(C11)=TRUE,C11,"") | D91: =IF(ISNUMBER(D11)=TRUE,D11,"") | E91: =IF(ISNUMBER(E11)=TRUE,E11,"") | F91: =IF(ISNUMBER(F11)=TRUE,F11,"") | G91: =IF(ISTEXT(G11)=TRUE,G11,"") -> N/A | H91: =IFERROR(H11/$S$5,0) -> 0 | I91: =IFERROR(I11/$U$8,0) -> 0 | J91: =IFERROR(J11/$W$8,0) -> 0 | K91: =IFERROR(K11/$Y$8,0) -> 0 | L91: =IFERROR(L11/$AA$8,0) -> 0 | M91: =IFERROR(M11/$AC$8,0) -> 0 | N91: =IFERROR(N11/$AE$8,0) -> 0 | O91: =IFERROR(O11/$AG$8,0) -> 0
A92: =IF(ISTEXT(A12)=TRUE,A12,"") | B92: =IF(ISTEXT(B12)=TRUE,B12,"") | C92: =IF(ISNUMBER(C12)=TRUE,C12,"") | D92: =IF(ISNUMBER(D12)=TRUE,D12,"") | E92: =IF(ISNUMBER(E12)=TRUE,E12,"") | F92: =IF(ISNUMBER(F12)=TRUE,F12,"") | G92: =IF(ISTEXT(G12)=TRUE,G12,"") -> N/A | H92: =IFERROR(H12/$S$5,0) -> 0 | I92: =IFERROR(I12/$U$8,0) -> 0 | J92: =IFERROR(J12/$W$8,0) -> 0 | K92: =IFERROR(K12/$Y$8,0) -> 0 | L92: =IFERROR(L12/$AA$8,0) -> 0 | M92: =IFERROR(M12/$AC$8,0) -> 0 | N92: =IFERROR(N12/$AE$8,0) -> 0 | O92: =IFERROR(O12/$AG$8,0) -> 0
A93: =IF(ISTEXT(A13)=TRUE,A13,"") | B93: =IF(ISTEXT(B13)=TRUE,B13,"") | C93: =IF(ISNUMBER(C13)=TRUE,C13,"") | D93: =IF(ISNUMBER(D13)=TRUE,D13,"") | E93: =IF(ISNUMBER(E13)=TRUE,E13,"") | F93: =IF(ISNUMBER(F13)=TRUE,F13,"") | G93: =IF(ISTEXT(G13)=TRUE,G13,"") -> N/A | H93: =IFERROR(H13/$S$5,0) -> 0 | I93: =IFERROR(I13/$U$8,0) -> 0 | J93: =IFERROR(J13/$W$8,0) -> 0 | K93: =IFERROR(K13/$Y$8,0) -> 0 | L93: =IFERROR(L13/$AA$8,0) -> 0 | M93: =IFERROR(M13/$AC$8,0) -> 0 | N93: =IFERROR(N13/$AE$8,0) -> 0 | O93: =IFERROR(O13/$AG$8,0) -> 0
A94: =IF(ISTEXT(A14)=TRUE,A14,"") | B94: =IF(ISTEXT(B14)=TRUE,B14,"") | C94: =IF(ISNUMBER(C14)=TRUE,C14,"") | D94: =IF(ISNUMBER(D14)=TRUE,D14,"") | E94: =IF(ISNUMBER(E14)=TRUE,E14,"") | F94: =IF(ISNUMBER(F14)=TRUE,F14,"") | G94: =IF(ISTEXT(G14)=TRUE,G14,"") -> N/A | H94: =IFERROR(H14/$S$5,0) -> 0 | I94: =IFERROR(I14/$U$8,0) -> 0 | J94: =IFERROR(J14/$W$8,0) -> 0 | K94: =IFERROR(K14/$Y$8,0) -> 0 | L94: =IFERROR(L14/$AA$8,0) -> 0 | M94: =IFERROR(M14/$AC$8,0) -> 0 | N94: =IFERROR(N14/$AE$8,0) -> 0 | O94: =IFERROR(O14/$AG$8,0) -> 0
A95: =IF(ISTEXT(A15)=TRUE,A15,"") | B95: =IF(ISTEXT(B15)=TRUE,B15,"") | C95: =IF(ISNUMBER(C15)=TRUE,C15,"") | D95: =IF(ISNUMBER(D15)=TRUE,D15,"") | E95: =IF(ISNUMBER(E15)=TRUE,E15,"") | F95: =IF(ISNUMBER(F15)=TRUE,F15,"") | G95: =IF(ISTEXT(G15)=TRUE,G15,"") -> N/A | H95: =IFERROR(H15/$S$5,0) -> 0 | I95: =IFERROR(I15/$U$8,0) -> 0 | J95: =IFERROR(J15/$W$8,0) -> 0 | K95: =IFERROR(K15/$Y$8,0) -> 0 | L95: =IFERROR(L15/$AA$8,0) -> 0 | M95: =IFERROR(M15/$AC$8,0) -> 0 | N95: =IFERROR(N15/$AE$8,0) -> 0 | O95: =IFERROR(O15/$AG$8,0) -> 0
A96: =IF(ISTEXT(A16)=TRUE,A16,"") | B96: =IF(ISTEXT(B16)=TRUE,B16,"") | C96: =IF(ISNUMBER(C16)=TRUE,C16,"") | D96: =IF(ISNUMBER(D16)=TRUE,D16,"") | E96: =IF(ISNUMBER(E16)=TRUE,E16,"") | F96: =IF(ISNUMBER(F16)=TRUE,F16,"") | G96: =IF(ISTEXT(G16)=TRUE,G16,"") -> N/A | H96: =IFERROR(H16/$S$5,0) -> 0 | I96: =IFERROR(I16/$U$8,0) -> 0 | J96: =IFERROR(J16/$W$8,0) -> 0 | K96: =IFERROR(K16/$Y$8,0) -> 0 | L96: =IFERROR(L16/$AA$8,0) -> 0 | M96: =IFERROR(M16/$AC$8,0) -> 0 | N96: =IFERROR(N16/$AE$8,0) -> 0 | O96: =IFERROR(O16/$AG$8,0) -> 0
... A108: =IF(ISTEXT(A28)=TRUE,A28,"") | B108: =IF(ISTEXT(B28)=TRUE,B28,"") | C108: =IF(ISNUMBER(C28)=TRUE,C28,"") | D108: =IF(ISNUMBER(D28)=TRUE,D28,"") | E108: =IF(ISNUMBER(E28)=TRUE,E28,"") | F108: =IF(ISNUMBER(F28)=TRUE,F28,"") | G108: =IF(ISTEXT(G28)=TRUE,G28,"") -> N/A | H108: =IFERROR(H28/$S$5,0) -> 0 | I108: =IFERROR(I28/$U$8,0) -> 0 | J108: =IFERROR(J28/$W$8,0) -> 0 | K108: =IFERROR(K28/$Y$8,0) -> 0 | L108: =IFERROR(L28/$AA$8,0) -> 0 | M108: =IFERROR(M28/$AC$8,0) -> 0 | N108: =IFERROR(N28/$AE$8,0) -> 0 | O108: =IFERROR(O28/$AG$8,0) -> 0
B109: Mechanical
A110: =IF(ISTEXT(A30)=TRUE,A30,"") | B110: =IF(ISTEXT(B30)=TRUE,B30,"") | C110: =IF(ISNUMBER(C30)=TRUE,C30,"") | D110: =IF(ISNUMBER(D30)=TRUE,D30,"") | E110: =IF(ISNUMBER(E30)=TRUE,E30,"") | F110: =IF(ISNUMBER(F30)=TRUE,F30,"") | G110: =IF(ISTEXT(G30)=TRUE,G30,"") -> N/A | H110: =IFERROR(H30/$S$5,0) -> 0 | I110: =IFERROR(I30/$U$8,0) -> 0 | J110: =IFERROR(J30/$W$8,0) -> 0 | K110: =IFERROR(K30/$Y$8,0) -> 0 | L110: =IFERROR(L30/$AA$8,0) -> 0 | M110: =IFERROR(M30/$AC$8,0) -> 0 | N110: =IFERROR(N30/$AE$8,0) -> 0 | O110: =IFERROR(O30/$AG$8,0) -> 0
A111: =IF(ISTEXT(A31)=TRUE,A31,"") | B111: =IF(ISTEXT(B31)=TRUE,B31,"") | C111: =IF(ISNUMBER(C31)=TRUE,C31,"") | D111: =IF(ISNUMBER(D31)=TRUE,D31,"") | E111: =IF(ISNUMBER(E31)=TRUE,E31,"") | F111: =IF(ISNUMBER(F31)=TRUE,F31,"") | G111: =IF(ISTEXT(G31)=TRUE,G31,"") -> N/A | H111: =IFERROR(H31/$S$5,0) -> 0 | I111: =IFERROR(I31/$U$8,0) -> 0 | J111: =IFERROR(J31/$W$8,0) -> 0 | K111: =IFERROR(K31/$Y$8,0) -> 0 | L111: =IFERROR(L31/$AA$8,0) -> 0 | M111: =IFERROR(M31/$AC$8,0) -> 0 | N111: =IFERROR(N31/$AE$8,0) -> 0 | O111: =IFERROR(O31/$AG$8,0) -> 0
A112: =IF(ISTEXT(A32)=TRUE,A32,"") | B112: =IF(ISTEXT(B32)=TRUE,B32,"") | C112: =IF(ISNUMBER(C32)=TRUE,C32,"") | D112: =IF(ISNUMBER(D32)=TRUE,D32,"") | E112: =IF(ISNUMBER(E32)=TRUE,E32,"") | F112: =IF(ISNUMBER(F32)=TRUE,F32,"") | G112: =IF(ISTEXT(G32)=TRUE,G32,"") -> N/A | H112: =IFERROR(H32/$S$5,0) -> 0 | I112: =IFERROR(I32/$U$8,0) -> 0 | J112: =IFERROR(J32/$W$8,0) -> 0 | K112: =IFERROR(K32/$Y$8,0) -> 0 | L112: =IFERROR(L32/$AA$8,0) -> 0 | M112: =IFERROR(M32/$AC$8,0) -> 0 | N112: =IFERROR(N32/$AE$8,0) -> 0 | O112: =IFERROR(O32/$AG$8,0) -> 0
A113: =IF(ISTEXT(A33)=TRUE,A33,"") | B113: =IF(ISTEXT(B33)=TRUE,B33,"") | C113: =IF(ISNUMBER(C33)=TRUE,C33,"") | D113: =IF(ISNUMBER(D33)=TRUE,D33,"") | E113: =IF(ISNUMBER(E33)=TRUE,E33,"") | F113: =IF(ISNUMBER(F33)=TRUE,F33,"") | G113: =IF(ISTEXT(G33)=TRUE,G33,"") -> N/A | H113: =IFERROR(H33/$S$5,0) -> 0 | I113: =IFERROR(I33/$U$8,0) -> 0 | J113: =IFERROR(J33/$W$8,0) -> 0 | K113: =IFERROR(K33/$Y$8,0) -> 0 | L113: =IFERROR(L33/$AA$8,0) -> 0 | M113: =IFERROR(M33/$AC$8,0) -> 0 | N113: =IFERROR(N33/$AE$8,0) -> 0 | O113: =IFERROR(O33/$AG$8,0) -> 0
A114: =IF(ISTEXT(A34)=TRUE,A34,"") | B114: =IF(ISTEXT(B34)=TRUE,B34,"") | C114: =IF(ISNUMBER(C34)=TRUE,C34,"") | D114: =IF(ISNUMBER(D34)=TRUE,D34,"") | E114: =IF(ISNUMBER(E34)=TRUE,E34,"") | F114: =IF(ISNUMBER(F34)=TRUE,F34,"") | G114: =IF(ISTEXT(G34)=TRUE,G34,"") -> N/A | H114: =IFERROR(H34/$S$5,0) -> 0 | I114: =IFERROR(I34/$U$8,0) -> 0 | J114: =IFERROR(J34/$W$8,0) -> 0 | K114: =IFERROR(K34/$Y$8,0) -> 0 | L114: =IFERROR(L34/$AA$8,0) -> 0 | M114: =IFERROR(M34/$AC$8,0) -> 0 | N114: =IFERROR(N34/$AE$8,0) -> 0 | O114: =IFERROR(O34/$AG$8,0) -> 0
A115: =IF(ISTEXT(A35)=TRUE,A35,"") | B115: =IF(ISTEXT(B35)=TRUE,B35,"") | C115: =IF(ISNUMBER(C35)=TRUE,C35,"") | D115: =IF(ISNUMBER(D35)=TRUE,D35,"") | E115: =IF(ISNUMBER(E35)=TRUE,E35,"") | F115: =IF(ISNUMBER(F35)=TRUE,F35,"") | G115: =IF(ISTEXT(G35)=TRUE,G35,"") -> N/A | H115: =IFERROR(H35/$S$5,0) -> 0 | I115: =IFERROR(I35/$U$8,0) -> 0 | J115: =IFERROR(J35/$W$8,0) -> 0 | K115: =IFERROR(K35/$Y$8,0) -> 0 | L115: =IFERROR(L35/$AA$8,0) -> 0 | M115: =IFERROR(M35/$AC$8,0) -> 0 | N115: =IFERROR(N35/$AE$8,0) -> 0 | O115: =IFERROR(O35/$AG$8,0) -> 0
A116: =IF(ISTEXT(A36)=TRUE,A36,"") | B116: =IF(ISTEXT(B36)=TRUE,B36,"") | C116: =IF(ISNUMBER(C36)=TRUE,C36,"") | D116: =IF(ISNUMBER(D36)=TRUE,D36,"") | E116: =IF(ISNUMBER(E36)=TRUE,E36,"") | F116: =IF(ISNUMBER(F36)=TRUE,F36,"") | G116: =IF(ISTEXT(G36)=TRUE,G36,"") -> N/A | H116: =IFERROR(H36/$S$5,0) -> 0 | I116: =IFERROR(I36/$U$8,0) -> 0 | J116: =IFERROR(J36/$W$8,0) -> 0 | K116: =IFERROR(K36/$Y$8,0) -> 0 | L116: =IFERROR(L36/$AA$8,0) -> 0 | M116: =IFERROR(M36/$AC$8,0) -> 0 | N116: =IFERROR(N36/$AE$8,0) -> 0 | O116: =IFERROR(O36/$AG$8,0) -> 0
A117: =IF(ISTEXT(A37)=TRUE,A37,"") | B117: =IF(ISTEXT(B37)=TRUE,B37,"") | C117: =IF(ISNUMBER(C37)=TRUE,C37,"") | D117: =IF(ISNUMBER(D37)=TRUE,D37,"") | E117: =IF(ISNUMBER(E37)=TRUE,E37,"") | F117: =IF(ISNUMBER(F37)=TRUE,F37,"") | G117: =IF(ISTEXT(G37)=TRUE,G37,"") -> N/A | H117: =IFERROR(H37/$S$5,0) -> 0 | I117: =IFERROR(I37/$U$8,0) -> 0 | J117: =IFERROR(J37/$W$8,0) -> 0 | K117: =IFERROR(K37/$Y$8,0) -> 0 | L117: =IFERROR(L37/$AA$8,0) -> 0 | M117: =IFERROR(M37/$AC$8,0) -> 0 | N117: =IFERROR(N37/$AE$8,0) -> 0 | O117: =IFERROR(O37/$AG$8,0) -> 0
A118: =IF(ISTEXT(A38)=TRUE,A38,"") | B118: =IF(ISTEXT(B38)=TRUE,B38,"") | C118: =IF(ISNUMBER(C38)=TRUE,C38,"") | D118: =IF(ISNUMBER(D38)=TRUE,D38,"") | E118: =IF(ISNUMBER(E38)=TRUE,E38,"") | F118: =IF(ISNUMBER(F38)=TRUE,F38,"") | G118: =IF(ISTEXT(G38)=TRUE,G38,"") -> N/A | H118: =IFERROR(H38/$S$5,0) -> 0 | I118: =IFERROR(I38/$U$8,0) -> 0 | J118: =IFERROR(J38/$W$8,0) -> 0 | K118: =IFERROR(K38/$Y$8,0) -> 0 | L118: =IFERROR(L38/$AA$8,0) -> 0 | M118: =IFERROR(M38/$AC$8,0) -> 0 | N118: =IFERROR(N38/$AE$8,0) -> 0 | O118: =IFERROR(O38/$AG$8,0) -> 0
A119: =IF(ISTEXT(A39)=TRUE,A39,"") | B119: =IF(ISTEXT(B39)=TRUE,B39,"") | C119: =IF(ISNUMBER(C39)=TRUE,C39,"") | D119: =IF(ISNUMBER(D39)=TRUE,D39,"") | E119: =IF(ISNUMBER(E39)=TRUE,E39,"") | F119: =IF(ISNUMBER(F39)=TRUE,F39,"") | G119: =IF(ISTEXT(G39)=TRUE,G39,"") -> N/A | H119: =IFERROR(H39/$S$5,0) -> 0 | I119: =IFERROR(I39/$U$8,0) -> 0 | J119: =IFERROR(J39/$W$8,0) -> 0 | K119: =IFERROR(K39/$Y$8,0) -> 0 | L119: =IFERROR(L39/$AA$8,0) -> 0 | M119: =IFERROR(M39/$AC$8,0) -> 0 | N119: =IFERROR(N39/$AE$8,0) -> 0 | O119: =IFERROR(O39/$AG$8,0) -> 0
A120: =IF(ISTEXT(A40)=TRUE,A40,"") | B120: =IF(ISTEXT(B40)=TRUE,B40,"") | C120: =IF(ISNUMBER(C40)=TRUE,C40,"") | D120: =IF(ISNUMBER(D40)=TRUE,D40,"") | E120: =IF(ISNUMBER(E40)=TRUE,E40,"") | F120: =IF(ISNUMBER(F40)=TRUE,F40,"") | G120: =IF(ISTEXT(G40)=TRUE,G40,"") -> N/A | H120: =IFERROR(H40/$S$5,0) -> 0 | I120: =IFERROR(I40/$U$8,0) -> 0 | J120: =IFERROR(J40/$W$8,0) -> 0 | K120: =IFERROR(K40/$Y$8,0) -> 0 | L120: =IFERROR(L40/$AA$8,0) -> 0 | M120: =IFERROR(M40/$AC$8,0) -> 0 | N120: =IFERROR(N40/$AE$8,0) -> 0 | O120: =IFERROR(O40/$AG$8,0) -> 0
A121: =IF(ISTEXT(A41)=TRUE,A41,"") | B121: =IF(ISTEXT(B41)=TRUE,B41,"") | C121: =IF(ISNUMBER(C41)=TRUE,C41,"") | D121: =IF(ISNUMBER(D41)=TRUE,D41,"") | E121: =IF(ISNUMBER(E41)=TRUE,E41,"") | F121: =IF(ISNUMBER(F41)=TRUE,F41,"") | G121: =IF(ISTEXT(G41)=TRUE,G41,"") -> N/A | H121: =IFERROR(H41/$S$5,0) -> 0 | I121: =IFERROR(I41/$U$8,0) -> 0 | J121: =IFERROR(J41/$W$8,0) -> 0 | K121: =IFERROR(K41/$Y$8,0) -> 0 | L121: =IFERROR(L41/$AA$8,0) -> 0 | M121: =IFERROR(M41/$AC$8,0) -> 0 | N121: =IFERROR(N41/$AE$8,0) -> 0 | O121: =IFERROR(O41/$AG$8,0) -> 0
... A123: =IF(ISTEXT(A43)=TRUE,A43,"") | B123: =IF(ISTEXT(B43)=TRUE,B43,"") | C123: =IF(ISNUMBER(C43)=TRUE,C43,"") | D123: =IF(ISNUMBER(D43)=TRUE,D43,"") | E123: =IF(ISNUMBER(E43)=TRUE,E43,"") | F123: =IF(ISNUMBER(F43)=TRUE,F43,"") | G123: =IF(ISTEXT(G43)=TRUE,G43,"") -> N/A | H123: =IFERROR(H43/$S$5,0) -> 0 | I123: =IFERROR(I43/$U$8,0) -> 0 | J123: =IFERROR(J43/$W$8,0) -> 0 | K123: =IFERROR(K43/$Y$8,0) -> 0 | L123: =IFERROR(L43/$AA$8,0) -> 0 | M123: =IFERROR(M43/$AC$8,0) -> 0 | N123: =IFERROR(N43/$AE$8,0) -> 0 | O123: =IFERROR(O43/$AG$8,0) -> 0
...

Sheet EEM Lifetimes
A1: Category | B1: Measure | C1: Measure Lifetime Ranges | D1: Current Averages | E1: Source 1 | F1: Source 2 | G1: Source 3 | L1: GENERAL SOURCE
A2: ADHESIVES, CAULK & PAINTS | B2: Caulking (interior & exterior) | C2: 10 | D2: 10
A3: ADHESIVES, CAULK & PAINTS | B3: Construction Glue | C3: 20+ | D3: 20 | L3: AVERAGE BUILDING LIFESPAN ASSUMPTION
A4: ADHESIVES, CAULK & PAINTS | B4: Roofing Adhesives/Cements | C4: 15+ | D4: 15
A5: ADHESIVES, CAULK & PAINTS | B5: Sealants | C5: 8 | D5: 8
A6: APPLIANCES | B6: Air Conditioner (window) | C6: 5 to 7 | D6: 10 | E6: 7 to 12 | F6: 15 yrs | L6: Average building lifespan = | M6: 63 | N6: SOURCE
A7: APPLIANCES | B7: Dehumidifier | C7: 8 | D7: 8
A8: APPLIANCES | B8: Dishwasher | C8: 9 | D8: 12 | E8: 9 to 11 | F8: 15
A9: APPLIANCES | B9: Dryer (clothes) | C9: 13 | D9: 13 | E9: 12 to 13 | F9: 8 to 18
A10: APPLIANCES | B10: Electric Range | C10: 13 to 15 | D10: 14 | E10: 13 to 16 | F10: 17 | G10: Commercial 12
A11: APPLIANCES | B11: Freezer | C11: 10 to 20 | D11: 15 | E11: 15
A12: APPLIANCES | B12: Gas Oven | C12: 10 to 18 | D12: 14
A13: APPLIANCES | B13: Gas Range | C13: 15 to 17 | D13: 15 | E13: 15 to 18 | F13: 15 | G13: Commercial 12
A14: APPLIANCES | B14: Hand Dryer | C14: 10 to 12 | D14: 11
A15: APPLIANCES | B15: Humidifier (portable) | C15: 8 | D15: 8
A16: APPLIANCES | B16: Microwave Oven | C16: 9 | D16: 9 | E16: 9 to 10
A17: APPLIANCES | B17: Range/Oven Hood | C17: 14 | D17: 14
A18: APPLIANCES | B18: Refrigerator | C18: 12 | D18: 14 | E18: SOURCE | F18: 15
A19: APPLIANCES | B19: Swamp Cooler | C19: 5 to 15 | D19: 10 | E19: 10 to 12
A20: APPLIANCES | B20: Washing Machine | C20: 5 to 15 | D20: 14 | E20: 11 | F20: 6 to 17
A21: DOORS | B21: Fiberglass (exterior) | C21: ='[1]Building Lifespan'!$B$2 -> 63 | D21: =$M$6 -> 63
A22: DOORS | B22: Fire-Rated Steel (exterior) | C22: 100+ | D22: =$M$6 -> 63
A23: DOORS | B23: Screen (exterior) | C23: 30 | D23: 30
A24: DOORS | B24: Sliding Glass/Patio (exterior) | C24: 20 | D24: 20
A25: DOORS | B25: Vinyl (exterior) | C25: 20 | D25: 20
A26: DOORS | B26: Wood (exterior) | C26: ='[1]Building Lifespan'!$B$2 -> 63 | D26: =$M$6 -> 63
A27: ELECTRICAL | B27: Fixtures | C27: 40 | D27: 40
A28: ELECTRICAL | B28: Lighting Controls | C28: 35 | D28: 35
A29: ELECTRICAL | B29: Residential Propane Backup Generators | C29: 12 | D29: 12
A30: ELECTRICAL | B30: Solar Panels | C30: 25 | D30: 25
A31: ELECTRICAL | B31: Solar System Batteries | C31: 3 to 12 | D31: 9 | E31: 7 to 10 | F31: 5 to 15
A32: ELECTRICAL | B32: Wind Turbine Generators | C32: 20 | D32: 20
A33: HVAC | B33: Air Conditioner (central) | C33: 7 to 15 | D33: 14 | E33: 15 to 20 | F33: 6 to 13 | G33: 21
A34: HVAC | B34: Air Exchanger | C34: 15 | D34: 15
A35: HVAC | B35: ASHP | C35: 15 | D35: 15 | E35: SOURCE
A36: HVAC | B36: Attic Fan | C36: 20 | D36: 20
A37: HVAC | B37: Boiler | C37: 40 | D37: 40
A38: HVAC | B38: Boiler- Electric | C38: 15 | D38: 15
A39: HVAC | B39: Boiler- Gas or oil | C39: 40 | D39: 33 | E39: 25 to 30
A40: HVAC | B40: Burner | C40: 10+ | D40: 10
A41: HVAC | B41: Centrifugal Chillers (Water-Cooled) | C41: 25 | D41: 25
A42: HVAC | B42: Commercial Electric Resistance Storage Water Heaters | C42: 12 | D42: 12
A43: HVAC | B43: Commercial Oil-Fired Storage Water Heaters | C43: 13 | D43: 13
A44: HVAC | B44: Compressor Line | C44: 5 | D44: 5 | E44: TRM
A45: HVAC | B45: Condenser | C45: 8 to 20 | D45: 14
A46: HVAC | B46: Condensing Boiler/Furnace | C46: 17 | D46: 17 | E46: SOURCE | F46: 15 to 20
A47: HVAC | B47: Dampers | C47: 20+ | D47: 20
A48: HVAC | B48: Dehumidifier | C48: 8 | D48: 8
A49: HVAC | B49: Diffusers, Grilles and Registers | C49: 25 | D49: 25
A50: HVAC | B50: Ducting | C50: ='[1]Building Lifespan'!$B$2 -> 63 | D50: =$M$6 -> 63
A51: HVAC | B51: Electric Radiant Heater | C51: 40 | D51: 40
A52: HVAC | B52: Electric Resistance Heater | C52: 18 | D52: 18
A53: HVAC | B53: Evaporative Cooler | C53: 15 to 25 | D53: 20
A54: HVAC | B54: Exhaust Fans | C54: 10 | D54: 10
A55: HVAC | B55: Furnace- gas or oil fired | C55: 23 | D55: 23
A56: HVAC | B56: GSHP | C56: 20 | D56: 20 | E56: SOURCE | F56: 8 to 21
A57: HVAC | B57: Heat Exchanger | C57: 10 to 15 | D57: 13
A58: HVAC | B58: Heat-Recovery Ventilator | C58: 20 | D58: 20
A59: HVAC | B59: Hot-Water and Steam-Radiant Boiler | C59: 40 | D59: 40
A60: HVAC | B60: HPWH | C60: 15 | D60: 15 | E60: SOURCE | F60: 13- 15
A61: HVAC | B61: Humidifier | C61: 12 | D61: 12
A62: HVAC | B62: Induction and Fan-Coil Units | C62: 10 to 15 | D62: 13
A63: HVAC | B63: Infrared Heater | C63: 17 | D63: 17 | E63: TRM
A64: HVAC | B64: Packaged Terminal AC | C64: 8 | D64: 8
A65: HVAC | B65: Packaged Terminal Heat Pump | C65: 8 | D65: 8
A66: HVAC | B66: Programmable Tstat | C66: 10 | D66: 10 | E66: SOURCE
A67: HVAC | B67: Reciprocating Chillers (Air-Cooled Only) | C67: 20 | D67: 20
A68: HVAC | B68: Rooftop Heat Pump | C68: 21 | D68: 21
A69: HVAC | B69: Screw, Scroll Chillers (Air-Cooled Only) | C69: 20 | D69: 20
A70: HVAC | B70: Thermostats | C70: 35 | D70: 35
A71: HVAC | B71: Ventilator | C71: 7 | D71: 7
A72: HVAC | B72: Water Heater- Gas/ Electric/ Oil fired Residential | C72: 13 to 15 | D72: 14 | E72: Source
A73: INSULATION & INFILTRATION BARRIERS | B73: Batts/Rolls | C73: ='[1]Building Lifespan'!$B$2 -> 63 | D73: =$M$6 -> 63
A74: INSULATION & INFILTRATION BARRIERS | B74: Black Paper (felt paper) | C74: 15 to 30 | D74: 23
A75: INSULATION & INFILTRATION BARRIERS | B75: Cellulose | C75: ='[1]Building Lifespan'!$B$2 -> 63 | D75: =$M$6 -> 63
A76: INSULATION & INFILTRATION BARRIERS | B76: Duct Insulation | C76: 15 | D76: 15 | E76: SOURCE
A77: INSULATION & INFILTRATION BARRIERS | B77: Fiberglass | C77: ='[1]Building Lifespan'!$B$2 -> 63 | D77: =$M$6 -> 63
A78: INSULATION & INFILTRATION BARRIERS | B78: Foamboard | C78: ='[1]Building Lifespan'!$B$2 -> 63 | D78: =$M$6 -> 63
A79: INSULATION & INFILTRATION BARRIERS | B79: Housewrap | C79: ='[1]Building Lifespan'!$B$2 -> 63 | D79: =$M$6 -> 63
A80: INSULATION & INFILTRATION BARRIERS | B80: Liquid-Applied Membrane | C80: 50 | D80: 50
A81: INSULATION & INFILTRATION BARRIERS | B81: Loose-Fill | C81: ='[1]Building Lifespan'!$B$2 -> 63 | D81: =$M$6 -> 63
A82: INSULATION & INFILTRATION BARRIERS | B82: Pipe Insulate | C82: 15 | D82: 15 | E82: SOURCE
A83: INSULATION & INFILTRATION BARRIERS | B83: Rockwool | C83: ='[1]Building Lifespan'!$B$2 -> 63 | D83: =$M$6 -> 63
A84: INSULATION & INFILTRATION BARRIERS | B84: Wrap Tape | C84: ='[1]Building Lifespan'!$B$2 -> 63 | D84: =$M$6 -> 63
A85: ROOFING | B85: EPDM (ethylene propylene diene monomer) Rubber | C85: 20 | D85: 20
A86: WINDOWS | B86: Aluminum/Aluminum-Clad | C86: 20 | D86: 20
A87: WINDOWS | B87: Double-Pane | C87: 8 to 20 | D87: 14 | F87: 20 years per energy star
A88: WINDOWS | B88: Skylights | C88: 15 | D88: 15
A89: WINDOWS | B89: Vinyl/Fiberglass Windows | C89: 30 | D89: 30

Sheet In-House Pricing
A1: BUILDING SHELL MEASURES | L1: MECHANICAL MEASURES | W1: ELECTRICAL MEASURES | AH1: RENEWABLE ENERGY MEASURES
B3: EEM | C3: B1 | D3: =#REF! -> #REF! | M3: EEM | N3: M1 | O3: =#REF! -> #REF! | X3: EEM | Y3: E1 | Z3: =#REF! -> #REF! | AI3: EEM | AJ3: R1 | AK3: =#REF! -> #REF!
A4: ITEMS REQ. | B4: DIV. | C4: SECT. | D4: PG.# | F4: QTY. | G4: UNIT | H4: MAT. | I4: LABOR | J4: TOTAL | L4: ITEMS REQ. | M4: DIV. | N4: SECT. | O4: PG.# | Q4: QTY. | R4: UNIT | S4: MAT. | T4: LABOR | U4: TOTAL | W4: ITEMS REQ. | X4: DIV. | Y4: SECT. | Z4: PG.# | AB4: QTY. | AC4: UNIT | AD4: MAT. | AE4: LABOR | AF4: TOTAL | AH4: ITEMS REQ. | AI4: DIV. | AJ4: SECT. | AK4: PG.# | AM4: QTY. | AN4: UNIT | AO4: MAT. | AP4: LABOR | AQ4: TOTAL
A5: Remove ceiling tile at perimeter of retail store | B5: 9 | C5: 1200 | D5: 288 | F5: 1800 | G5: sf | I5: 0.35 | J5: =F5*(H5+I5) -> 630 | L5: Remove appropriate ceiling tiles | M5: 9 | N5: 1200 | O5: 288 | Q5: 80 | R5: sf | T5: 0.35 | U5: =Q5*(S5+T5) -> 28 | AF5: =AB5*(AD5+AE5) -> 0 | AQ5: =AM5*(AO5+AP5) -> 0
A6: Surgically air seal at roof to wall connection | F6: 1 | G6: LS | H6: 2800 | I6: 2200 | J6: =F6*(H6+I6) -> 5000 | L6: Demo existing duct runs (35"-0" each) | M6: 15 | N6: 1200 | O6: 482 | Q6: =(4+4)*20 -> 160 | R6: lf | T6: 2.12 | U6: =Q6*(S6+T6) -> 339.2 | AF6: =AB6*(AD6+AE6) -> 0 | AQ6: =AM6*(AO6+AP6) -> 0
A7: Replace ceiling tile at perimeter | B7: 9 | C7: 1200 | D7: 288 | F7: 1800 | G7: sf | I7: 0.35 | J7: =F7*(H7+I7) -> 630 | L7: Install duct runs (35"-0" each) | M7: 15 | N7: 1660 | O7: 493 | Q7: =(3*4)*20 -> 240 | R7: lf | S7: 3.17 | T7: 5.9 | U7: =Q7*(S7+T7) -> 2176.8 | AF7: =AB7*(AD7+AE7) -> 0 | AQ7: =AM7*(AO7+AP7) -> 0
J8: =F8*(H8+I8) -> 0 | L8: Install diffusers (24"x24") | M8: 15 | N8: 5280 | O8: 499 | Q8: =3*4 -> 12 | R8: ea | S8: 92 | T8: 35.5 | U8: =Q8*(S8+T8) -> 1530 | AF8: =AB8*(AD8+AE8) -> 0 | AQ8: =AM8*(AO8+AP8) -> 0
J9: =F9*(H9+I9) -> 0 | L9: Reinstall appropriate ceiling tiles | M9: 9 | N9: 1200 | O9: 288 | Q9: 80 | R9: sf | T9: 0.35 | U9: =Q9*(S9+T9) -> 28 | AF9: =AB9*(AD9+AE9) -> 0 | AQ9: =AM9*(AO9+AP9) -> 0
J10: =F10*(H10+I10) -> 0 | U10: =Q10*(S10+T10) -> 0 | AF10: =AB10*(AD10+AE10) -> 0 | AQ10: =AM10*(AO10+AP10) -> 0
J11: =F11*(H11+I11) -> 0 | U11: =Q11*(S11+T11) -> 0 | AF11: =AB11*(AD11+AE11) -> 0 | AQ11: =AM11*(AO11+AP11) -> 0
J12: =F12*(H12+I12) -> 0 | U12: =Q12*(S12+T12) -> 0 | AF12: =AB12*(AD12+AE12) -> 0 | AQ12: =AM12*(AO12+AP12) -> 0
I13: TOTAL | J13: =SUM(J5:J12) -> 6260 | T13: TOTAL | U13: =SUM(U5:U12) -> 4102 | AE13: TOTAL | AF13: =SUM(AF5:AF12) -> 0 | AP13: TOTAL | AQ13: =SUM(AQ5:AQ12) -> 0
B15: EEM | C15: B2 | D15: =#REF! -> #REF! | M15: EEM | N15: M2 | O15: =#REF! -> #REF! | X15: EEM | Y15: E2 | Z15: =#REF! -> #REF! | AI15: EEM | AJ15: E2 | AK15: =#REF! -> #REF!
A16: ITEMS REQ. | B16: DIV. | C16: SECT. | D16: PG.# | F16: QTY. | G16: UNIT | H16: MAT. | I16: LABOR | J16: TOTAL | L16: ITEMS REQ. | M16: DIV. | N16: SECT. | O16: PG.# | Q16: QTY. | R16: UNIT | S16: MAT. | T16: LABOR | U16: TOTAL | W16: ITEMS REQ. | X16: DIV. | Y16: SECT. | Z16: PG.# | AB16: QTY. | AC16: UNIT | AD16: MAT. | AE16: LABOR | AF16: TOTAL | AH16: ITEMS REQ. | AI16: DIV. | AJ16: SECT. | AK16: PG.# | AM16: QTY. | AN16: UNIT | AO16: MAT. | AP16: LABOR | AQ16: TOTAL
A17: Clean 10" diameter area around RTU | F17: 785.4 | G17: sf | I17: 0.86 | J17: =F17*(H17+I17) -> 675.444 | L17: Remove appropriate ceiling tiles | M17: 9 | N17: 1200 | O17: 288 | Q17: 40 | R17: sf | T17: 0.35 | U17: =Q17*(S17+T17) -> 14 | AF17: =AB17*(AD17+AE17) -> 0 | AQ17: =AM17*(AO17+AP17) -> 0
A18: Paint 10' diameter w/ cool roof coating | F18: =(3.1416*25)*10 -> 785.4 | G18: sf | H18: 7.5 | I18: 0.86 | J18: =F18*(H18+I18) -> 6565.944 | L18: Install duct runs (35"-0" each) | M18: 15 | N18: 1660 | O18: 493 | Q18: =35*4 -> 140 | R18: lf | S18: 3.17 | T18: 5.9 | U18: =Q18*(S18+T18) -> 1269.8 | AF18: =AB18*(AD18+AE18) -> 0 | AQ18: =AM18*(AO18+AP18) -> 0
J19: =F19*(H19+I19) -> 0 | L19: Install diffusers (24"x24") | M19: 15 | N19: 5280 | O19: 499 | Q19: =3*4 -> 12 | R19: ea | S19: 92 | T19: 35.5 | U19: =Q19*(S19+T19) -> 1530 | AF19: =AB19*(AD19+AE19) -> 0 | AQ19: =AM19*(AO19+AP19) -> 0
J20: =F20*(H20+I20) -> 0 | L20: Reinstall appropriate ceiling tiles | M20: 9 | N20: 1200 | O20: 288 | Q20: 40 | R20: sf | T20: 0.35 | U20: =Q20*(S20+T20) -> 14 | AF20: =AB20*(AD20+AE20) -> 0 | AQ20: =AM20*(AO20+AP20) -> 0
J21: =F21*(H21+I21) -> 0 | L21: Install fans | M21: 15 | N21: 7560 | O21: 495 | Q21: 4 | R21: ea | S21: 1125 | T21: 188 | U21: =Q21*(S21+T21) -> 5252 | AF21: =AB21*(AD21+AE21) -> 0 | AQ21: =AM21*(AO21+AP21) -> 0
J22: =F22*(H22+I22) -> 0 | L22: Install dampers | M22: 15 | N22: 6020 | O22: 492 | Q22: 4 | R22: ea | S22: 36.5 | T22: 22 | U22: =Q22*(S22+T22) -> 234 | AF22: =AB22*(AD22+AE22) -> 0 | AQ22: =AM22*(AO22+AP22) -> 0
J23: =F23*(H23+I23) -> 0 | L23: Install louvers | M23: 15 | N23: 3200 | O23: 499 | Q23: 4 | R23: ea | S23: 41.5 | T23: 14.05 | U23: =Q23*(S23+T23) -> 222.2 | AF23: =AB23*(AD23+AE23) -> 0 | AQ23: =AM23*(AO23+AP23) -> 0
J24: =F24*(H24+I24) -> 0 | U24: =Q24*(S24+T24) -> 0 | AF24: =AB24*(AD24+AE24) -> 0 | AQ24: =AM24*(AO24+AP24) -> 0
I25: TOTAL | J25: =SUM(J17:J24) -> 7241.388 | T25: TOTAL | U25: =SUM(U17:U24) -> 8536 | AE25: TOTAL | AF25: =SUM(AF17:AF24) -> 0 | AP25: TOTAL | AQ25: =SUM(AQ17:AQ24) -> 0
B27: EEM | C27: B3 | D27: =#REF! -> #REF! | M27: EEM | N27: M3 | O27: =#REF! -> #REF! | X27: EEM | Y27: E3 | Z27: =#REF! -> #REF! | AI27: EEM | AJ27: E3 | AK27: =#REF! -> #REF!
A28: ITEMS REQ. | B28: DIV. | C28: SECT. | D28: PG.# | F28: QTY. | G28: UNIT | H28: MAT. | I28: LABOR | J28: TOTAL | L28: ITEMS REQ. | M28: DIV. | N28: SECT. | O28: PG.# | Q28: QTY. | R28: UNIT | S28: MAT. | T28: LABOR | U28: TOTAL | W28: ITEMS REQ. | X28: DIV. | Y28: SECT. | Z28: PG.# | AB28: QTY. | AC28: UNIT | AD28: MAT. | AE28: LABOR | AF28: TOTAL | AH28: ITEMS REQ. | AI28: DIV. | AJ28: SECT. | AK28: PG.# | AM28: QTY. | AN28: UNIT | AO28: MAT. | AP28: LABOR | AQ28: TOTAL
J29: =F29*(H29+I29) -> 0 | U29: =Q29*(S29+T29) -> 0 | AF29: =AB29*(AD29+AE29) -> 0 | AQ29: =AM29*(AO29+AP29) -> 0
J30: =F30*(H30+I30) -> 0 | U30: =Q30*(S30+T30) -> 0 | AF30: =AB30*(AD30+AE30) -> 0 | AQ30: =AM30*(AO30+AP30) -> 0
J31: =F31*(H31+I31) -> 0 | U31: =Q31*(S31+T31) -> 0 | AF31: =AB31*(AD31+AE31) -> 0 | AQ31: =AM31*(AO31+AP31) -> 0
J32: =F32*(H32+I32) -> 0 | U32: =Q32*(S32+T32) -> 0 | AF32: =AB32*(AD32+AE32) -> 0 | AQ32: =AM32*(AO32+AP32) -> 0
J33: =F33*(H33+I33) -> 0 | U33: =Q33*(S33+T33) -> 0 | AF33: =AB33*(AD33+AE33) -> 0 | AQ33: =AM33*(AO33+AP33) -> 0
J34: =F34*(H34+I34) -> 0 | U34: =Q34*(S34+T34) -> 0 | AF34: =AB34*(AD34+AE34) -> 0 | AQ34: =AM34*(AO34+AP34) -> 0
J35: =F35*(H35+I35) -> 0 | U35: =Q35*(S35+T35) -> 0 | AF35: =AB35*(AD35+AE35) -> 0 | AQ35: =AM35*(AO35+AP35) -> 0
J36: =F36*(H36+I36) -> 0 | U36: =Q36*(S36+T36) -> 0 | AF36: =AB36*(AD36+AE36) -> 0 | AQ36: =AM36*(AO36+AP36) -> 0
I37: TOTAL | J37: =SUM(J29:J36) -> 0 | T37: TOTAL | U37: =SUM(U29:U36) -> 0 | AE37: TOTAL | AF37: =SUM(AF29:AF36) -> 0 | AP37: TOTAL | AQ37: =SUM(AQ29:AQ36) -> 0
B39: EEM | C39: B4 | D39: =#REF! -> #REF! | M39: EEM | N39: M4 | O39: =#REF! -> #REF! | X39: EEM | Y39: E4 | Z39: =#REF! -> #REF! | AI39: EEM | AJ39: E4 | AK39: =#REF! -> #REF!
A40: ITEMS REQ. | B40: DIV. | C40: SECT. | D40: PG.# | F40: QTY. | G40: UNIT | H40: MAT. | I40: LABOR | J40: TOTAL | L40: ITEMS REQ. | M40: DIV. | N40: SECT. | O40: PG.# | Q40: QTY. | R40: UNIT | S40: MAT. | T40: LABOR | U40: TOTAL | W40: ITEMS REQ. | X40: DIV. | Y40: SECT. | Z40: PG.# | AB40: QTY. | AC40: UNIT | AD40: MAT. | AE40: LABOR | AF40: TOTAL | AH40: ITEMS REQ. | AI40: DIV. | AJ40: SECT. | AK40: PG.# | AM40: QTY. | AN40: UNIT | AO40: MAT. | AP40: LABOR | AQ40: TOTAL
J41: =F41*(H41+I41) -> 0 | U41: =Q41*(S41+T41) -> 0 | AF41: =AB41*(AD41+AE41) -> 0 | AQ41: =AM41*(AO41+AP41) -> 0
J42: =F42*(H42+I42) -> 0 | U42: =Q42*(S42+T42) -> 0 | AF42: =AB42*(AD42+AE42) -> 0 | AQ42: =AM42*(AO42+AP42) -> 0
J43: =F43*(H43+I43) -> 0 | U43: =Q43*(S43+T43) -> 0 | AF43: =AB43*(AD43+AE43) -> 0 | AQ43: =AM43*(AO43+AP43) -> 0
J44: =F44*(H44+I44) -> 0 | U44: =Q44*(S44+T44) -> 0 | AF44: =AB44*(AD44+AE44) -> 0 | AQ44: =AM44*(AO44+AP44) -> 0
J45: =F45*(H45+I45) -> 0 | U45: =Q45*(S45+T45) -> 0 | AF45: =AB45*(AD45+AE45) -> 0 | AQ45: =AM45*(AO45+AP45) -> 0
J46: =F46*(H46+I46) -> 0 | U46: =Q46*(S46+T46) -> 0 | AF46: =AB46*(AD46+AE46) -> 0 | AQ46: =AM46*(AO46+AP46) -> 0
J47: =F47*(H47+I47) -> 0 | U47: =Q47*(S47+T47) -> 0 | AF47: =AB47*(AD47+AE47) -> 0 | AQ47: =AM47*(AO47+AP47) -> 0
J48: =F48*(H48+I48) -> 0 | U48: =Q48*(S48+T48) -> 0 | AF48: =AB48*(AD48+AE48) -> 0 | AQ48: =AM48*(AO48+AP48) -> 0
I49: TOTAL | J49: =SUM(J41:J48) -> 0 | T49: TOTAL | U49: =SUM(U41:U48) -> 0 | AE49: TOTAL | AF49: =SUM(AF41:AF48) -> 0 | AP49: TOTAL | AQ49: =SUM(AQ41:AQ48) -> 0
B51: EEM | C51: B5 | M51: EEM | N51: M5 | X51: EEM | Y51: E5 | AI51: EEM | AJ51: E5
A52: ITEMS REQ. | B52: DIV. | C52: SECT. | D52: PG.# | F52: QTY. | G52: UNIT | H52: MAT. | I52: LABOR | J52: TOTAL | L52: ITEMS REQ. | M52: DIV. | N52: SECT. | O52: PG.# | Q52: QTY. | R52: UNIT | S52: MAT. | T52: LABOR | U52: TOTAL | W52: ITEMS REQ. | X52: DIV. | Y52: SECT. | Z52: PG.# | AB52: QTY. | AC52: UNIT | AD52: MAT. | AE52: LABOR | AF52: TOTAL | AH52: ITEMS REQ. | AI52: DIV. | AJ52: SECT. | AK52: PG.# | AM52: QTY. | AN52: UNIT | AO52: MAT. | AP52: LABOR | AQ52: TOTAL
J53: =F53*(H53+I53) -> 0 | U53: =Q53*(S53+T53) -> 0 | AF53: =AB53*(AD53+AE53) -> 0 | AQ53: =AM53*(AO53+AP53) -> 0
J54: =F54*(H54+I54) -> 0 | U54: =Q54*(S54+T54) -> 0 | AF54: =AB54*(AD54+AE54) -> 0 | AQ54: =AM54*(AO54+AP54) -> 0
J55: =F55*(H55+I55) -> 0 | U55: =Q55*(S55+T55) -> 0 | AF55: =AB55*(AD55+AE55) -> 0 | AQ55: =AM55*(AO55+AP55) -> 0
J56: =F56*(H56+I56) -> 0 | U56: =Q56*(S56+T56) -> 0 | AF56: =AB56*(AD56+AE56) -> 0 | AQ56: =AM56*(AO56+AP56) -> 0
J57: =F57*(H57+I57) -> 0 | U57: =Q57*(S57+T57) -> 0 | AF57: =AB57*(AD57+AE57) -> 0 | AQ57: =AM57*(AO57+AP57) -> 0
J58: =F58*(H58+I58) -> 0 | U58: =Q58*(S58+T58) -> 0 | AF58: =AB58*(AD58+AE58) -> 0 | AQ58: =AM58*(AO58+AP58) -> 0
J59: =F59*(H59+I59) -> 0 | U59: =Q59*(S59+T59) -> 0 | AF59: =AB59*(AD59+AE59) -> 0 | AQ59: =AM59*(AO59+AP59) -> 0
J60: =F60*(H60+I60) -> 0 | U60: =Q60*(S60+T60) -> 0 | AF60: =AB60*(AD60+AE60) -> 0 | AQ60: =AM60*(AO60+AP60) -> 0
I61: TOTAL | J61: =SUM(J53:J60) -> 0 | T61: TOTAL | U61: =SUM(U53:U60) -> 0 | AE61: TOTAL | AF61: =SUM(AF53:AF60) -> 0 | AP61: TOTAL | AQ61: =SUM(AQ53:AQ60) -> 0
B63: EEM | C63: B6 | M63: EEM | N63: M6 | X63: EEM | Y63: E6 | AI63: EEM | AJ63: E6
A64: ITEMS REQ. | B64: DIV. | C64: SECT. | D64: PG.# | F64: QTY. | G64: UNIT | H64: MAT. | I64: LABOR | J64: TOTAL | L64: ITEMS REQ. | M64: DIV. | N64: SECT. | O64: PG.# | Q64: QTY. | R64: UNIT | S64: MAT. | T64: LABOR | U64: TOTAL | W64: ITEMS REQ. | X64: DIV. | Y64: SECT. | Z64: PG.# | AB64: QTY. | AC64: UNIT | AD64: MAT. | AE64: LABOR | AF64: TOTAL | AH64: ITEMS REQ. | AI64: DIV. | AJ64: SECT. | AK64: PG.# | AM64: QTY. | AN64: UNIT | AO64: MAT. | AP64: LABOR | AQ64: TOTAL
J65: =F65*(H65+I65) -> 0 | U65: =Q65*(S65+T65) -> 0 | AF65: =AB65*(AD65+AE65) -> 0 | AQ65: =AM65*(AO65+AP65) -> 0
J66: =F66*(H66+I66) -> 0 | U66: =Q66*(S66+T66) -> 0 | AF66: =AB66*(AD66+AE66) -> 0 | AQ66: =AM66*(AO66+AP66) -> 0
J67: =F67*(H67+I67) -> 0 | U67: =Q67*(S67+T67) -> 0 | AF67: =AB67*(AD67+AE67) -> 0 | AQ67: =AM67*(AO67+AP67) -> 0
J68: =F68*(H68+I68) -> 0 | U68: =Q68*(S68+T68) -> 0 | AF68: =AB68*(AD68+AE68) -> 0 | AQ68: =AM68*(AO68+AP68) -> 0
J69: =F69*(H69+I69) -> 0 | U69: =Q69*(S69+T69) -> 0 | AF69: =AB69*(AD69+AE69) -> 0 | AQ69: =AM69*(AO69+AP69) -> 0
J70: =F70*(H70+I70) -> 0 | U70: =Q70*(S70+T70) -> 0 | AF70: =AB70*(AD70+AE70) -> 0 | AQ70: =AM70*(AO70+AP70) -> 0
J71: =F71*(H71+I71) -> 0 | U71: =Q71*(S71+T71) -> 0 | AF71: =AB71*(AD71+AE71) -> 0 | AQ71: =AM71*(AO71+AP71) -> 0
J72: =F72*(H72+I72) -> 0 | U72: =Q72*(S72+T72) -> 0 | AF72: =AB72*(AD72+AE72) -> 0 | AQ72: =AM72*(AO72+AP72) -> 0
I73: TOTAL | J73: =SUM(J65:J72) -> 0 | T73: TOTAL | U73: =SUM(U65:U72) -> 0 | AE73: TOTAL | AF73: =SUM(AF65:AF72) -> 0 | AP73: TOTAL | AQ73: =SUM(AQ65:AQ72) -> 0
B75: EEM | C75: B7 | M75: EEM | N75: M7 | X75: EEM | Y75: E7 | AI75: EEM | AJ75: E7
A76: ITEMS REQ. | B76: DIV. | C76: SECT. | D76: PG.# | F76: QTY. | G76: UNIT | H76: MAT. | I76: LABOR | J76: TOTAL | L76: ITEMS REQ. | M76: DIV. | N76: SECT. | O76: PG.# | Q76: QTY. | R76: UNIT | S76: MAT. | T76: LABOR | U76: TOTAL | W76: ITEMS REQ. | X76: DIV. | Y76: SECT. | Z76: PG.# | AB76: QTY. | AC76: UNIT | AD76: MAT. | AE76: LABOR | AF76: TOTAL | AH76: ITEMS REQ. | AI76: DIV. | AJ76: SECT. | AK76: PG.# | AM76: QTY. | AN76: UNIT | AO76: MAT. | AP76: LABOR | AQ76: TOTAL
J77: =F77*(H77+I77) -> 0 | U77: =Q77*(S77+T77) -> 0 | AF77: =AB77*(AD77+AE77) -> 0 | AQ77: =AM77*(AO77+AP77) -> 0
J78: =F78*(H78+I78) -> 0 | U78: =Q78*(S78+T78) -> 0 | AF78: =AB78*(AD78+AE78) -> 0 | AQ78: =AM78*(AO78+AP78) -> 0
J79: =F79*(H79+I79) -> 0 | U79: =Q79*(S79+T79) -> 0 | AF79: =AB79*(AD79+AE79) -> 0 | AQ79: =AM79*(AO79+AP79) -> 0
J80: =F80*(H80+I80) -> 0 | U80: =Q80*(S80+T80) -> 0 | AF80: =AB80*(AD80+AE80) -> 0 | AQ80: =AM80*(AO80+AP80) -> 0
J81: =F81*(H81+I81) -> 0 | U81: =Q81*(S81+T81) -> 0 | AF81: =AB81*(AD81+AE81) -> 0 | AQ81: =AM81*(AO81+AP81) -> 0
J82: =F82*(H82+I82) -> 0 | U82: =Q82*(S82+T82) -> 0 | AF82: =AB82*(AD82+AE82) -> 0 | AQ82: =AM82*(AO82+AP82) -> 0
J83: =F83*(H83+I83) -> 0 | U83: =Q83*(S83+T83) -> 0 | AF83: =AB83*(AD83+AE83) -> 0 | AQ83: =AM83*(AO83+AP83) -> 0
J84: =F84*(H84+I84) -> 0 | U84: =Q84*(S84+T84) -> 0 | AF84: =AB84*(AD84+AE84) -> 0 | AQ84: =AM84*(AO84+AP84) -> 0
I85: TOTAL | J85: =SUM(J77:J84) -> 0 | T85: TOTAL | U85: =SUM(U77:U84) -> 0 | AE85: TOTAL | AF85: =SUM(AF77:AF84) -> 0 | AP85: TOTAL | AQ85: =SUM(AQ77:AQ84) -> 0
B87: EEM | C87: B8 | D87: =#REF! -> #REF! | M87: EEM | N87: M8 | O87: =#REF! -> #REF! | X87: EEM | Y87: E8 | Z87: =#REF! -> #REF! | AI87: EEM | AJ87: E8 | AK87: =#REF! -> #REF!
A88: ITEMS REQ. | B88: DIV. | C88: SECT. | D88: PG.# | F88: QTY. | G88: UNIT | H88: MAT. | I88: LABOR | J88: TOTAL | L88: ITEMS REQ. | M88: DIV. | N88: SECT. | O88: PG.# | Q88: QTY. | R88: UNIT | S88: MAT. | T88: LABOR | U88: TOTAL | W88: ITEMS REQ. | X88: DIV. | Y88: SECT. | Z88: PG.# | AB88: QTY. | AC88: UNIT | AD88: MAT. | AE88: LABOR | AF88: TOTAL | AH88: ITEMS REQ. | AI88: DIV. | AJ88: SECT. | AK88: PG.# | AM88: QTY. | AN88: UNIT | AO88: MAT. | AP88: LABOR | AQ88: TOTAL
J89: =F89*(H89+I89) -> 0 | U89: =Q89*(S89+T89) -> 0 | AF89: =AB89*(AD89+AE89) -> 0 | AQ89: =AM89*(AO89+AP89) -> 0
J90: =F90*(H90+I90) -> 0 | U90: =Q90*(S90+T90) -> 0 | AF90: =AB90*(AD90+AE90) -> 0 | AQ90: =AM90*(AO90+AP90) -> 0
J91: =F91*(H91+I91) -> 0 | U91: =Q91*(S91+T91) -> 0 | AF91: =AB91*(AD91+AE91) -> 0 | AQ91: =AM91*(AO91+AP91) -> 0
J92: =F92*(H92+I92) -> 0 | U92: =Q92*(S92+T92) -> 0 | AF92: =AB92*(AD92+AE92) -> 0 | AQ92: =AM92*(AO92+AP92) -> 0
J93: =F93*(H93+I93) -> 0 | U93: =Q93*(S93+T93) -> 0 | AF93: =AB93*(AD93+AE93) -> 0 | AQ93: =AM93*(AO93+AP93) -> 0
J94: =F94*(H94+I94) -> 0 | U94: =Q94*(S94+T94) -> 0 | AF94: =AB94*(AD94+AE94) -> 0 | AQ94: =AM94*(AO94+AP94) -> 0
J95: =F95*(H95+I95) -> 0 | U95: =Q95*(S95+T95) -> 0 | AF95: =AB95*(AD95+AE95) -> 0 | AQ95: =AM95*(AO95+AP95) -> 0
J96: =F96*(H96+I96) -> 0 | U96: =Q96*(S96+T96) -> 0 | AF96: =AB96*(AD96+AE96) -> 0 | AQ96: =AM96*(AO96+AP96) -> 0
I97: TOTAL | J97: =SUM(J89:J96) -> 0 | T97: TOTAL | U97: =SUM(U89:U96) -> 0 | AE97: TOTAL | AF97: =SUM(AF89:AF96) -> 0 | AP97: TOTAL | AQ97: =SUM(AQ89:AQ96) -> 0
B99: EEM | C99: B5 | D99: ='[2]Costing Summary'!C58 | M99: EEM | N99: M5 | O99: ='[2]Costing Summary'!C77 | X99: EEM | Y99: E5 | Z99: =#REF! -> #REF! | AI99: EEM | AJ99: R5 | AK99: =#REF! -> #REF!
A100: ITEMS REQ. | B100: DIV. | C100: SECT. | D100: PG.# | F100: QTY. | G100: UNIT | H100: MAT. | I100: LABOR | J100: TOTAL | L100: ITEMS REQ. | M100: DIV. | N100: SECT. | O100: PG.# | Q100: QTY. | R100: UNIT | S100: MAT. | T100: LABOR | U100: TOTAL | W100: ITEMS REQ. | X100: DIV. | Y100: SECT. | Z100: PG.# | AB100: QTY. | AC100: UNIT | AD100: MAT. | AE100: LABOR | AF100: TOTAL | AH100: ITEMS REQ. | AI100: DIV. | AJ100: SECT. | AK100: PG.# | AM100: QTY. | AN100: UNIT | AO100: MAT. | AP100: LABOR | AQ100: TOTAL
J101: =F101*(H101+I101) -> 0 | U101: =Q101*(S101+T101) -> 0 | AF101: =AB101*(AD101+AE101) -> 0 | AQ101: =AM101*(AO101+AP101) -> 0
J102: =F102*(H102+I102) -> 0 | U102: =Q102*(S102+T102) -> 0 | AF102: =AB102*(AD102+AE102) -> 0 | AQ102: =AM102*(AO102+AP102) -> 0
J103: =F103*(H103+I103) -> 0 | U103: =Q103*(S103+T103) -> 0 | AF103: =AB103*(AD103+AE103) -> 0 | AQ103: =AM103*(AO103+AP103) -> 0
J104: =F104*(H104+I104) -> 0 | U104: =Q104*(S104+T104) -> 0 | AF104: =AB104*(AD104+AE104) -> 0 | AQ104: =AM104*(AO104+AP104) -> 0
J105: =F105*(H105+I105) -> 0 | U105: =Q105*(S105+T105) -> 0 | AF105: =AB105*(AD105+AE105) -> 0 | AQ105: =AM105*(AO105+AP105) -> 0
J106: =F106*(H106+I106) -> 0 | U106: =Q106*(S106+T106) -> 0 | AF106: =AB106*(AD106+AE106) -> 0 | AQ106: =AM106*(AO106+AP106) -> 0
J107: =F107*(H107+I107) -> 0 | U107: =Q107*(S107+T107) -> 0 | AF107: =AB107*(AD107+AE107) -> 0 | AQ107: =AM107*(AO107+AP107) -> 0
J108: =F108*(H108+I108) -> 0 | U108: =Q108*(S108+T108) -> 0 | AF108: =AB108*(AD108+AE108) -> 0 | AQ108: =AM108*(AO108+AP108) -> 0
I109: TOTAL | J109: =SUM(J101:J108) -> 0 | T109: TOTAL | U109: =SUM(U101:U108) -> 0 | AE109: TOTAL | AF109: =SUM(AF101:AF108) -> 0 | AP109: TOTAL | AQ109: =SUM(AQ101:AQ108) -> 0
...

Sheet Interest Rate
A1: INTEREST RATE CALCULATOR
A3: STEP 1) FILL OUT THIS CALCULATOR | C3: NIST Energy Escalation Rate Calculator
A4: USING THE INFO IN THIS TABLE
A5: TO GET THE NOMINAL ESCALATION RATE | B5: Percent of Energy Cost Savings
B7: Coal | C7: Distillate Oil | D7: Electricity | E7: Natural Gas | F7: Residual
B8: 0 | C8: ='EEM Data Entry'!I160 -> #DIV/0! | D8: ='EEM Data Entry'!H160 -> #DIV/0! | E8: ='EEM Data Entry'!J160 -> #DIV/0! | F8: =1-(SUM(C8:E8)) -> #DIV/0!
B10: Inflation | C10: 0.034
A12: STEP 2) ENTER THE NOMINAL ESCALATION RATE HERE
A14: STEP 3) EDIT THE DISCOUNT RATE IF NEED (SHOULDN'T BE NECESSARY) | C14: 0.05
A15: Discount rate resource if needed
A17: INTEREST RATE CALCULATED = | B17: =((1+C14)/(1+C12))-1 -> 0.05

Sheet RESULTS
C1: COPY AND PASTE TABLES BELOW INTO REPORT AS APPROPRIATE, DELETE IRRELEVANT COLUMNS | V1: NO INCENTIVES
C3: ENVELOPE | I3: conversions | J3: 0.29307103 | K3: 0.0072790267 | L3: 0.01 | M3: 0.010928961 | V3: ENVELOPE | Y3: conversions | Z3: 0.29307103 | AA3: 0.0072790267 | AB3: 0.01 | AC3: 0.010928961
C5: EEM # | D5: Building Envelope Upgrades | E5: Capital Investment | F5: Estimated Incentive* | G5: Incentive Reference | H5: Estimated Net Cost | I5: Annual Energy Cost Savings | J5: Annual Electric Savings (kWh) | K5: Annual Oil Savings (Gal) | L5: Annual Nat. Gas Savings (Therms) | M5: Annual Propane Savings (Gal) | N5: Annual kBTU Savings | O5: Simple Payback (Years) | P5: IRR | Q5: NPV | V5: =C5 -> EEM # | W5: =D5 -> Building Envelope Upgrades | X5: =E5 -> Capital Investment | Y5: =I5 -> Annual Energy Cost Savings | Z5: =J5 -> Annual Electric Savings (kWh) | AA5: =K5 -> Annual Oil Savings (Gal) | AB5: =L5 -> Annual Nat. Gas Savings (Therms) | AC5: =M5 -> Annual Propane Savings (Gal) | AD5: =O5 -> Simple Payback (Years) | AE5: =P5 -> IRR | AF5: =Q5 -> NPV | AQ5: Annual kBTU Savings
A6: =SUM(B6) -> 1 | B6: =IF(ISTEXT(D6)=TRUE,1,0) -> 1 | C6: ='Individual Measure List'!A8 | D6: ='Individual Measure List'!B8 | E6: ='EEM Data Entry'!D85 | F6: ='EEM Data Entry'!E85 | G6: ='EEM Data Entry'!G85 -> N/A | H6: ='EEM Data Entry'!F85 | I6: ='Individual Measure List'!F8 -> 0 | J6: =IF('Savings Summary'!D7=0,"",'Savings Summary'!D7) | K6: =IF('Savings Summary'!F7=0,"",'Savings Summary'!F7) | L6: =IF('Savings Summary'!H7=0,"",'Savings Summary'!H7) | M6: =IF('Savings Summary'!J7=0,"",'Savings Summary'!J7) | N6: =IF('RESULTS kBtu'!H6=0,"",'RESULTS kBtu'!H6) | O6: ='Individual Measure List'!H8 -> #VALUE! | P6: ='Individual Measure List'!J8 -> #NUM! | Q6: ='Individual Measure List'!K8 -> #VALUE! | S6: Discount Rate Assumptions | V6: =C6 | W6: =D6 | X6: =E6 | Y6: =I6 -> 0 | Z6: =J6 | AA6: =K6 | AB6: =L6 | AC6: =M6 | AD6: =O6 -> #VALUE! | AE6: =P6 -> #NUM! | AF6: =Q6 -> #VALUE! | AQ6: ='Individual Measure List'!G8 -> 0
A7: =SUM(B6:B7) -> 2 | B7: =IF(ISTEXT(D7)=TRUE,1,0) -> 1 | C7: ='Individual Measure List'!A9 | D7: ='Individual Measure List'!B9 | E7: ='EEM Data Entry'!D86 | F7: ='EEM Data Entry'!E86 | G7: ='EEM Data Entry'!G86 -> N/A | H7: ='EEM Data Entry'!F86 | I7: ='Individual Measure List'!F9 -> 0 | J7: =IF('Savings Summary'!D8=0,"",'Savings Summary'!D8) | K7: =IF('Savings Summary'!F8=0,"",'Savings Summary'!F8) | L7: =IF('Savings Summary'!H8=0,"",'Savings Summary'!H8) | M7: =IF('Savings Summary'!J8=0,"",'Savings Summary'!J8) | N7: =IF('RESULTS kBtu'!H7=0,"",'RESULTS kBtu'!H7) | O7: ='Individual Measure List'!H9 -> #VALUE! | P7: ='Individual Measure List'!J9 -> #NUM! | Q7: ='Individual Measure List'!K9 -> #VALUE! | S7: Inflation | T7: ='Interest Rate'!C10 -> 0.034 | V7: =C7 | W7: =D7 | X7: =E7 | Y7: =I7 -> 0 | Z7: =J7 | AA7: =K7 | AB7: =L7 | AC7: =M7 | AD7: =O7 -> #VALUE! | AE7: =P7 -> #NUM! | AF7: =Q7 -> #VALUE! | AQ7: ='Individual Measure List'!G9 -> 0
A8: =SUM(B6:B8) -> 3 | B8: =IF(ISTEXT(D8)=TRUE,1,0) -> 1 | C8: ='Individual Measure List'!A10 | D8: ='Individual Measure List'!B10 | E8: ='EEM Data Entry'!D87 | F8: ='EEM Data Entry'!E87 | G8: ='EEM Data Entry'!G87 -> N/A | H8: ='EEM Data Entry'!F87 | I8: ='Individual Measure List'!F10 -> 0 | J8: =IF('Savings Summary'!D9=0,"",'Savings Summary'!D9) | K8: =IF('Savings Summary'!F9=0,"",'Savings Summary'!F9) | L8: =IF('Savings Summary'!H9=0,"",'Savings Summary'!H9) | M8: =IF('Savings Summary'!J9=0,"",'Savings Summary'!J9) | N8: =IF('RESULTS kBtu'!H8=0,"",'RESULTS kBtu'!H8) | O8: ='Individual Measure List'!H10 -> #VALUE! | P8: ='Individual Measure List'!J10 -> #NUM! | Q8: ='Individual Measure List'!K10 -> #VALUE! | S8: Nominal Escalation Rate | T8: ='Interest Rate'!C12 -> 0 | V8: =C8 | W8: =D8 | X8: =E8 | Y8: =I8 -> 0 | Z8: =J8 | AA8: =K8 | AB8: =L8 | AC8: =M8 | AD8: =O8 -> #VALUE! | AE8: =P8 -> #NUM! | AF8: =Q8 -> #VALUE! | AQ8: ='Individual Measure List'!G10 -> 0
A9: =SUM(B6:B9) -> 4 | B9: =IF(ISTEXT(D9)=TRUE,1,0) -> 1 | C9: ='Individual Measure List'!A11 | D9: ='Individual Measure List'!B11 | E9: ='EEM Data Entry'!D88 | F9: ='EEM Data Entry'!E88 | G9: ='EEM Data Entry'!G88 -> N/A | H9: ='EEM Data Entry'!F88 | I9: ='Individual Measure List'!F11 -> 0 | J9: =IF('Savings Summary'!D10=0,"",'Savings Summary'!D10) | K9: =IF('Savings Summary'!F10=0,"",'Savings Summary'!F10) | L9: =IF('Savings Summary'!H10=0,"",'Savings Summary'!H10) | M9: =IF('Savings Summary'!J10=0,"",'Savings Summary'!J10) | N9: =IF('RESULTS kBtu'!H9=0,"",'RESULTS kBtu'!H9) | O9: ='Individual Measure List'!H11 -> #VALUE! | P9: ='Individual Measure List'!J11 -> #NUM! | Q9: ='Individual Measure List'!K11 -> #VALUE! | S9: Discount Rate | T9: ='Interest Rate'!C14 -> 0.05 | V9: =C9 | W9: =D9 | X9: =E9 | Y9: =I9 -> 0 | Z9: =J9 | AA9: =K9 | AB9: =L9 | AC9: =M9 | AD9: =O9 -> #VALUE! | AE9: =P9 -> #NUM! | AF9: =Q9 -> #VALUE! | AQ9: ='Individual Measure List'!G11 -> 0
A10: =SUM(B6:B10) -> 5 | B10: =IF(ISTEXT(D10)=TRUE,1,0) -> 1 | C10: ='Individual Measure List'!A12 | D10: ='Individual Measure List'!B12 | E10: ='EEM Data Entry'!D89 | F10: ='EEM Data Entry'!E89 | G10: ='EEM Data Entry'!G89 -> N/A | H10: ='EEM Data Entry'!F89 | I10: ='Individual Measure List'!F12 -> 0 | J10: =IF('Savings Summary'!D11=0,"",'Savings Summary'!D11) | K10: =IF('Savings Summary'!F11=0,"",'Savings Summary'!F11) | L10: =IF('Savings Summary'!H11=0,"",'Savings Summary'!H11) | M10: =IF('Savings Summary'!J11=0,"",'Savings Summary'!J11) | N10: =IF('RESULTS kBtu'!H10=0,"",'RESULTS kBtu'!H10) | O10: ='Individual Measure List'!H12 -> #VALUE! | P10: ='Individual Measure List'!J12 -> #NUM! | Q10: ='Individual Measure List'!K12 -> #VALUE! | S10: Adjusted Discount Rate | T10: ='Interest Rate'!B17 -> 0.05 | V10: =C10 | W10: =D10 | X10: =E10 | Y10: =I10 -> 0 | Z10: =J10 | AA10: =K10 | AB10: =L10 | AC10: =M10 | AD10: =O10 -> #VALUE! | AE10: =P10 -> #NUM! | AF10: =Q10 -> #VALUE! | AQ10: ='Individual Measure List'!G12 -> 0
A11: =SUM(B6:B11) -> 6 | B11: =IF(ISTEXT(D11)=TRUE,1,0) -> 1 | C11: ='Individual Measure List'!A13 | D11: ='Individual Measure List'!B13 | E11: ='EEM Data Entry'!D90 | F11: ='EEM Data Entry'!E90 | G11: ='EEM Data Entry'!G90 -> N/A | H11: ='EEM Data Entry'!F90 | I11: ='Individual Measure List'!F13 -> 0 | J11: =IF('Savings Summary'!D12=0,"",'Savings Summary'!D12) | K11: =IF('Savings Summary'!F12=0,"",'Savings Summary'!F12) | L11: =IF('Savings Summary'!H12=0,"",'Savings Summary'!H12) | M11: =IF('Savings Summary'!J12=0,"",'Savings Summary'!J12) | N11: =IF('RESULTS kBtu'!H11=0,"",'RESULTS kBtu'!H11) | O11: ='Individual Measure List'!H13 -> #VALUE! | P11: ='Individual Measure List'!J13 -> #NUM! | Q11: ='Individual Measure List'!K13 -> #VALUE! | S11: *Calculated using the Nation Institute of Standards and Technology (NIST) Energy Escalation Rate Calculator | V11: =C11 | W11: =D11 | X11: =E11 | Y11: =I11 -> 0 | Z11: =J11 | AA11: =K11 | AB11: =L11 | AC11: =M11 | AD11: =O11 -> #VALUE! | AE11: =P11 -> #NUM! | AF11: =Q11 -> #VALUE! | AQ11: ='Individual Measure List'!G13 -> 0
A12: =SUM(B6:B12) -> 7 | B12: =IF(ISTEXT(D12)=TRUE,1,0) -> 1 | C12: ='Individual Measure List'!A14 | D12: ='Individual Measure List'!B14 | E12: ='EEM Data Entry'!D91 | F12: ='EEM Data Entry'!E91 | G12: ='EEM Data Entry'!G91 -> N/A | H12: ='EEM Data Entry'!F91 | I12: ='Individual Measure List'!F14 -> 0 | J12: =IF('Savings Summary'!D13=0,"",'Savings Summary'!D13) | K12: =IF('Savings Summary'!F13=0,"",'Savings Summary'!F13) | L12: =IF('Savings Summary'!H13=0,"",'Savings Summary'!H13) | M12: =IF('Savings Summary'!J13=0,"",'Savings Summary'!J13) | N12: =IF('RESULTS kBtu'!H12=0,"",'RESULTS kBtu'!H12) | O12: ='Individual Measure List'!H14 -> #VALUE! | P12: ='Individual Measure List'!J14 -> #NUM! | Q12: ='Individual Measure List'!K14 -> #VALUE! | V12: =C12 | W12: =D12 | X12: =E12 | Y12: =I12 -> 0 | Z12: =J12 | AA12: =K12 | AB12: =L12 | AC12: =M12 | AD12: =O12 -> #VALUE! | AE12: =P12 -> #NUM! | AF12: =Q12 -> #VALUE! | AQ12: ='Individual Measure List'!G14 -> 0
A13: =SUM(B6:B13) -> 8 | B13: =IF(ISTEXT(D13)=TRUE,1,0) -> 1 | C13: ='Individual Measure List'!A15 | D13: ='Individual Measure List'!B15 | E13: ='EEM Data Entry'!D92 | F13: ='EEM Data Entry'!E92 | G13: ='EEM Data Entry'!G92 -> N/A | H13: ='EEM Data Entry'!F92 | I13: ='Individual Measure List'!F15 -> 0 | J13: =IF('Savings Summary'!D14=0,"",'Savings Summary'!D14) | K13: =IF('Savings Summary'!F14=0,"",'Savings Summary'!F14) | L13: =IF('Savings Summary'!H14=0,"",'Savings Summary'!H14) | M13: =IF('Savings Summary'!J14=0,"",'Savings Summary'!J14) | N13: =IF('RESULTS kBtu'!H13=0,"",'RESULTS kBtu'!H13) | O13: ='Individual Measure List'!H15 -> #VALUE! | P13: ='Individual Measure List'!J15 -> #NUM! | Q13: ='Individual Measure List'!K15 -> #VALUE! | V13: =C13 | W13: =D13 | X13: =E13 | Y13: =I13 -> 0 | Z13: =J13 | AA13: =K13 | AB13: =L13 | AC13: =M13 | AD13: =O13 -> #VALUE! | AE13: =P13 -> #NUM! | AF13: =Q13 -> #VALUE! | AQ13: ='Individual Measure List'!G15 -> 0
A14: =SUM(B6:B14) -> 9 | B14: =IF(ISTEXT(D14)=TRUE,1,0) -> 1 | C14: ='Individual Measure List'!A16 | D14: ='Individual Measure List'!B16 | E14: ='EEM Data Entry'!D93 | F14: ='EEM Data Entry'!E93 | G14: ='EEM Data Entry'!G93 -> N/A | H14: ='EEM Data Entry'!F93 | I14: ='Individual Measure List'!F16 -> 0 | J14: =IF('Savings Summary'!D15=0,"",'Savings Summary'!D15) | K14: =IF('Savings Summary'!F15=0,"",'Savings Summary'!F15) | L14: =IF('Savings Summary'!H15=0,"",'Savings Summary'!H15) | M14: =IF('Savings Summary'!J15=0,"",'Savings Summary'!J15) | N14: =IF('RESULTS kBtu'!H14=0,"",'RESULTS kBtu'!H14) | O14: ='Individual Measure List'!H16 -> #VALUE! | P14: ='Individual Measure List'!J16 -> #NUM! | Q14: ='Individual Measure List'!K16 -> #VALUE! | V14: =C14 | W14: =D14 | X14: =E14 | Y14: =I14 -> 0 | Z14: =J14 | AA14: =K14 | AB14: =L14 | AC14: =M14 | AD14: =O14 -> #VALUE! | AE14: =P14 -> #NUM! | AF14: =Q14 -> #VALUE! | AQ14: ='Individual Measure List'!G16 -> 0
A15: =SUM(B6:B15) -> 10 | B15: =IF(ISTEXT(D15)=TRUE,1,0) -> 1 | C15: ='Individual Measure List'!A17 | D15: ='Individual Measure List'!B17 | E15: ='EEM Data Entry'!D94 | F15: ='EEM Data Entry'!E94 | G15: ='EEM Data Entry'!G94 -> N/A | H15: ='EEM Data Entry'!F94 | I15: ='Individual Measure List'!F17 -> 0 | J15: =IF('Savings Summary'!D16=0,"",'Savings Summary'!D16) | K15: =IF('Savings Summary'!F16=0,"",'Savings Summary'!F16) | L15: =IF('Savings Summary'!H16=0,"",'Savings Summary'!H16) | M15: =IF('Savings Summary'!J16=0,"",'Savings Summary'!J16) | N15: =IF('RESULTS kBtu'!H15=0,"",'RESULTS kBtu'!H15) | O15: ='Individual Measure List'!H17 -> #VALUE! | P15: ='Individual Measure List'!J17 -> #NUM! | Q15: ='Individual Measure List'!K17 -> #VALUE! | V15: =C15 | W15: =D15 | X15: =E15 | Y15: =I15 -> 0 | Z15: =J15 | AA15: =K15 | AB15: =L15 | AC15: =M15 | AD15: =O15 -> #VALUE! | AE15: =P15 -> #NUM! | AF15: =Q15 -> #VALUE! | AQ15: ='Individual Measure List'!G17 -> 0
C16: *Please see "Note Regarding Incentives" on first page of financial modeling section | V16: *Please see "Note Regarding Incentives" on first page of financial modeling section
C18: MECHANICAL | V18: MECHANICAL
C20: EEM # | D20: Mechanical System Upgrades | E20: Capital Investment | F20: Estimated Incentive* | G20: Incentive Reference | H20: Estimated Net Cost | I20: Annual Energy Cost Savings | J20: Annual Electric Savings (kWh) | K20: Annual Oil Savings (Gal) | L20: Annual Nat. Gas Savings (Therms) | M20: Annual Propane Savings (Gal) | N20: Annual kBTU Savings | O20: Simple Payback (Years) | P20: IRR | Q20: NPV | V20: =C20 -> EEM # | W20: =D20 -> Mechanical System Upgrades | X20: =E20 -> Capital Investment | Y20: =I20 -> Annual Energy Cost Savings | Z20: =J20 -> Annual Electric Savings (kWh) | AA20: =K20 -> Annual Oil Savings (Gal) | AB20: =L20 -> Annual Nat. Gas Savings (Therms) | AC20: =M20 -> Annual Propane Savings (Gal) | AD20: =O20 -> Simple Payback (Years) | AE20: =P20 -> IRR | AF20: =Q20 -> NPV | AQ20: Annual kBTU Savings
A21: =SUM(B6:B21) -> 11 | B21: =IF(ISTEXT(D21)=TRUE,1,0) -> 1 | C21: ='Individual Measure List'!A33 | D21: ='Individual Measure List'!B33 | E21: ='EEM Data Entry'!D110 | F21: ='EEM Data Entry'!E110 | G21: ='EEM Data Entry'!G110 -> N/A | H21: ='EEM Data Entry'!F110 | I21: ='Individual Measure List'!F33 -> 0 | J21: =IF('Savings Summary'!D34=0,"",'Savings Summary'!D34) | K21: =IF('Savings Summary'!F34=0,"",'Savings Summary'!F34) | L21: =IF('Savings Summary'!H34=0,"",'Savings Summary'!H34) | M21: =IF('Savings Summary'!J34=0,"",'Savings Summary'!J34) | N21: =IF('RESULTS kBtu'!H21=0,"",'RESULTS kBtu'!H21) | O21: ='Individual Measure List'!H33 -> #VALUE! | P21: ='Individual Measure List'!J33 -> #NUM! | Q21: ='Individual Measure List'!K33 -> #VALUE! | V21: =C21 | W21: =D21 | X21: =E21 | Y21: =I21 -> 0 | Z21: =J21 | AA21: =K21 | AB21: =L21 | AC21: =M21 | AD21: =O21 -> #VALUE! | AE21: =P21 -> #NUM! | AF21: =Q21 -> #VALUE! | AQ21: ='Individual Measure List'!G33 -> 0
A22: =SUM(B6:B22) -> 12 | B22: =IF(ISTEXT(D22)=TRUE,1,0) -> 1 | C22: ='Individual Measure List'!A34 | D22: ='Individual Measure List'!B34 | E22: ='EEM Data Entry'!D111 | F22: ='EEM Data Entry'!E111 | G22: ='EEM Data Entry'!G111 -> N/A | H22: ='EEM Data Entry'!F111 | I22: ='Individual Measure List'!F34 -> 0 | J22: =IF('Savings Summary'!D35=0,"",'Savings Summary'!D35) | K22: =IF('Savings Summary'!F35=0,"",'Savings Summary'!F35) | L22: =IF('Savings Summary'!H35=0,"",'Savings Summary'!H35) | M22: =IF('Savings Summary'!J35=0,"",'Savings Summary'!J35) | N22: =IF('RESULTS kBtu'!H22=0,"",'RESULTS kBtu'!H22) | O22: ='Individual Measure List'!H34 -> #VALUE! | P22: ='Individual Measure List'!J34 -> #NUM! | Q22: ='Individual Measure List'!K34 -> #VALUE! | V22: =C22 | W22: =D22 | X22: =E22 | Y22: =I22 -> 0 | Z22: =J22 | AA22: =K22 | AB22: =L22 | AC22: =M22 | AD22: =O22 -> #VALUE! | AE22: =P22 -> #NUM! | AF22: =Q22 -> #VALUE! | AQ22: ='Individual Measure List'!G34 -> 0
A23: =SUM(B6:B23) -> 13 | B23: =IF(ISTEXT(D23)=TRUE,1,0) -> 1 | C23: ='Individual Measure List'!A35 | D23: ='Individual Measure List'!B35 | E23: ='EEM Data Entry'!D112 | F23: ='EEM Data Entry'!E112 | G23: ='EEM Data Entry'!G112 -> N/A | H23: ='EEM Data Entry'!F112 | I23: ='Individual Measure List'!F35 -> 0 | J23: =IF('Savings Summary'!D36=0,"",'Savings Summary'!D36) | K23: =IF('Savings Summary'!F36=0,"",'Savings Summary'!F36) | L23: =IF('Savings Summary'!H36=0,"",'Savings Summary'!H36) | M23: =IF('Savings Summary'!J36=0,"",'Savings Summary'!J36) | N23: =IF('RESULTS kBtu'!H23=0,"",'RESULTS kBtu'!H23) | O23: ='Individual Measure List'!H35 -> #VALUE! | P23: ='Individual Measure List'!J35 -> #NUM! | Q23: ='Individual Measure List'!K35 -> #VALUE! | V23: =C23 | W23: =D23 | X23: =E23 | Y23: =I23 -> 0 | Z23: =J23 | AA23: =K23 | AB23: =L23 | AC23: =M23 | AD23: =O23 -> #VALUE! | AE23: =P23 -> #NUM! | AF23: =Q23 -> #VALUE! | AQ23: ='Individual Measure List'!G35 -> 0
A24: =SUM(B6:B24) -> 14 | B24: =IF(ISTEXT(D24)=TRUE,1,0) -> 1 | C24: ='Individual Measure List'!A36 | D24: ='Individual Measure List'!B36 | E24: ='EEM Data Entry'!D113 | F24: ='EEM Data Entry'!E113 | G24: ='EEM Data Entry'!G113 -> N/A | H24: ='EEM Data Entry'!F113 | I24: ='Individual Measure List'!F36 -> 0 | J24: =IF('Savings Summary'!D37=0,"",'Savings Summary'!D37) | K24: =IF('Savings Summary'!F37=0,"",'Savings Summary'!F37) | L24: =IF('Savings Summary'!H37=0,"",'Savings Summary'!H37) | M24: =IF('Savings Summary'!J37=0,"",'Savings Summary'!J37) | N24: =IF('RESULTS kBtu'!H24=0,"",'RESULTS kBtu'!H24) | O24: ='Individual Measure List'!H36 -> #VALUE! | P24: ='Individual Measure List'!J36 -> #NUM! | Q24: ='Individual Measure List'!K36 -> #VALUE! | V24: =C24 | W24: =D24 | X24: =E24 | Y24: =I24 -> 0 | Z24: =J24 | AA24: =K24 | AB24: =L24 | AC24: =M24 | AD24: =O24 -> #VALUE! | AE24: =P24 -> #NUM! | AF24: =Q24 -> #VALUE! | AQ24: ='Individual Measure List'!G36 -> 0
A25: =SUM(B6:B25) -> 15 | B25: =IF(ISTEXT(D25)=TRUE,1,0) -> 1 | C25: ='Individual Measure List'!A37 | D25: ='Individual Measure List'!B37 | E25: ='EEM Data Entry'!D114 | F25: ='EEM Data Entry'!E114 | G25: ='EEM Data Entry'!G114 -> N/A | H25: ='EEM Data Entry'!F114 | I25: ='Individual Measure List'!F37 -> 0 | J25: =IF('Savings Summary'!D38=0,"",'Savings Summary'!D38) | K25: =IF('Savings Summary'!F38=0,"",'Savings Summary'!F38) | L25: =IF('Savings Summary'!H38=0,"",'Savings Summary'!H38) | M25: =IF('Savings Summary'!J38=0,"",'Savings Summary'!J38) | N25: =IF('RESULTS kBtu'!H25=0,"",'RESULTS kBtu'!H25) | O25: ='Individual Measure List'!H37 -> #VALUE! | P25: ='Individual Measure List'!J37 -> #NUM! | Q25: ='Individual Measure List'!K37 -> #VALUE! | V25: =C25 | W25: =D25 | X25: =E25 | Y25: =I25 -> 0 | Z25: =J25 | AA25: =K25 | AB25: =L25 | AC25: =M25 | AD25: =O25 -> #VALUE! | AE25: =P25 -> #NUM! | AF25: =Q25 -> #VALUE! | AQ25: ='Individual Measure List'!G37 -> 0
A26: =SUM(B6:B26) -> 16 | B26: =IF(ISTEXT(D26)=TRUE,1,0) -> 1 | C26: ='Individual Measure List'!A38 | D26: ='Individual Measure List'!B38 | E26: ='EEM Data Entry'!D115 | F26: ='EEM Data Entry'!E115 | G26: ='EEM Data Entry'!G115 -> N/A | H26: ='EEM Data Entry'!F115 | I26: ='Individual Measure List'!F38 -> 0 | J26: =IF('Savings Summary'!D39=0,"",'Savings Summary'!D39) | K26: =IF('Savings Summary'!F39=0,"",'Savings Summary'!F39) | L26: =IF('Savings Summary'!H39=0,"",'Savings Summary'!H39) | M26: =IF('Savings Summary'!J39=0,"",'Savings Summary'!J39) | N26: =IF('RESULTS kBtu'!H26=0,"",'RESULTS kBtu'!H26) | O26: ='Individual Measure List'!H38 -> #VALUE! | P26: ='Individual Measure List'!J38 -> #NUM! | Q26: ='Individual Measure List'!K38 -> #VALUE! | V26: =C26 | W26: =D26 | X26: =E26 | Y26: =I26 -> 0 | Z26: =J26 | AA26: =K26 | AB26: =L26 | AC26: =M26 | AD26: =O26 -> #VALUE! | AE26: =P26 -> #NUM! | AF26: =Q26 -> #VALUE! | AQ26: ='Individual Measure List'!G38 -> 0
A27: =SUM(B6:B27) -> 17 | B27: =IF(ISTEXT(D27)=TRUE,1,0) -> 1 | C27: ='Individual Measure List'!A39 | D27: ='Individual Measure List'!B39 | E27: ='EEM Data Entry'!D116 | F27: ='EEM Data Entry'!E116 | G27: ='EEM Data Entry'!G116 -> N/A | H27: ='EEM Data Entry'!F116 | I27: ='Individual Measure List'!F39 -> 0 | J27: =IF('Savings Summary'!D40=0,"",'Savings Summary'!D40) | K27: =IF('Savings Summary'!F40=0,"",'Savings Summary'!F40) | L27: =IF('Savings Summary'!H40=0,"",'Savings Summary'!H40) | M27: =IF('Savings Summary'!J40=0,"",'Savings Summary'!J40) | N27: =IF('RESULTS kBtu'!H27=0,"",'RESULTS kBtu'!H27) | O27: ='Individual Measure List'!H39 -> #VALUE! | P27: ='Individual Measure List'!J39 -> #NUM! | Q27: ='Individual Measure List'!K39 -> #VALUE! | V27: =C27 | W27: =D27 | X27: =E27 | Y27: =I27 -> 0 | Z27: =J27 | AA27: =K27 | AB27: =L27 | AC27: =M27 | AD27: =O27 -> #VALUE! | AE27: =P27 -> #NUM! | AF27: =Q27 -> #VALUE! | AQ27: ='Individual Measure List'!G39 -> 0
A28: =SUM(B6:B28) -> 18 | B28: =IF(ISTEXT(D28)=TRUE,1,0) -> 1 | C28: ='Individual Measure List'!A40 | D28: ='Individual Measure List'!B40 | E28: ='EEM Data Entry'!D117 | F28: ='EEM Data Entry'!E117 | G28: ='EEM Data Entry'!G117 -> N/A | H28: ='EEM Data Entry'!F117 | I28: ='Individual Measure List'!F40 -> 0 | J28: =IF('Savings Summary'!D41=0,"",'Savings Summary'!D41) | K28: =IF('Savings Summary'!F41=0,"",'Savings Summary'!F41) | L28: =IF('Savings Summary'!H41=0,"",'Savings Summary'!H41) | M28: =IF('Savings Summary'!J41=0,"",'Savings Summary'!J41) | N28: =IF('RESULTS kBtu'!H28=0,"",'RESULTS kBtu'!H28) | O28: ='Individual Measure List'!H40 -> #VALUE! | P28: ='Individual Measure List'!J40 -> #NUM! | Q28: ='Individual Measure List'!K40 -> #VALUE! | V28: =C28 | W28: =D28 | X28: =E28 | Y28: =I28 -> 0 | Z28: =J28 | AA28: =K28 | AB28: =L28 | AC28: =M28 | AD28: =O28 -> #VALUE! | AE28: =P28 -> #NUM! | AF28: =Q28 -> #VALUE! | AQ28: ='Individual Measure List'!G40 -> 0
A29: =SUM(B6:B29) -> 19 | B29: =IF(ISTEXT(D29)=TRUE,1,0) -> 1 | C29: ='Individual Measure List'!A41 | D29: ='Individual Measure List'!B41 | E29: ='EEM Data Entry'!D118 | F29: ='EEM Data Entry'!E118 | G29: ='EEM Data Entry'!G118 -> N/A | H29: ='EEM Data Entry'!F118 | I29: ='Individual Measure List'!F41 -> 0 | J29: =IF('Savings Summary'!D42=0,"",'Savings Summary'!D42) | K29: =IF('Savings Summary'!F42=0,"",'Savings Summary'!F42) | L29: =IF('Savings Summary'!H42=0,"",'Savings Summary'!H42) | M29: =IF('Savings Summary'!J42=0,"",'Savings Summary'!J42) | N29: =IF('RESULTS kBtu'!H29=0,"",'RESULTS kBtu'!H29) | O29: ='Individual Measure List'!H41 -> #VALUE! | P29: ='Individual Measure List'!J41 -> #NUM! | Q29: ='Individual Measure List'!K41 -> #VALUE! | V29: =C29 | W29: =D29 | X29: =E29 | Y29: =I29 -> 0 | Z29: =J29 | AA29: =K29 | AB29: =L29 | AC29: =M29 | AD29: =O29 -> #VALUE! | AE29: =P29 -> #NUM! | AF29: =Q29 -> #VALUE! | AQ29: ='Individual Measure List'!G41 -> 0
A30: =SUM(B6:B30) -> 20 | B30: =IF(ISTEXT(D30)=TRUE,1,0) -> 1 | C30: ='Individual Measure List'!A42 | D30: ='Individual Measure List'!B42 | E30: ='EEM Data Entry'!D119 | F30: ='EEM Data Entry'!E119 | G30: ='EEM Data Entry'!G119 -> N/A | H30: ='EEM Data Entry'!F119 | I30: ='Individual Measure List'!F42 -> 0 | J30: =IF('Savings Summary'!D43=0,"",'Savings Summary'!D43) | K30: =IF('Savings Summary'!F43=0,"",'Savings Summary'!F43) | L30: =IF('Savings Summary'!H43=0,"",'Savings Summary'!H43) | M30: =IF('Savings Summary'!J43=0,"",'Savings Summary'!J43) | N30: =IF('RESULTS kBtu'!H30=0,"",'RESULTS kBtu'!H30) | O30: ='Individual Measure List'!H42 -> #VALUE! | P30: ='Individual Measure List'!J42 -> #NUM! | Q30: ='Individual Measure List'!K42 -> #VALUE! | V30: =C30 | W30: =D30 | X30: =E30 | Y30: =I30 -> 0 | Z30: =J30 | AA30: =K30 | AB30: =L30 | AC30: =M30 | AD30: =O30 -> #VALUE! | AE30: =P30 -> #NUM! | AF30: =Q30 -> #VALUE! | AQ30: ='Individual Measure List'!G42 -> 0
C31: *Please see "Note Regarding Incentives" on first page of financial modeling section | V31: *Please see "Note Regarding Incentives" on first page of financial modeling section
C33: APPLIANCES & LIGHTING | V33: APPLIANCES & LIGHTING
C35: EEM # | D35: Appliances & Lighting Upgrades | E35: Capital Investment | F35: Estimated Incentive* | G35: Incentive Reference | H35: Estimated Net Cost | I35: Annual Energy Cost Savings | J35: Annual Electric Savings (kWh) | K35: Annual Oil Savings (Gal) | L35: Annual Nat. Gas Savings (Therms) | M35: Annual Propane Savings (Gal) | N35: Annual kBTU Savings | O35: Simple Payback (Years) | P35: IRR | Q35: NPV | V35: =C35 -> EEM # | W35: =D35 -> Appliances & Lighting Upgrades | X35: =E35 -> Capital Investment | Y35: =I35 -> Annual Energy Cost Savings | Z35: =J35 -> Annual Electric Savings (kWh) | AA35: =K35 -> Annual Oil Savings (Gal) | AB35: =L35 -> Annual Nat. Gas Savings (Therms) | AC35: =M35 -> Annual Propane Savings (Gal) | AD35: =O35 -> Simple Payback (Years) | AE35: =P35 -> IRR | AF35: =Q35 -> NPV | AQ35: Annual kBTU Savings
A36: =SUM(B6:B36) -> 21 | B36: =IF(ISTEXT(D36)=TRUE,1,0) -> 1 | C36: ='Individual Measure List'!A49 | D36: ='Individual Measure List'!B49 | E36: ='EEM Data Entry'!D125 | F36: ='EEM Data Entry'!E125 | G36: ='EEM Data Entry'!G125 -> N/A | H36: ='EEM Data Entry'!F125 | I36: ='Individual Measure List'!F49 -> 0 | J36: =IF('Savings Summary'!D51=0,"",'Savings Summary'!D51) | K36: =IF('Savings Summary'!F51=0,"",'Savings Summary'!F51) | L36: =IF('Savings Summary'!H51=0,"",'Savings Summary'!H51) | M36: =IF('Savings Summary'!J51=0,"",'Savings Summary'!J51) | N36: =IF('RESULTS kBtu'!H36=0,"",'RESULTS kBtu'!H36) | O36: ='Individual Measure List'!H49 -> #VALUE! | P36: ='Individual Measure List'!J49 -> #NUM! | Q36: ='Individual Measure List'!K49 -> #VALUE! | V36: =C36 | W36: =D36 | X36: =E36 | Y36: =I36 -> 0 | Z36: =J36 | AA36: =K36 | AB36: =L36 | AC36: =M36 | AD36: =O36 -> #VALUE! | AE36: =P36 -> #NUM! | AF36: =Q36 -> #VALUE! | AQ36: ='Individual Measure List'!G49 -> 0
A37: =SUM(B6:B37) -> 22 | B37: =IF(ISTEXT(D37)=TRUE,1,0) -> 1 | C37: ='Individual Measure List'!A50 | D37: ='Individual Measure List'!B50 | E37: ='EEM Data Entry'!D126 | F37: ='EEM Data Entry'!E126 | G37: ='EEM Data Entry'!G126 -> N/A | H37: ='EEM Data Entry'!F126 | I37: ='Individual Measure List'!F50 -> 0 | J37: =IF('Savings Summary'!D52=0,"",'Savings Summary'!D52) | K37: =IF('Savings Summary'!F52=0,"",'Savings Summary'!F52) | L37: =IF('Savings Summary'!H52=0,"",'Savings Summary'!H52) | M37: =IF('Savings Summary'!J52=0,"",'Savings Summary'!J52) | N37: =IF('RESULTS kBtu'!H37=0,"",'RESULTS kBtu'!H37) | O37: ='Individual Measure List'!H50 -> #VALUE! | P37: ='Individual Measure List'!J50 -> #NUM! | Q37: ='Individual Measure List'!K50 -> #VALUE! | V37: =C37 | W37: =D37 | X37: =E37 | Y37: =I37 -> 0 | Z37: =J37 | AA37: =K37 | AB37: =L37 | AC37: =M37 | AD37: =O37 -> #VALUE! | AE37: =P37 -> #NUM! | AF37: =Q37 -> #VALUE! | AQ37: ='Individual Measure List'!G50 -> 0
A38: =SUM(B6:B38) -> 23 | B38: =IF(ISTEXT(D38)=TRUE,1,0) -> 1 | C38: ='Individual Measure List'!A51 | D38: ='Individual Measure List'!B51 | E38: ='EEM Data Entry'!D127 | F38: ='EEM Data Entry'!E127 | G38: ='EEM Data Entry'!G127 -> N/A | H38: ='EEM Data Entry'!F127 | I38: ='Individual Measure List'!F51 -> 0 | J38: =IF('Savings Summary'!D53=0,"",'Savings Summary'!D53) | K38: =IF('Savings Summary'!F53=0,"",'Savings Summary'!F53) | L38: =IF('Savings Summary'!H53=0,"",'Savings Summary'!H53) | M38: =IF('Savings Summary'!J53=0,"",'Savings Summary'!J53) | N38: =IF('RESULTS kBtu'!H38=0,"",'RESULTS kBtu'!H38) | O38: ='Individual Measure List'!H51 -> #VALUE! | P38: ='Individual Measure List'!J51 -> #NUM! | Q38: ='Individual Measure List'!K51 -> #VALUE! | V38: =C38 | W38: =D38 | X38: =E38 | Y38: =I38 -> 0 | Z38: =J38 | AA38: =K38 | AB38: =L38 | AC38: =M38 | AD38: =O38 -> #VALUE! | AE38: =P38 -> #NUM! | AF38: =Q38 -> #VALUE! | AQ38: ='Individual Measure List'!G51 -> 0
A39: =SUM(B6:B39) -> 24 | B39: =IF(ISTEXT(D39)=TRUE,1,0) -> 1 | C39: ='Individual Measure List'!A52 | D39: ='Individual Measure List'!B52 | E39: ='EEM Data Entry'!D128 | F39: ='EEM Data Entry'!E128 | G39: ='EEM Data Entry'!G128 -> N/A | H39: ='EEM Data Entry'!F128 | I39: ='Individual Measure List'!F52 -> 0 | J39: =IF('Savings Summary'!D54=0,"",'Savings Summary'!D54) | K39: =IF('Savings Summary'!F54=0,"",'Savings Summary'!F54) | L39: =IF('Savings Summary'!H54=0,"",'Savings Summary'!H54) | M39: =IF('Savings Summary'!J54=0,"",'Savings Summary'!J54) | N39: =IF('RESULTS kBtu'!H39=0,"",'RESULTS kBtu'!H39) | O39: ='Individual Measure List'!H52 -> #VALUE! | P39: ='Individual Measure List'!J52 -> #NUM! | Q39: ='Individual Measure List'!K52 -> #VALUE! | V39: =C39 | W39: =D39 | X39: =E39 | Y39: =I39 -> 0 | Z39: =J39 | AA39: =K39 | AB39: =L39 | AC39: =M39 | AD39: =O39 -> #VALUE! | AE39: =P39 -> #NUM! | AF39: =Q39 -> #VALUE! | AQ39: ='Individual Measure List'!G52 -> 0
A40: =SUM(B6:B40) -> 25 | B40: =IF(ISTEXT(D40)=TRUE,1,0) -> 1 | C40: ='Individual Measure List'!A53 | D40: ='Individual Measure List'!B53 | E40: ='EEM Data Entry'!D129 | F40: ='EEM Data Entry'!E129 | G40: ='EEM Data Entry'!G129 -> N/A | H40: ='EEM Data Entry'!F129 | I40: ='Individual Measure List'!F53 -> 0 | J40: =IF('Savings Summary'!D55=0,"",'Savings Summary'!D55) | K40: =IF('Savings Summary'!F55=0,"",'Savings Summary'!F55) | L40: =IF('Savings Summary'!H55=0,"",'Savings Summary'!H55) | M40: =IF('Savings Summary'!J55=0,"",'Savings Summary'!J55) | N40: =IF('RESULTS kBtu'!H40=0,"",'RESULTS kBtu'!H40) | O40: ='Individual Measure List'!H53 -> #VALUE! | P40: ='Individual Measure List'!J53 -> #NUM! | Q40: ='Individual Measure List'!K53 -> #VALUE! | V40: =C40 | W40: =D40 | X40: =E40 | Y40: =I40 -> 0 | Z40: =J40 | AA40: =K40 | AB40: =L40 | AC40: =M40 | AD40: =O40 -> #VALUE! | AE40: =P40 -> #NUM! | AF40: =Q40 -> #VALUE! | AQ40: ='Individual Measure List'!G53 -> 0
A41: =SUM(B6:B41) -> 26 | B41: =IF(ISTEXT(D41)=TRUE,1,0) -> 1 | C41: ='Individual Measure List'!A54 | D41: ='Individual Measure List'!B54 | E41: ='EEM Data Entry'!D130 | F41: ='EEM Data Entry'!E130 | G41: ='EEM Data Entry'!G130 -> N/A | H41: ='EEM Data Entry'!F130 | I41: ='Individual Measure List'!F54 -> 0 | J41: =IF('Savings Summary'!D56=0,"",'Savings Summary'!D56) | K41: =IF('Savings Summary'!F56=0,"",'Savings Summary'!F56) | L41: =IF('Savings Summary'!H56=0,"",'Savings Summary'!H56) | M41: =IF('Savings Summary'!J56=0,"",'Savings Summary'!J56) | N41: =IF('RESULTS kBtu'!H41=0,"",'RESULTS kBtu'!H41) | O41: ='Individual Measure List'!H54 -> #VALUE! | P41: ='Individual Measure List'!J54 -> #NUM! | Q41: ='Individual Measure List'!K54 -> #VALUE! | V41: =C41 | W41: =D41 | X41: =E41 | Y41: =I41 -> 0 | Z41: =J41 | AA41: =K41 | AB41: =L41 | AC41: =M41 | AD41: =O41 -> #VALUE! | AE41: =P41 -> #NUM! | AF41: =Q41 -> #VALUE! | AQ41: ='Individual Measure List'!G54 -> 0
A42: =SUM(B6:B42) -> 27 | B42: =IF(ISTEXT(D42)=TRUE,1,0) -> 1 | C42: ='Individual Measure List'!A55 | D42: ='Individual Measure List'!B55 | E42: ='EEM Data Entry'!D131 | F42: ='EEM Data Entry'!E131 | G42: ='EEM Data Entry'!G131 -> N/A | H42: ='EEM Data Entry'!F131 | I42: ='Individual Measure List'!F55 -> 0 | J42: =IF('Savings Summary'!D57=0,"",'Savings Summary'!D57) | K42: =IF('Savings Summary'!F57=0,"",'Savings Summary'!F57) | L42: =IF('Savings Summary'!H57=0,"",'Savings Summary'!H57) | M42: =IF('Savings Summary'!J57=0,"",'Savings Summary'!J57) | N42: =IF('RESULTS kBtu'!H42=0,"",'RESULTS kBtu'!H42) | O42: ='Individual Measure List'!H55 -> #VALUE! | P42: ='Individual Measure List'!J55 -> #NUM! | Q42: ='Individual Measure List'!K55 -> #VALUE! | V42: =C42 | W42: =D42 | X42: =E42 | Y42: =I42 -> 0 | Z42: =J42 | AA42: =K42 | AB42: =L42 | AC42: =M42 | AD42: =O42 -> #VALUE! | AE42: =P42 -> #NUM! | AF42: =Q42 -> #VALUE! | AQ42: ='Individual Measure List'!G55 -> 0
A43: =SUM(B6:B43) -> 28 | B43: =IF(ISTEXT(D43)=TRUE,1,0) -> 1 | C43: ='Individual Measure List'!A56 | D43: ='Individual Measure List'!B56 | E43: ='EEM Data Entry'!D132 | F43: ='EEM Data Entry'!E132 | G43: ='EEM Data Entry'!G132 -> N/A | H43: ='EEM Data Entry'!F132 | I43: ='Individual Measure List'!F56 -> 0 | J43: =IF('Savings Summary'!D58=0,"",'Savings Summary'!D58) | K43: =IF('Savings Summary'!F58=0,"",'Savings Summary'!F58) | L43: =IF('Savings Summary'!H58=0,"",'Savings Summary'!H58) | M43: =IF('Savings Summary'!J58=0,"",'Savings Summary'!J58) | N43: =IF('RESULTS kBtu'!H43=0,"",'RESULTS kBtu'!H43) | O43: ='Individual Measure List'!H56 -> #VALUE! | P43: ='Individual Measure List'!J56 -> #NUM! | Q43: ='Individual Measure List'!K56 -> #VALUE! | V43: =C43 | W43: =D43 | X43: =E43 | Y43: =I43 -> 0 | Z43: =J43 | AA43: =K43 | AB43: =L43 | AC43: =M43 | AD43: =O43 -> #VALUE! | AE43: =P43 -> #NUM! | AF43: =Q43 -> #VALUE! | AQ43: ='Individual Measure List'!G56 -> 0
A44: =SUM(B6:B44) -> 29 | B44: =IF(ISTEXT(D44)=TRUE,1,0) -> 1 | C44: ='Individual Measure List'!A57 | D44: ='Individual Measure List'!B57 | E44: ='EEM Data Entry'!D133 | F44: ='EEM Data Entry'!E133 | G44: ='EEM Data Entry'!G133 -> N/A | H44: ='EEM Data Entry'!F133 | I44: ='Individual Measure List'!F57 -> 0 | J44: =IF('Savings Summary'!D59=0,"",'Savings Summary'!D59) | K44: =IF('Savings Summary'!F59=0,"",'Savings Summary'!F59) | L44: =IF('Savings Summary'!H59=0,"",'Savings Summary'!H59) | M44: =IF('Savings Summary'!J59=0,"",'Savings Summary'!J59) | N44: =IF('RESULTS kBtu'!H44=0,"",'RESULTS kBtu'!H44) | O44: ='Individual Measure List'!H57 -> #VALUE! | P44: ='Individual Measure List'!J57 -> #NUM! | Q44: ='Individual Measure List'!K57 -> #VALUE! | V44: =C44 | W44: =D44 | X44: =E44 | Y44: =I44 -> 0 | Z44: =J44 | AA44: =K44 | AB44: =L44 | AC44: =M44 | AD44: =O44 -> #VALUE! | AE44: =P44 -> #NUM! | AF44: =Q44 -> #VALUE! | AQ44: ='Individual Measure List'!G57 -> 0
A45: =SUM(B6:B45) -> 30 | B45: =IF(ISTEXT(D45)=TRUE,1,0) -> 1 | C45: ='Individual Measure List'!A58 | D45: ='Individual Measure List'!B58 | E45: ='EEM Data Entry'!D134 | F45: ='EEM Data Entry'!E134 | G45: ='EEM Data Entry'!G134 -> N/A | H45: ='EEM Data Entry'!F134 | I45: ='Individual Measure List'!F58 -> 0 | J45: =IF('Savings Summary'!D60=0,"",'Savings Summary'!D60) | K45: =IF('Savings Summary'!F60=0,"",'Savings Summary'!F60) | L45: =IF('Savings Summary'!H60=0,"",'Savings Summary'!H60) | M45: =IF('Savings Summary'!J60=0,"",'Savings Summary'!J60) | N45: =IF('RESULTS kBtu'!H45=0,"",'RESULTS kBtu'!H45) | O45: ='Individual Measure List'!H58 -> #VALUE! | P45: ='Individual Measure List'!J58 -> #NUM! | Q45: ='Individual Measure List'!K58 -> #VALUE! | V45: =C45 | W45: =D45 | X45: =E45 | Y45: =I45 -> 0 | Z45: =J45 | AA45: =K45 | AB45: =L45 | AC45: =M45 | AD45: =O45 -> #VALUE! | AE45: =P45 -> #NUM! | AF45: =Q45 -> #VALUE! | AQ45: ='Individual Measure List'!G58 -> 0
C46: *Please see "Note Regarding Incentives" on first page of financial modeling section | V46: *Please see "Note Regarding Incentives" on first page of financial modeling section
C48: RENEWABLE | V48: RENEWABLE
C50: EEM # | D50: Renewable System Upgrades | E50: Capital Investment | F50: Estimated Incentive* | G50: Incentive Reference | H50: Estimated Net Cost | I50: Annual Energy Cost Savings | J50: Annual Electric Savings (kWh) | K50: Annual Oil Savings (Gal) | L50: Annual Nat. Gas Savings (Therms) | M50: Annual Propane Savings (Gal) | N50: Annual kBTU Savings | O50: Simple Payback (Years) | P50: IRR | Q50: NPV | V50: =C50 -> EEM # | W50: =D50 -> Renewable System Upgrades | X50: =E50 -> Capital Investment | Y50: =I50 -> Annual Energy Cost Savings | Z50: =J50 -> Annual Electric Savings (kWh) | AA50: =K50 -> Annual Oil Savings (Gal) | AB50: =L50 -> Annual Nat. Gas Savings (Therms) | AC50: =M50 -> Annual Propane Savings (Gal) | AD50: =O50 -> Simple Payback (Years) | AE50: =P50 -> IRR | AF50: =Q50 -> NPV | AQ50: Annual kBTU Savings
A51: =SUM(B6:B51) -> 31 | B51: =IF(ISTEXT(D51)=TRUE,1,0) -> 1 | C51: ='Individual Measure List'!A66 | D51: ='Individual Measure List'!B66 | E51: ='EEM Data Entry'!D141 | F51: ='EEM Data Entry'!E141 | G51: ='EEM Data Entry'!G141 -> N/A | H51: ='EEM Data Entry'!F141 | I51: ='Individual Measure List'!F66 -> 0 | J51: =IF('Savings Summary'!D69=0,"",'Savings Summary'!D69) | K51: =IF('Savings Summary'!F69=0,"",'Savings Summary'!F69) | L51: =IF('Savings Summary'!H69=0,"",'Savings Summary'!H69) | M51: =IF('Savings Summary'!J69=0,"",'Savings Summary'!J69) | N51: =IF('RESULTS kBtu'!H51=0,"",'RESULTS kBtu'!H51) | O51: ='Individual Measure List'!H66 -> #VALUE! | P51: ='Individual Measure List'!J66 -> #NUM! | Q51: ='Individual Measure List'!K66 -> #VALUE! | V51: =C51 | W51: =D51 | X51: =E51 | Y51: =I51 -> 0 | Z51: =J51 | AA51: =K51 | AB51: =L51 | AC51: =M51 | AD51: =O51 -> #VALUE! | AE51: =P51 -> #NUM! | AF51: =Q51 -> #VALUE! | AQ51: ='Individual Measure List'!G66 -> 0
A52: =SUM(B6:B52) -> 32 | B52: =IF(ISTEXT(D52)=TRUE,1,0) -> 1 | C52: ='Individual Measure List'!A67 | D52: ='Individual Measure List'!B67 | E52: ='EEM Data Entry'!D142 | F52: ='EEM Data Entry'!E142 | G52: ='EEM Data Entry'!G142 -> N/A | H52: ='EEM Data Entry'!F142 | I52: ='Individual Measure List'!F67 -> 0 | J52: =IF('Savings Summary'!D70=0,"",'Savings Summary'!D70) | K52: =IF('Savings Summary'!F70=0,"",'Savings Summary'!F70) | L52: =IF('Savings Summary'!H70=0,"",'Savings Summary'!H70) | M52: =IF('Savings Summary'!J70=0,"",'Savings Summary'!J70) | N52: =IF('RESULTS kBtu'!H52=0,"",'RESULTS kBtu'!H52) | O52: ='Individual Measure List'!H67 -> #VALUE! | P52: ='Individual Measure List'!J67 -> #NUM! | Q52: ='Individual Measure List'!K67 -> #VALUE! | V52: =C52 | W52: =D52 | X52: =E52 | Y52: =I52 -> 0 | Z52: =J52 | AA52: =K52 | AB52: =L52 | AC52: =M52 | AD52: =O52 -> #VALUE! | AE52: =P52 -> #NUM! | AF52: =Q52 -> #VALUE! | AQ52: ='Individual Measure List'!G67 -> 0
A53: =SUM(B6:B53) -> 33 | B53: =IF(ISTEXT(D53)=TRUE,1,0) -> 1 | C53: ='Individual Measure List'!A68 | D53: ='Individual Measure List'!B68 | E53: ='EEM Data Entry'!D143 | F53: ='EEM Data Entry'!E143 | G53: ='EEM Data Entry'!G143 -> N/A | H53: ='EEM Data Entry'!F143 | I53: ='Individual Measure List'!F68 -> 0 | J53: =IF('Savings Summary'!D71=0,"",'Savings Summary'!D71) | K53: =IF('Savings Summary'!F71=0,"",'Savings Summary'!F71) | L53: =IF('Savings Summary'!H71=0,"",'Savings Summary'!H71) | M53: =IF('Savings Summary'!J71=0,"",'Savings Summary'!J71) | N53: =IF('RESULTS kBtu'!H53=0,"",'RESULTS kBtu'!H53) | O53: ='Individual Measure List'!H68 -> #VALUE! | P53: ='Individual Measure List'!J68 -> #NUM! | Q53: ='Individual Measure List'!K68 -> #VALUE! | V53: =C53 | W53: =D53 | X53: =E53 | Y53: =I53 -> 0 | Z53: =J53 | AA53: =K53 | AB53: =L53 | AC53: =M53 | AD53: =O53 -> #VALUE! | AE53: =P53 -> #NUM! | AF53: =Q53 -> #VALUE! | AQ53: ='Individual Measure List'!G68 -> 0
A54: =SUM(B6:B54) -> 34 | B54: =IF(ISTEXT(D54)=TRUE,1,0) -> 1 | C54: ='Individual Measure List'!A69 | D54: ='Individual Measure List'!B69 | E54: ='EEM Data Entry'!D144 | F54: ='EEM Data Entry'!E144 | G54: ='EEM Data Entry'!G144 -> N/A | H54: ='EEM Data Entry'!F144 | I54: ='Individual Measure List'!F69 -> 0 | J54: =IF('Savings Summary'!D72=0,"",'Savings Summary'!D72) | K54: =IF('Savings Summary'!F72=0,"",'Savings Summary'!F72) | L54: =IF('Savings Summary'!H72=0,"",'Savings Summary'!H72) | M54: =IF('Savings Summary'!J72=0,"",'Savings Summary'!J72) | N54: =IF('RESULTS kBtu'!H54=0,"",'RESULTS kBtu'!H54) | O54: ='Individual Measure List'!H69 -> #VALUE! | P54: ='Individual Measure List'!J69 -> #NUM! | Q54: ='Individual Measure List'!K69 -> #VALUE! | V54: =C54 | W54: =D54 | X54: =E54 | Y54: =I54 -> 0 | Z54: =J54 | AA54: =K54 | AB54: =L54 | AC54: =M54 | AD54: =O54 -> #VALUE! | AE54: =P54 -> #NUM! | AF54: =Q54 -> #VALUE! | AQ54: ='Individual Measure List'!G69 -> 0
A55: =SUM(B6:B55) -> 35 | B55: =IF(ISTEXT(D55)=TRUE,1,0) -> 1 | C55: ='Individual Measure List'!A70 | D55: ='Individual Measure List'!B70 | E55: ='EEM Data Entry'!D145 | F55: ='EEM Data Entry'!E145 | G55: ='EEM Data Entry'!G145 -> N/A | H55: ='EEM Data Entry'!F145 | I55: ='Individual Measure List'!F70 -> 0 | J55: =IF('Savings Summary'!D73=0,"",'Savings Summary'!D73) | K55: =IF('Savings Summary'!F73=0,"",'Savings Summary'!F73) | L55: =IF('Savings Summary'!H73=0,"",'Savings Summary'!H73) | M55: =IF('Savings Summary'!J73=0,"",'Savings Summary'!J73) | N55: =IF('RESULTS kBtu'!H55=0,"",'RESULTS kBtu'!H55) | O55: ='Individual Measure List'!H70 -> #VALUE! | P55: ='Individual Measure List'!J70 -> #NUM! | Q55: ='Individual Measure List'!K70 -> #VALUE! | V55: =C55 | W55: =D55 | X55: =E55 | Y55: =I55 -> 0 | Z55: =J55 | AA55: =K55 | AB55: =L55 | AC55: =M55 | AD55: =O55 -> #VALUE! | AE55: =P55 -> #NUM! | AF55: =Q55 -> #VALUE! | AQ55: ='Individual Measure List'!G70 -> 0
A56: =SUM(B6:B56) -> 36 | B56: =IF(ISTEXT(D56)=TRUE,1,0) -> 1 | C56: ='Individual Measure List'!A71 | D56: ='Individual Measure List'!B71 | E56: ='EEM Data Entry'!D146 | F56: ='EEM Data Entry'!E146 | G56: ='EEM Data Entry'!G146 -> N/A | H56: ='EEM Data Entry'!F146 | I56: ='Individual Measure List'!F71 -> 0 | J56: =IF('Savings Summary'!D74=0,"",'Savings Summary'!D74) | K56: =IF('Savings Summary'!F74=0,"",'Savings Summary'!F74) | L56: =IF('Savings Summary'!H74=0,"",'Savings Summary'!H74) | M56: =IF('Savings Summary'!J74=0,"",'Savings Summary'!J74) | N56: =IF('RESULTS kBtu'!H56=0,"",'RESULTS kBtu'!H56) | O56: ='Individual Measure List'!H71 -> #VALUE! | P56: ='Individual Measure List'!J71 -> #NUM! | Q56: ='Individual Measure List'!K71 -> #VALUE! | V56: =C56 | W56: =D56 | X56: =E56 | Y56: =I56 -> 0 | Z56: =J56 | AA56: =K56 | AB56: =L56 | AC56: =M56 | AD56: =O56 -> #VALUE! | AE56: =P56 -> #NUM! | AF56: =Q56 -> #VALUE! | AQ56: ='Individual Measure List'!G71 -> 0
A57: =SUM(B6:B57) -> 37 | B57: =IF(ISTEXT(D57)=TRUE,1,0) -> 1 | C57: ='Individual Measure List'!A72 | D57: ='Individual Measure List'!B72 | E57: ='EEM Data Entry'!D147 | F57: ='EEM Data Entry'!E147 | G57: ='EEM Data Entry'!G147 -> N/A | H57: ='EEM Data Entry'!F147 | I57: ='Individual Measure List'!F72 -> 0 | J57: =IF('Savings Summary'!D75=0,"",'Savings Summary'!D75) | K57: =IF('Savings Summary'!F75=0,"",'Savings Summary'!F75) | L57: =IF('Savings Summary'!H75=0,"",'Savings Summary'!H75) | M57: =IF('Savings Summary'!J75=0,"",'Savings Summary'!J75) | N57: =IF('RESULTS kBtu'!H57=0,"",'RESULTS kBtu'!H57) | O57: ='Individual Measure List'!H72 -> #VALUE! | P57: ='Individual Measure List'!J72 -> #NUM! | Q57: ='Individual Measure List'!K72 -> #VALUE! | V57: =C57 | W57: =D57 | X57: =E57 | Y57: =I57 -> 0 | Z57: =J57 | AA57: =K57 | AB57: =L57 | AC57: =M57 | AD57: =O57 -> #VALUE! | AE57: =P57 -> #NUM! | AF57: =Q57 -> #VALUE! | AQ57: ='Individual Measure List'!G72 -> 0
A58: =SUM(B6:B58) -> 38 | B58: =IF(ISTEXT(D58)=TRUE,1,0) -> 1 | C58: ='Individual Measure List'!A73 | D58: ='Individual Measure List'!B73 | E58: ='EEM Data Entry'!D148 | F58: ='EEM Data Entry'!E148 | G58: ='EEM Data Entry'!G148 -> N/A | H58: ='EEM Data Entry'!F148 | I58: ='Individual Measure List'!F73 -> 0 | J58: =IF('Savings Summary'!D76=0,"",'Savings Summary'!D76) | K58: =IF('Savings Summary'!F76=0,"",'Savings Summary'!F76) | L58: =IF('Savings Summary'!H76=0,"",'Savings Summary'!H76) | M58: =IF('Savings Summary'!J76=0,"",'Savings Summary'!J76) | N58: =IF('RESULTS kBtu'!H58=0,"",'RESULTS kBtu'!H58) | O58: ='Individual Measure List'!H73 -> #VALUE! | P58: ='Individual Measure List'!J73 -> #NUM! | Q58: ='Individual Measure List'!K73 -> #VALUE! | V58: =C58 | W58: =D58 | X58: =E58 | Y58: =I58 -> 0 | Z58: =J58 | AA58: =K58 | AB58: =L58 | AC58: =M58 | AD58: =O58 -> #VALUE! | AE58: =P58 -> #NUM! | AF58: =Q58 -> #VALUE! | AQ58: ='Individual Measure List'!G73 -> 0
A59: =SUM(B6:B59) -> 39 | B59: =IF(ISTEXT(D59)=TRUE,1,0) -> 1 | C59: ='Individual Measure List'!A74 | D59: ='Individual Measure List'!B74 | E59: ='EEM Data Entry'!D149 | F59: ='EEM Data Entry'!E149 | G59: ='EEM Data Entry'!G149 -> N/A | H59: ='EEM Data Entry'!F149 | I59: ='Individual Measure List'!F74 -> 0 | J59: =IF('Savings Summary'!D77=0,"",'Savings Summary'!D77) | K59: =IF('Savings Summary'!F77=0,"",'Savings Summary'!F77) | L59: =IF('Savings Summary'!H77=0,"",'Savings Summary'!H77) | M59: =IF('Savings Summary'!J77=0,"",'Savings Summary'!J77) | N59: =IF('RESULTS kBtu'!H59=0,"",'RESULTS kBtu'!H59) | O59: ='Individual Measure List'!H74 -> #VALUE! | P59: ='Individual Measure List'!J74 -> #NUM! | Q59: ='Individual Measure List'!K74 -> #VALUE! | V59: =C59 | W59: =D59 | X59: =E59 | Y59: =I59 -> 0 | Z59: =J59 | AA59: =K59 | AB59: =L59 | AC59: =M59 | AD59: =O59 -> #VALUE! | AE59: =P59 -> #NUM! | AF59: =Q59 -> #VALUE! | AQ59: ='Individual Measure List'!G74 -> 0
A60: =SUM(B6:B60) -> 40 | B60: =IF(ISTEXT(D60)=TRUE,1,0) -> 1 | C60: ='Individual Measure List'!A75 | D60: ='Individual Measure List'!B75 | E60: ='EEM Data Entry'!D150 | F60: ='EEM Data Entry'!E150 | G60: ='EEM Data Entry'!G150 -> N/A | H60: ='EEM Data Entry'!F150 | I60: ='Individual Measure List'!F75 -> 0 | J60: =IF('Savings Summary'!D78=0,"",'Savings Summary'!D78) | K60: =IF('Savings Summary'!F78=0,"",'Savings Summary'!F78) | L60: =IF('Savings Summary'!H78=0,"",'Savings Summary'!H78) | M60: =IF('Savings Summary'!J78=0,"",'Savings Summary'!J78) | N60: =IF('RESULTS kBtu'!H60=0,"",'RESULTS kBtu'!H60) | O60: ='Individual Measure List'!H75 -> #VALUE! | P60: ='Individual Measure List'!J75 -> #NUM! | Q60: ='Individual Measure List'!K75 -> #VALUE! | V60: =C60 | W60: =D60 | X60: =E60 | Y60: =I60 -> 0 | Z60: =J60 | AA60: =K60 | AB60: =L60 | AC60: =M60 | AD60: =O60 -> #VALUE! | AE60: =P60 -> #NUM! | AF60: =Q60 -> #VALUE! | AQ60: ='Individual Measure List'!G75 -> 0
C61: *Please see "Note Regarding Incentives" on first page of financial modeling section | V61: *Please see "Note Regarding Incentives" on first page of financial modeling section
C63: PACKAGE | V63: PACKAGE
E65: Capital Investment | F65: Estimated Incentive* | G65: Incentive Reference | H65: Estimated Net Cost | I65: Annual Energy Cost Savings | J65: Annual Electric Savings (kWh) | K65: Annual Oil Savings (Gal) | L65: Annual Nat. Gas Savings (Therms) | M65: Annual Propane Savings (Gal) | N65: Annual kBTU Savings | O65: Simple Payback (Years) | P65: IRR | Q65: NPV | X65: =E65 -> Capital Investment | Y65: =I65 -> Annual Energy Cost Savings | Z65: =J65 -> Annual Electric Savings (kWh) | AA65: =K65 -> Annual Oil Savings (Gal) | AB65: =L65 -> Annual Nat. Gas Savings (Therms) | AC65: =M65 -> Annual Propane Savings (Gal) | AD65: =O65 -> Simple Payback (Years) | AE65: =P65 -> IRR | AF65: =Q65 -> NPV | AQ65: Annual kBTU Savings
D66: ='Packaged EEMs'!B82 -> RECOMMENDED PACKAGE: Example | E66: =SUM('EEM Data Entry'!D85:D108,'EEM Data Entry'!D110:D123,'EEM Data Entry'!D125:D139,'EEM Data Entry'!D141:D154) -> 0 | F66: =SUM('EEM Data Entry'!E85:E108,'EEM Data Entry'!E110:E123,'EEM Data Entry'!E125:E139,'EEM Data Entry'!E141:E154) -> 0 | H66: =SUM('EEM Data Entry'!F85:F108,'EEM Data Entry'!F110:F123,'EEM Data Entry'!F125:F139,'EEM Data Entry'!F141:F154) -> 0 | I66: ='Packaged EEMs'!F82 -> 0 | J66: ='Cascading Savings'!D87 -> 0 | K66: ='Cascading Savings'!F87 -> 0 | L66: ='Cascading Savings'!H87 -> 0 | M66: ='Cascading Savings'!J87 -> 0 | N66: =IF('RESULTS kBtu'!H66=0,"",'RESULTS kBtu'!H66) | O66: ='Packaged EEMs'!H82 -> #DIV/0! | P66: ='Packaged EEMs'!J82 -> #NUM! | Q66: ='Packaged EEMs'!K82 -> 0 | W66: =D66 -> RECOMMENDED PACKAGE: Example | X66: =E66 -> 0 | Y66: =I66 -> 0 | Z66: =J66 -> 0 | AA66: =K66 -> 0 | AB66: =L66 -> 0 | AC66: =M66 -> 0 | AD66: =O66 -> #DIV/0! | AE66: =P66 -> #NUM! | AF66: =Q66 -> 0 | AQ66: ='Packaged EEMs'!G82 -> 0
D67: *Please see "Note Regarding Incentives" on first page of financial modeling section | W67: =D67 -> *Please see "Note Regarding Incentives" on first page of financial modeling section | X67: =E67 -> 0 | Y67: =I67 -> 0 | Z67: =J67 -> 0 | AA67: =K67 -> 0 | AB67: =L67 -> 0 | AC67: =M67 -> 0 | AD67: =O67 -> 0 | AE67: =P67 -> 0 | AF67: =Q67 -> 0

Sheet RESULTS kBtu
A1: COPY AND PASTE TABLES BELOW INTO REPORT AS APPROPRIATE | P1: NO INCENTIVES
A3: ENVELOPE | P3: ENVELOPE
A5: EEM # | B5: Building Envelope Upgrades | C5: Capital Investment | D5: Estimated Incentive* | E5: Incentive Reference | F5: Estimated Net Cost | G5: Annual Energy Cost Savings | H5: Annual kBTU Savings | I5: Simple Payback (Years) | J5: IRR | K5: NPV | P5: =A5 -> EEM # | Q5: =B5 -> Building Envelope Upgrades | R5: =C5 -> Capital Investment | S5: =G5 -> Annual Energy Cost Savings | T5: =H5 -> Annual kBTU Savings | U5: =I5 -> Simple Payback (Years) | V5: =J5 -> IRR | W5: =K5 -> NPV
A6: ='Individual Measure List'!A8 | B6: ='Individual Measure List'!B8 | C6: ='EEM Data Entry'!D85 | D6: ='EEM Data Entry'!E85 | E6: ='EEM Data Entry'!G85 -> N/A | F6: ='EEM Data Entry'!F85 | G6: ='Individual Measure List'!F8 -> 0 | H6: ='Individual Measure List'!G8 -> 0 | I6: ='Individual Measure List'!H8 -> #VALUE! | J6: ='Individual Measure List'!J8 -> #NUM! | K6: ='Individual Measure List'!K8 -> #VALUE! | M6: Discount Rate | P6: =A6 | Q6: =B6 | R6: =C6 | S6: =G6 -> 0 | T6: =H6 -> 0 | U6: =I6 -> #VALUE! | V6: =J6 -> #NUM! | W6: =K6 -> #VALUE!
A7: ='Individual Measure List'!A9 | B7: ='Individual Measure List'!B9 | C7: ='EEM Data Entry'!D86 | D7: ='EEM Data Entry'!E86 | E7: ='EEM Data Entry'!G86 -> N/A | F7: ='EEM Data Entry'!F86 | G7: ='Individual Measure List'!F9 -> 0 | H7: ='Individual Measure List'!G9 -> 0 | I7: ='Individual Measure List'!H9 -> #VALUE! | J7: ='Individual Measure List'!J9 -> #NUM! | K7: ='Individual Measure List'!K9 -> #VALUE! | M7: Inflation | N7: ='Interest Rate'!C10 -> 0.034 | P7: =A7 | Q7: =B7 | R7: =C7 | S7: =G7 -> 0 | T7: =H7 -> 0 | U7: =I7 -> #VALUE! | V7: =J7 -> #NUM! | W7: =K7 -> #VALUE!
A8: ='Individual Measure List'!A10 | B8: ='Individual Measure List'!B10 | C8: ='EEM Data Entry'!D87 | D8: ='EEM Data Entry'!E87 | E8: ='EEM Data Entry'!G87 -> N/A | F8: ='EEM Data Entry'!F87 | G8: ='Individual Measure List'!F10 -> 0 | H8: ='Individual Measure List'!G10 -> 0 | I8: ='Individual Measure List'!H10 -> #VALUE! | J8: ='Individual Measure List'!J10 -> #NUM! | K8: ='Individual Measure List'!K10 -> #VALUE! | M8: Nominal Escalation Rate | N8: ='Interest Rate'!C12 -> 0 | P8: =A8 | Q8: =B8 | R8: =C8 | S8: =G8 -> 0 | T8: =H8 -> 0 | U8: =I8 -> #VALUE! | V8: =J8 -> #NUM! | W8: =K8 -> #VALUE!
A9: ='Individual Measure List'!A11 | B9: ='Individual Measure List'!B11 | C9: ='EEM Data Entry'!D88 | D9: ='EEM Data Entry'!E88 | E9: ='EEM Data Entry'!G88 -> N/A | F9: ='EEM Data Entry'!F88 | G9: ='Individual Measure List'!F11 -> 0 | H9: ='Individual Measure List'!G11 -> 0 | I9: ='Individual Measure List'!H11 -> #VALUE! | J9: ='Individual Measure List'!J11 -> #NUM! | K9: ='Individual Measure List'!K11 -> #VALUE! | M9: Discount Rate | N9: ='Interest Rate'!C14 -> 0.05 | P9: =A9 | Q9: =B9 | R9: =C9 | S9: =G9 -> 0 | T9: =H9 -> 0 | U9: =I9 -> #VALUE! | V9: =J9 -> #NUM! | W9: =K9 -> #VALUE!
A10: ='Individual Measure List'!A12 | B10: ='Individual Measure List'!B12 | C10: ='EEM Data Entry'!D89 | D10: ='EEM Data Entry'!E89 | E10: ='EEM Data Entry'!G89 -> N/A | F10: ='EEM Data Entry'!F89 | G10: ='Individual Measure List'!F12 -> 0 | H10: ='Individual Measure List'!G12 -> 0 | I10: ='Individual Measure List'!H12 -> #VALUE! | J10: ='Individual Measure List'!J12 -> #NUM! | K10: ='Individual Measure List'!K12 -> #VALUE! | M10: Adjusted Discount Rate | N10: ='Interest Rate'!B17 -> 0.05 | P10: =A10 | Q10: =B10 | R10: =C10 | S10: =G10 -> 0 | T10: =H10 -> 0 | U10: =I10 -> #VALUE! | V10: =J10 -> #NUM! | W10: =K10 -> #VALUE!
A11: ='Individual Measure List'!A13 | B11: ='Individual Measure List'!B13 | C11: ='EEM Data Entry'!D90 | D11: ='EEM Data Entry'!E90 | E11: ='EEM Data Entry'!G90 -> N/A | F11: ='EEM Data Entry'!F90 | G11: ='Individual Measure List'!F13 -> 0 | H11: ='Individual Measure List'!G13 -> 0 | I11: ='Individual Measure List'!H13 -> #VALUE! | J11: ='Individual Measure List'!J13 -> #NUM! | K11: ='Individual Measure List'!K13 -> #VALUE! | M11: *Calculated using the Nation Institute of Standards and Technology (NIST) Energy Escalation Rate Calculator | P11: =A11 | Q11: =B11 | R11: =C11 | S11: =G11 -> 0 | T11: =H11 -> 0 | U11: =I11 -> #VALUE! | V11: =J11 -> #NUM! | W11: =K11 -> #VALUE!
A12: ='Individual Measure List'!A14 | B12: ='Individual Measure List'!B14 | C12: ='EEM Data Entry'!D91 | D12: ='EEM Data Entry'!E91 | E12: ='EEM Data Entry'!G91 -> N/A | F12: ='EEM Data Entry'!F91 | G12: ='Individual Measure List'!F14 -> 0 | H12: ='Individual Measure List'!G14 -> 0 | I12: ='Individual Measure List'!H14 -> #VALUE! | J12: ='Individual Measure List'!J14 -> #NUM! | K12: ='Individual Measure List'!K14 -> #VALUE! | P12: =A12 | Q12: =B12 | R12: =C12 | S12: =G12 -> 0 | T12: =H12 -> 0 | U12: =I12 -> #VALUE! | V12: =J12 -> #NUM! | W12: =K12 -> #VALUE!
A13: ='Individual Measure List'!A15 | B13: ='Individual Measure List'!B15 | C13: ='EEM Data Entry'!D92 | D13: ='EEM Data Entry'!E92 | E13: ='EEM Data Entry'!G92 -> N/A | F13: ='EEM Data Entry'!F92 | G13: ='Individual Measure List'!F15 -> 0 | H13: ='Individual Measure List'!G15 -> 0 | I13: ='Individual Measure List'!H15 -> #VALUE! | J13: ='Individual Measure List'!J15 -> #NUM! | K13: ='Individual Measure List'!K15 -> #VALUE! | P13: =A13 | Q13: =B13 | R13: =C13 | S13: =G13 -> 0 | T13: =H13 -> 0 | U13: =I13 -> #VALUE! | V13: =J13 -> #NUM! | W13: =K13 -> #VALUE!
A14: ='Individual Measure List'!A16 | B14: ='Individual Measure List'!B16 | C14: ='EEM Data Entry'!D93 | D14: ='EEM Data Entry'!E93 | E14: ='EEM Data Entry'!G93 -> N/A | F14: ='EEM Data Entry'!F93 | G14: ='Individual Measure List'!F16 -> 0 | H14: ='Individual Measure List'!G16 -> 0 | I14: ='Individual Measure List'!H16 -> #VALUE! | J14: ='Individual Measure List'!J16 -> #NUM! | K14: ='Individual Measure List'!K16 -> #VALUE! | P14: =A14 | Q14: =B14 | R14: =C14 | S14: =G14 -> 0 | T14: =H14 -> 0 | U14: =I14 -> #VALUE! | V14: =J14 -> #NUM! | W14: =K14 -> #VALUE!
A15: ='Individual Measure List'!A17 | B15: ='Individual Measure List'!B17 | C15: ='EEM Data Entry'!D94 | D15: ='EEM Data Entry'!E94 | E15: ='EEM Data Entry'!G94 -> N/A | F15: ='EEM Data Entry'!F94 | G15: ='Individual Measure List'!F17 -> 0 | H15: ='Individual Measure List'!G17 -> 0 | I15: ='Individual Measure List'!H17 -> #VALUE! | J15: ='Individual Measure List'!J17 -> #NUM! | K15: ='Individual Measure List'!K17 -> #VALUE! | P15: =A15 | Q15: =B15 | R15: =C15 | S15: =G15 -> 0 | T15: =H15 -> 0 | U15: =I15 -> #VALUE! | V15: =J15 -> #NUM! | W15: =K15 -> #VALUE!
A16: *Please see "Note Regarding Incentives" on first page of financial modeling section | P16: *Please see "Note Regarding Incentives" on first page of financial modeling section
A18: MECHANICAL | P18: MECHANICAL
A20: EEM # | B20: Mechanical System Upgrades | C20: Capital Investment | D20: Estimated Incentive* | E20: Incentive Reference | F20: Estimated Net Cost | G20: Annual Energy Cost Savings | H20: Annual kBTU Savings | I20: Simple Payback (Years) | J20: IRR | K20: NPV | P20: =A20 -> EEM # | Q20: =B20 -> Mechanical System Upgrades | R20: =C20 -> Capital Investment | S20: =G20 -> Annual Energy Cost Savings | T20: =H20 -> Annual kBTU Savings | U20: =I20 -> Simple Payback (Years) | V20: =J20 -> IRR | W20: =K20 -> NPV
A21: ='Individual Measure List'!A33 | B21: ='Individual Measure List'!B33 | C21: ='EEM Data Entry'!D110 | D21: ='EEM Data Entry'!E110 | E21: ='EEM Data Entry'!G110 -> N/A | F21: ='EEM Data Entry'!F110 | G21: ='Individual Measure List'!F33 -> 0 | H21: ='Individual Measure List'!G33 -> 0 | I21: ='Individual Measure List'!H33 -> #VALUE! | J21: ='Individual Measure List'!J33 -> #NUM! | K21: ='Individual Measure List'!K33 -> #VALUE! | P21: =A21 | Q21: =B21 | R21: =C21 | S21: =G21 -> 0 | T21: =H21 -> 0 | U21: =I21 -> #VALUE! | V21: =J21 -> #NUM! | W21: =K21 -> #VALUE!
A22: ='Individual Measure List'!A34 | B22: ='Individual Measure List'!B34 | C22: ='EEM Data Entry'!D111 | D22: ='EEM Data Entry'!E111 | E22: ='EEM Data Entry'!G111 -> N/A | F22: ='EEM Data Entry'!F111 | G22: ='Individual Measure List'!F34 -> 0 | H22: ='Individual Measure List'!G34 -> 0 | I22: ='Individual Measure List'!H34 -> #VALUE! | J22: ='Individual Measure List'!J34 -> #NUM! | K22: ='Individual Measure List'!K34 -> #VALUE! | P22: =A22 | Q22: =B22 | R22: =C22 | S22: =G22 -> 0 | T22: =H22 -> 0 | U22: =I22 -> #VALUE! | V22: =J22 -> #NUM! | W22: =K22 -> #VALUE!
A23: ='Individual Measure List'!A35 | B23: ='Individual Measure List'!B35 | C23: ='EEM Data Entry'!D112 | D23: ='EEM Data Entry'!E112 | E23: ='EEM Data Entry'!G112 -> N/A | F23: ='EEM Data Entry'!F112 | G23: ='Individual Measure List'!F35 -> 0 | H23: ='Individual Measure List'!G35 -> 0 | I23: ='Individual Measure List'!H35 -> #VALUE! | J23: ='Individual Measure List'!J35 -> #NUM! | K23: ='Individual Measure List'!K35 -> #VALUE! | P23: =A23 | Q23: =B23 | R23: =C23 | S23: =G23 -> 0 | T23: =H23 -> 0 | U23: =I23 -> #VALUE! | V23: =J23 -> #NUM! | W23: =K23 -> #VALUE!
A24: ='Individual Measure List'!A36 | B24: ='Individual Measure List'!B36 | C24: ='EEM Data Entry'!D113 | D24: ='EEM Data Entry'!E113 | E24: ='EEM Data Entry'!G113 -> N/A | F24: ='EEM Data Entry'!F113 | G24: ='Individual Measure List'!F36 -> 0 | H24: ='Individual Measure List'!G36 -> 0 | I24: ='Individual Measure List'!H36 -> #VALUE! | J24: ='Individual Measure List'!J36 -> #NUM! | K24: ='Individual Measure List'!K36 -> #VALUE! | P24: =A24 | Q24: =B24 | R24: =C24 | S24: =G24 -> 0 | T24: =H24 -> 0 | U24: =I24 -> #VALUE! | V24: =J24 -> #NUM! | W24: =K24 -> #VALUE!
A25: ='Individual Measure List'!A37 | B25: ='Individual Measure List'!B37 | C25: ='EEM Data Entry'!D114 | D25: ='EEM Data Entry'!E114 | E25: ='EEM Data Entry'!G114 -> N/A | F25: ='EEM Data Entry'!F114 | G25: ='Individual Measure List'!F37 -> 0 | H25: ='Individual Measure List'!G37 -> 0 | I25: ='Individual Measure List'!H37 -> #VALUE! | J25: ='Individual Measure List'!J37 -> #NUM! | K25: ='Individual Measure List'!K37 -> #VALUE! | P25: =A25 | Q25: =B25 | R25: =C25 | S25: =G25 -> 0 | T25: =H25 -> 0 | U25: =I25 -> #VALUE! | V25: =J25 -> #NUM! | W25: =K25 -> #VALUE!
A26: ='Individual Measure List'!A38 | B26: ='Individual Measure List'!B38 | C26: ='EEM Data Entry'!D115 | D26: ='EEM Data Entry'!E115 | E26: ='EEM Data Entry'!G115 -> N/A | F26: ='EEM Data Entry'!F115 | G26: ='Individual Measure List'!F38 -> 0 | H26: ='Individual Measure List'!G38 -> 0 | I26: ='Individual Measure List'!H38 -> #VALUE! | J26: ='Individual Measure List'!J38 -> #NUM! | K26: ='Individual Measure List'!K38 -> #VALUE! | P26: =A26 | Q26: =B26 | R26: =C26 | S26: =G26 -> 0 | T26: =H26 -> 0 | U26: =I26 -> #VALUE! | V26: =J26 -> #NUM! | W26: =K26 -> #VALUE!
A27: ='Individual Measure List'!A39 | B27: ='Individual Measure List'!B39 | C27: ='EEM Data Entry'!D116 | D27: ='EEM Data Entry'!E116 | E27: ='EEM Data Entry'!G116 -> N/A | F27: ='EEM Data Entry'!F116 | G27: ='Individual Measure List'!F39 -> 0 | H27: ='Individual Measure List'!G39 -> 0 | I27: ='Individual Measure List'!H39 -> #VALUE! | J27: ='Individual Measure List'!J39 -> #NUM! | K27: ='Individual Measure List'!K39 -> #VALUE! | P27: =A27 | Q27: =B27 | R27: =C27 | S27: =G27 -> 0 | T27: =H27 -> 0 | U27: =I27 -> #VALUE! | V27: =J27 -> #NUM! | W27: =K27 -> #VALUE!
A28: ='Individual Measure List'!A40 | B28: ='Individual Measure List'!B40 | C28: ='EEM Data Entry'!D117 | D28: ='EEM Data Entry'!E117 | E28: ='EEM Data Entry'!G117 -> N/A | F28: ='EEM Data Entry'!F117 | G28: ='Individual Measure List'!F40 -> 0 | H28: ='Individual Measure List'!G40 -> 0 | I28: ='Individual Measure List'!H40 -> #VALUE! | J28: ='Individual Measure List'!J40 -> #NUM! | K28: ='Individual Measure List'!K40 -> #VALUE! | P28: =A28 | Q28: =B28 | R28: =C28 | S28: =G28 -> 0 | T28: =H28 -> 0 | U28: =I28 -> #VALUE! | V28: =J28 -> #NUM! | W28: =K28 -> #VALUE!
A29: ='Individual Measure List'!A41 | B29: ='Individual Measure List'!B41 | C29: ='EEM Data Entry'!D118 | D29: ='EEM Data Entry'!E118 | E29: ='EEM Data Entry'!G118 -> N/A | F29: ='EEM Data Entry'!F118 | G29: ='Individual Measure List'!F41 -> 0 | H29: ='Individual Measure List'!G41 -> 0 | I29: ='Individual Measure List'!H41 -> #VALUE! | J29: ='Individual Measure List'!J41 -> #NUM! | K29: ='Individual Measure List'!K41 -> #VALUE! | P29: =A29 | Q29: =B29 | R29: =C29 | S29: =G29 -> 0 | T29: =H29 -> 0 | U29: =I29 -> #VALUE! | V29: =J29 -> #NUM! | W29: =K29 -> #VALUE!
A30: ='Individual Measure List'!A42 | B30: ='Individual Measure List'!B42 | C30: ='EEM Data Entry'!D119 | D30: ='EEM Data Entry'!E119 | E30: ='EEM Data Entry'!G119 -> N/A | F30: ='EEM Data Entry'!F119 | G30: ='Individual Measure List'!F42 -> 0 | H30: ='Individual Measure List'!G42 -> 0 | I30: ='Individual Measure List'!H42 -> #VALUE! | J30: ='Individual Measure List'!J42 -> #NUM! | K30: ='Individual Measure List'!K42 -> #VALUE! | P30: =A30 | Q30: =B30 | R30: =C30 | S30: =G30 -> 0 | T30: =H30 -> 0 | U30: =I30 -> #VALUE! | V30: =J30 -> #NUM! | W30: =K30 -> #VALUE!
A31: *Please see "Note Regarding Incentives" on first page of financial modeling section | P31: *Please see "Note Regarding Incentives" on first page of financial modeling section
A33: APPLIANCES & LIGHTING | P33: APPLIANCES & LIGHTING
A35: EEM # | B35: Appliances & Lighting Upgrades | C35: Capital Investment | D35: Estimated Incentive* | E35: Incentive Reference | F35: Estimated Net Cost | G35: Annual Energy Cost Savings | H35: Annual kBTU Savings | I35: Simple Payback (Years) | J35: IRR | K35: NPV | P35: =A35 -> EEM # | Q35: =B35 -> Appliances & Lighting Upgrades | R35: =C35 -> Capital Investment | S35: =G35 -> Annual Energy Cost Savings | T35: =H35 -> Annual kBTU Savings | U35: =I35 -> Simple Payback (Years) | V35: =J35 -> IRR | W35: =K35 -> NPV
A36: ='Individual Measure List'!A49 | B36: ='Individual Measure List'!B49 | C36: ='EEM Data Entry'!D125 | D36: ='EEM Data Entry'!E125 | E36: ='EEM Data Entry'!G125 -> N/A | F36: ='EEM Data Entry'!F125 | G36: ='Individual Measure List'!F49 -> 0 | H36: ='Individual Measure List'!G49 -> 0 | I36: ='Individual Measure List'!H49 -> #VALUE! | J36: ='Individual Measure List'!J49 -> #NUM! | K36: ='Individual Measure List'!K49 -> #VALUE! | P36: =A36 | Q36: =B36 | R36: =C36 | S36: =G36 -> 0 | T36: =H36 -> 0 | U36: =I36 -> #VALUE! | V36: =J36 -> #NUM! | W36: =K36 -> #VALUE!
A37: ='Individual Measure List'!A50 | B37: ='Individual Measure List'!B50 | C37: ='EEM Data Entry'!D126 | D37: ='EEM Data Entry'!E126 | E37: ='EEM Data Entry'!G126 -> N/A | F37: ='EEM Data Entry'!F126 | G37: ='Individual Measure List'!F50 -> 0 | H37: ='Individual Measure List'!G50 -> 0 | I37: ='Individual Measure List'!H50 -> #VALUE! | J37: ='Individual Measure List'!J50 -> #NUM! | K37: ='Individual Measure List'!K50 -> #VALUE! | P37: =A37 | Q37: =B37 | R37: =C37 | S37: =G37 -> 0 | T37: =H37 -> 0 | U37: =I37 -> #VALUE! | V37: =J37 -> #NUM! | W37: =K37 -> #VALUE!
A38: ='Individual Measure List'!A51 | B38: ='Individual Measure List'!B51 | C38: ='EEM Data Entry'!D127 | D38: ='EEM Data Entry'!E127 | E38: ='EEM Data Entry'!G127 -> N/A | F38: ='EEM Data Entry'!F127 | G38: ='Individual Measure List'!F51 -> 0 | H38: ='Individual Measure List'!G51 -> 0 | I38: ='Individual Measure List'!H51 -> #VALUE! | J38: ='Individual Measure List'!J51 -> #NUM! | K38: ='Individual Measure List'!K51 -> #VALUE! | P38: =A38 | Q38: =B38 | R38: =C38 | S38: =G38 -> 0 | T38: =H38 -> 0 | U38: =I38 -> #VALUE! | V38: =J38 -> #NUM! | W38: =K38 -> #VALUE!
A39: ='Individual Measure List'!A52 | B39: ='Individual Measure List'!B52 | C39: ='EEM Data Entry'!D128 | D39: ='EEM Data Entry'!E128 | E39: ='EEM Data Entry'!G128 -> N/A | F39: ='EEM Data Entry'!F128 | G39: ='Individual Measure List'!F52 -> 0 | H39: ='Individual Measure List'!G52 -> 0 | I39: ='Individual Measure List'!H52 -> #VALUE! | J39: ='Individual Measure List'!J52 -> #NUM! | K39: ='Individual Measure List'!K52 -> #VALUE! | P39: =A39 | Q39: =B39 | R39: =C39 | S39: =G39 -> 0 | T39: =H39 -> 0 | U39: =I39 -> #VALUE! | V39: =J39 -> #NUM! | W39: =K39 -> #VALUE!
A40: ='Individual Measure List'!A53 | B40: ='Individual Measure List'!B53 | C40: ='EEM Data Entry'!D129 | D40: ='EEM Data Entry'!E129 | E40: ='EEM Data Entry'!G129 -> N/A | F40: ='EEM Data Entry'!F129 | G40: ='Individual Measure List'!F53 -> 0 | H40: ='Individual Measure List'!G53 -> 0 | I40: ='Individual Measure List'!H53 -> #VALUE! | J40: ='Individual Measure List'!J53 -> #NUM! | K40: ='Individual Measure List'!K53 -> #VALUE! | P40: =A40 | Q40: =B40 | R40: =C40 | S40: =G40 -> 0 | T40: =H40 -> 0 | U40: =I40 -> #VALUE! | V40: =J40 -> #NUM! | W40: =K40 -> #VALUE!
A41: ='Individual Measure List'!A54 | B41: ='Individual Measure List'!B54 | C41: ='EEM Data Entry'!D130 | D41: ='EEM Data Entry'!E130 | E41: ='EEM Data Entry'!G130 -> N/A | F41: ='EEM Data Entry'!F130 | G41: ='Individual Measure List'!F54 -> 0 | H41: ='Individual Measure List'!G54 -> 0 | I41: ='Individual Measure List'!H54 -> #VALUE! | J41: ='Individual Measure List'!J54 -> #NUM! | K41: ='Individual Measure List'!K54 -> #VALUE! | P41: =A41 | Q41: =B41 | R41: =C41 | S41: =G41 -> 0 | T41: =H41 -> 0 | U41: =I41 -> #VALUE! | V41: =J41 -> #NUM! | W41: =K41 -> #VALUE!
A42: ='Individual Measure List'!A55 | B42: ='Individual Measure List'!B55 | C42: ='EEM Data Entry'!D131 | D42: ='EEM Data Entry'!E131 | E42: ='EEM Data Entry'!G131 -> N/A | F42: ='EEM Data Entry'!F131 | G42: ='Individual Measure List'!F55 -> 0 | H42: ='Individual Measure List'!G55 -> 0 | I42: ='Individual Measure List'!H55 -> #VALUE! | J42: ='Individual Measure List'!J55 -> #NUM! | K42: ='Individual Measure List'!K55 -> #VALUE! | P42: =A42 | Q42: =B42 | R42: =C42 | S42: =G42 -> 0 | T42: =H42 -> 0 | U42: =I42 -> #VALUE! | V42: =J42 -> #NUM! | W42: =K42 -> #VALUE!
A43: ='Individual Measure List'!A56 | B43: ='Individual Measure List'!B56 | C43: ='EEM Data Entry'!D132 | D43: ='EEM Data Entry'!E132 | E43: ='EEM Data Entry'!G132 -> N/A | F43: ='EEM Data Entry'!F132 | G43: ='Individual Measure List'!F56 -> 0 | H43: ='Individual Measure List'!G56 -> 0 | I43: ='Individual Measure List'!H56 -> #VALUE! | J43: ='Individual Measure List'!J56 -> #NUM! | K43: ='Individual Measure List'!K56 -> #VALUE! | P43: =A43 | Q43: =B43 | R43: =C43 | S43: =G43 -> 0 | T43: =H43 -> 0 | U43: =I43 -> #VALUE! | V43: =J43 -> #NUM! | W43: =K43 -> #VALUE!
A44: ='Individual Measure List'!A57 | B44: ='Individual Measure List'!B57 | C44: ='EEM Data Entry'!D133 | D44: ='EEM Data Entry'!E133 | E44: ='EEM Data Entry'!G133 -> N/A | F44: ='EEM Data Entry'!F133 | G44: ='Individual Measure List'!F57 -> 0 | H44: ='Individual Measure List'!G57 -> 0 | I44: ='Individual Measure List'!H57 -> #VALUE! | J44: ='Individual Measure List'!J57 -> #NUM! | K44: ='Individual Measure List'!K57 -> #VALUE! | P44: =A44 | Q44: =B44 | R44: =C44 | S44: =G44 -> 0 | T44: =H44 -> 0 | U44: =I44 -> #VALUE! | V44: =J44 -> #NUM! | W44: =K44 -> #VALUE!
A45: ='Individual Measure List'!A58 | B45: ='Individual Measure List'!B58 | C45: ='EEM Data Entry'!D134 | D45: ='EEM Data Entry'!E134 | E45: ='EEM Data Entry'!G134 -> N/A | F45: ='EEM Data Entry'!F134 | G45: ='Individual Measure List'!F58 -> 0 | H45: ='Individual Measure List'!G58 -> 0 | I45: ='Individual Measure List'!H58 -> #VALUE! | J45: ='Individual Measure List'!J58 -> #NUM! | K45: ='Individual Measure List'!K58 -> #VALUE! | P45: =A45 | Q45: =B45 | R45: =C45 | S45: =G45 -> 0 | T45: =H45 -> 0 | U45: =I45 -> #VALUE! | V45: =J45 -> #NUM! | W45: =K45 -> #VALUE!
A46: *Please see "Note Regarding Incentives" on first page of financial modeling section | P46: *Please see "Note Regarding Incentives" on first page of financial modeling section
A48: RENEWABLE | P48: RENEWABLE
A50: EEM # | B50: Renewable System Upgrades | C50: Capital Investment | D50: Estimated Incentive* | E50: Incentive Reference | F50: Estimated Net Cost | G50: Annual Energy Cost Savings | H50: Annual kBTU Savings | I50: Simple Payback (Years) | J50: IRR | K50: NPV | P50: =A50 -> EEM # | Q50: =B50 -> Renewable System Upgrades | R50: =C50 -> Capital Investment | S50: =G50 -> Annual Energy Cost Savings | T50: =H50 -> Annual kBTU Savings | U50: =I50 -> Simple Payback (Years) | V50: =J50 -> IRR | W50: =K50 -> NPV
A51: ='Individual Measure List'!A66 | B51: ='Individual Measure List'!B66 | C51: ='EEM Data Entry'!D141 | D51: ='EEM Data Entry'!E141 | E51: ='EEM Data Entry'!G141 -> N/A | F51: ='EEM Data Entry'!F141 | G51: ='Individual Measure List'!F66 -> 0 | H51: ='Individual Measure List'!G66 -> 0 | I51: ='Individual Measure List'!H66 -> #VALUE! | J51: ='Individual Measure List'!J66 -> #NUM! | K51: ='Individual Measure List'!K66 -> #VALUE! | P51: =A51 | Q51: =B51 | R51: =C51 | S51: =G51 -> 0 | T51: =H51 -> 0 | U51: =I51 -> #VALUE! | V51: =J51 -> #NUM! | W51: =K51 -> #VALUE!
A52: ='Individual Measure List'!A67 | B52: ='Individual Measure List'!B67 | C52: ='EEM Data Entry'!D142 | D52: ='EEM Data Entry'!E142 | E52: ='EEM Data Entry'!G142 -> N/A | F52: ='EEM Data Entry'!F142 | G52: ='Individual Measure List'!F67 -> 0 | H52: ='Individual Measure List'!G67 -> 0 | I52: ='Individual Measure List'!H67 -> #VALUE! | J52: ='Individual Measure List'!J67 -> #NUM! | K52: ='Individual Measure List'!K67 -> #VALUE! | P52: =A52 | Q52: =B52 | R52: =C52 | S52: =G52 -> 0 | T52: =H52 -> 0 | U52: =I52 -> #VALUE! | V52: =J52 -> #NUM! | W52: =K52 -> #VALUE!
A53: ='Individual Measure List'!A68 | B53: ='Individual Measure List'!B68 | C53: ='EEM Data Entry'!D143 | D53: ='EEM Data Entry'!E143 | E53: ='EEM Data Entry'!G143 -> N/A | F53: ='EEM Data Entry'!F143 | G53: ='Individual Measure List'!F68 -> 0 | H53: ='Individual Measure List'!G68 -> 0 | I53: ='Individual Measure List'!H68 -> #VALUE! | J53: ='Individual Measure List'!J68 -> #NUM! | K53: ='Individual Measure List'!K68 -> #VALUE! | P53: =A53 | Q53: =B53 | R53: =C53 | S53: =G53 -> 0 | T53: =H53 -> 0 | U53: =I53 -> #VALUE! | V53: =J53 -> #NUM! | W53: =K53 -> #VALUE!
A54: ='Individual Measure List'!A69 | B54: ='Individual Measure List'!B69 | C54: ='EEM Data Entry'!D144 | D54: ='EEM Data Entry'!E144 | E54: ='EEM Data Entry'!G144 -> N/A | F54: ='EEM Data Entry'!F144 | G54: ='Individual Measure List'!F69 -> 0 | H54: ='Individual Measure List'!G69 -> 0 | I54: ='Individual Measure List'!H69 -> #VALUE! | J54: ='Individual Measure List'!J69 -> #NUM! | K54: ='Individual Measure List'!K69 -> #VALUE! | P54: =A54 | Q54: =B54 | R54: =C54 | S54: =G54 -> 0 | T54: =H54 -> 0 | U54: =I54 -> #VALUE! | V54: =J54 -> #NUM! | W54: =K54 -> #VALUE!
A55: ='Individual Measure List'!A70 | B55: ='Individual Measure List'!B70 | C55: ='EEM Data Entry'!D145 | D55: ='EEM Data Entry'!E145 | E55: ='EEM Data Entry'!G145 -> N/A | F55: ='EEM Data Entry'!F145 | G55: ='Individual Measure List'!F70 -> 0 | H55: ='Individual Measure List'!G70 -> 0 | I55: ='Individual Measure List'!H70 -> #VALUE! | J55: ='Individual Measure List'!J70 -> #NUM! | K55: ='Individual Measure List'!K70 -> #VALUE! | P55: =A55 | Q55: =B55 | R55: =C55 | S55: =G55 -> 0 | T55: =H55 -> 0 | U55: =I55 -> #VALUE! | V55: =J55 -> #NUM! | W55: =K55 -> #VALUE!
A56: ='Individual Measure List'!A71 | B56: ='Individual Measure List'!B71 | C56: ='EEM Data Entry'!D146 | D56: ='EEM Data Entry'!E146 | E56: ='EEM Data Entry'!G146 -> N/A | F56: ='EEM Data Entry'!F146 | G56: ='Individual Measure List'!F71 -> 0 | H56: ='Individual Measure List'!G71 -> 0 | I56: ='Individual Measure List'!H71 -> #VALUE! | J56: ='Individual Measure List'!J71 -> #NUM! | K56: ='Individual Measure List'!K71 -> #VALUE! | P56: =A56 | Q56: =B56 | R56: =C56 | S56: =G56 -> 0 | T56: =H56 -> 0 | U56: =I56 -> #VALUE! | V56: =J56 -> #NUM! | W56: =K56 -> #VALUE!
A57: ='Individual Measure List'!A72 | B57: ='Individual Measure List'!B72 | C57: ='EEM Data Entry'!D147 | D57: ='EEM Data Entry'!E147 | E57: ='EEM Data Entry'!G147 -> N/A | F57: ='EEM Data Entry'!F147 | G57: ='Individual Measure List'!F72 -> 0 | H57: ='Individual Measure List'!G72 -> 0 | I57: ='Individual Measure List'!H72 -> #VALUE! | J57: ='Individual Measure List'!J72 -> #NUM! | K57: ='Individual Measure List'!K72 -> #VALUE! | P57: =A57 | Q57: =B57 | R57: =C57 | S57: =G57 -> 0 | T57: =H57 -> 0 | U57: =I57 -> #VALUE! | V57: =J57 -> #NUM! | W57: =K57 -> #VALUE!
A58: ='Individual Measure List'!A73 | B58: ='Individual Measure List'!B73 | C58: ='EEM Data Entry'!D148 | D58: ='EEM Data Entry'!E148 | E58: ='EEM Data Entry'!G148 -> N/A | F58: ='EEM Data Entry'!F148 | G58: ='Individual Measure List'!F73 -> 0 | H58: ='Individual Measure List'!G73 -> 0 | I58: ='Individual Measure List'!H73 -> #VALUE! | J58: ='Individual Measure List'!J73 -> #NUM! | K58: ='Individual Measure List'!K73 -> #VALUE! | P58: =A58 | Q58: =B58 | R58: =C58 | S58: =G58 -> 0 | T58: =H58 -> 0 | U58: =I58 -> #VALUE! | V58: =J58 -> #NUM! | W58: =K58 -> #VALUE!
A59: ='Individual Measure List'!A74 | B59: ='Individual Measure List'!B74 | C59: ='EEM Data Entry'!D149 | D59: ='EEM Data Entry'!E149 | E59: ='EEM Data Entry'!G149 -> N/A | F59: ='EEM Data Entry'!F149 | G59: ='Individual Measure List'!F74 -> 0 | H59: ='Individual Measure List'!G74 -> 0 | I59: ='Individual Measure List'!H74 -> #VALUE! | J59: ='Individual Measure List'!J74 -> #NUM! | K59: ='Individual Measure List'!K74 -> #VALUE! | P59: =A59 | Q59: =B59 | R59: =C59 | S59: =G59 -> 0 | T59: =H59 -> 0 | U59: =I59 -> #VALUE! | V59: =J59 -> #NUM! | W59: =K59 -> #VALUE!
A60: ='Individual Measure List'!A75 | B60: ='Individual Measure List'!B75 | C60: ='EEM Data Entry'!D150 | D60: ='EEM Data Entry'!E150 | E60: ='EEM Data Entry'!G150 -> N/A | F60: ='EEM Data Entry'!F150 | G60: ='Individual Measure List'!F75 -> 0 | H60: ='Individual Measure List'!G75 -> 0 | I60: ='Individual Measure List'!H75 -> #VALUE! | J60: ='Individual Measure List'!J75 -> #NUM! | K60: ='Individual Measure List'!K75 -> #VALUE! | P60: =A60 | Q60: =B60 | R60: =C60 | S60: =G60 -> 0 | T60: =H60 -> 0 | U60: =I60 -> #VALUE! | V60: =J60 -> #NUM! | W60: =K60 -> #VALUE!
A61: *Please see "Note Regarding Incentives" on first page of financial modeling section | P61: *Please see "Note Regarding Incentives" on first page of financial modeling section
A63: PACKAGE | P63: PACKAGE
C65: Capital Investment | D65: Estimated Incentive* | E65: Incentive Reference | F65: Estimated Net Cost | G65: Annual Energy Cost Savings | H65: Annual kBTU Savings | I65: Simple Payback (Years) | J65: IRR | K65: NPV | R65: =C65 -> Capital Investment | S65: =G65 -> Annual Energy Cost Savings | T65: =H65 -> Annual kBTU Savings | U65: =I65 -> Simple Payback (Years) | V65: =J65 -> IRR | W65: =K65 -> NPV
B66: ='Packaged EEMs'!B82 -> RECOMMENDED PACKAGE: Example | C66: =SUM('EEM Data Entry'!D85:D108,'EEM Data Entry'!D110:D123,'EEM Data Entry'!D125:D139,'EEM Data Entry'!D141:D154) -> 0 | D66: =SUM('EEM Data Entry'!E85:E108,'EEM Data Entry'!E110:E123,'EEM Data Entry'!E125:E139,'EEM Data Entry'!E141:E154) -> 0 | F66: =SUM('EEM Data Entry'!F85:F108,'EEM Data Entry'!F110:F123,'EEM Data Entry'!F125:F139,'EEM Data Entry'!F141:F154) -> 0 | G66: ='Packaged EEMs'!F82 -> 0 | H66: ='Packaged EEMs'!G82 -> 0 | I66: ='Packaged EEMs'!H82 -> #DIV/0! | J66: ='Packaged EEMs'!J82 -> #NUM! | K66: ='Packaged EEMs'!K82 -> 0 | Q66: =B66 -> RECOMMENDED PACKAGE: Example | R66: =C66 -> 0 | S66: =G66 -> 0 | T66: =H66 -> 0 | U66: =I66 -> #DIV/0! | V66: =J66 -> #NUM! | W66: =K66 -> 0
B67: *Please see "Note Regarding Incentives" on first page of financial modeling section | Q67: *Please see "Note Regarding Incentives" on first page of financial modeling section

Sheet RESULTS by Fuel
C1: COPY AND PASTE TABLES BELOW INTO REPORT AS APPROPRIATE | U1: NO INCENTIVES
C3: ENVELOPE | I3: conversions | J3: 0.29307103 | K3: 0.0072790267 | L3: 0.01 | M3: 0.010928961 | U3: ENVELOPE | X3: conversions | Y3: 0.29307103 | Z3: 0.0072790267 | AA3: 0.01 | AB3: 0.010928961
C5: EEM # | D5: Building Envelope Upgrades | E5: Capital Investment | F5: Estimated Incentive* | G5: Incentive Reference | H5: Estimated Net Cost | I5: Annual Energy Cost Savings | J5: Annual Electric Savings (kWh) | K5: Annual Oil Savings (Gal) | L5: Annual Nat. Gas Savings (Therms) | M5: Annual Propane Savings (Gal) | N5: Simple Payback (Years) | O5: IRR | P5: NPV | U5: =C5 -> EEM # | V5: =D5 -> Building Envelope Upgrades | W5: =E5 -> Capital Investment | X5: =I5 -> Annual Energy Cost Savings | Y5: =J5 -> Annual Electric Savings (kWh) | Z5: =K5 -> Annual Oil Savings (Gal) | AA5: =L5 -> Annual Nat. Gas Savings (Therms) | AB5: =M5 -> Annual Propane Savings (Gal) | AC5: =N5 -> Simple Payback (Years) | AD5: =O5 -> IRR | AE5: =P5 -> NPV | AP5: Annual kBTU Savings
A6: =SUM(B6) -> 1 | B6: =IF(ISTEXT(D6)=TRUE,1,0) -> 1 | C6: ='Individual Measure List'!A8 | D6: ='Individual Measure List'!B8 | E6: ='EEM Data Entry'!D85 | F6: ='EEM Data Entry'!E85 | G6: ='EEM Data Entry'!G85 -> N/A | H6: ='EEM Data Entry'!F85 | I6: ='Individual Measure List'!F8 -> 0 | J6: =IF('Savings Summary'!D7=0,"",'Savings Summary'!D7) | K6: =IF('Savings Summary'!F7=0,"",'Savings Summary'!F7) | L6: =IF('Savings Summary'!H7=0,"",'Savings Summary'!H7) | M6: =IF('Savings Summary'!J7=0,"",'Savings Summary'!J7) | N6: ='Individual Measure List'!H8 -> #VALUE! | O6: ='Individual Measure List'!J8 -> #NUM! | P6: ='Individual Measure List'!K8 -> #VALUE! | R6: Discount Rate | U6: =C6 | V6: =D6 | W6: =E6 | X6: =I6 -> 0 | Y6: =J6 | Z6: =K6 | AA6: =L6 | AB6: =M6 | AC6: =N6 -> #VALUE! | AD6: =O6 -> #NUM! | AE6: =P6 -> #VALUE! | AP6: ='Individual Measure List'!G8 -> 0
A7: =SUM(B6:B7) -> 2 | B7: =IF(ISTEXT(D7)=TRUE,1,0) -> 1 | C7: ='Individual Measure List'!A9 | D7: ='Individual Measure List'!B9 | E7: ='EEM Data Entry'!D86 | F7: ='EEM Data Entry'!E86 | G7: ='EEM Data Entry'!G86 -> N/A | H7: ='EEM Data Entry'!F86 | I7: ='Individual Measure List'!F9 -> 0 | J7: =IF('Savings Summary'!D8=0,"",'Savings Summary'!D8) | K7: =IF('Savings Summary'!F8=0,"",'Savings Summary'!F8) | L7: =IF('Savings Summary'!H8=0,"",'Savings Summary'!H8) | M7: =IF('Savings Summary'!J8=0,"",'Savings Summary'!J8) | N7: ='Individual Measure List'!H9 -> #VALUE! | O7: ='Individual Measure List'!J9 -> #NUM! | P7: ='Individual Measure List'!K9 -> #VALUE! | R7: Inflation | S7: ='Interest Rate'!C10 -> 0.034 | U7: =C7 | V7: =D7 | W7: =E7 | X7: =I7 -> 0 | Y7: =J7 | Z7: =K7 | AA7: =L7 | AB7: =M7 | AC7: =N7 -> #VALUE! | AD7: =O7 -> #NUM! | AE7: =P7 -> #VALUE! | AP7: ='Individual Measure List'!G9 -> 0
A8: =SUM(B6:B8) -> 3 | B8: =IF(ISTEXT(D8)=TRUE,1,0) -> 1 | C8: ='Individual Measure List'!A10 | D8: ='Individual Measure List'!B10 | E8: ='EEM Data Entry'!D87 | F8: ='EEM Data Entry'!E87 | G8: ='EEM Data Entry'!G87 -> N/A | H8: ='EEM Data Entry'!F87 | I8: ='Individual Measure List'!F10 -> 0 | J8: =IF('Savings Summary'!D9=0,"",'Savings Summary'!D9) | K8: =IF('Savings Summary'!F9=0,"",'Savings Summary'!F9) | L8: =IF('Savings Summary'!H9=0,"",'Savings Summary'!H9) | M8: =IF('Savings Summary'!J9=0,"",'Savings Summary'!J9) | N8: ='Individual Measure List'!H10 -> #VALUE! | O8: ='Individual Measure List'!J10 -> #NUM! | P8: ='Individual Measure List'!K10 -> #VALUE! | R8: Nominal Escalation Rate | S8: ='Interest Rate'!C12 -> 0 | U8: =C8 | V8: =D8 | W8: =E8 | X8: =I8 -> 0 | Y8: =J8 | Z8: =K8 | AA8: =L8 | AB8: =M8 | AC8: =N8 -> #VALUE! | AD8: =O8 -> #NUM! | AE8: =P8 -> #VALUE! | AP8: ='Individual Measure List'!G10 -> 0
A9: =SUM(B6:B9) -> 4 | B9: =IF(ISTEXT(D9)=TRUE,1,0) -> 1 | C9: ='Individual Measure List'!A11 | D9: ='Individual Measure List'!B11 | E9: ='EEM Data Entry'!D88 | F9: ='EEM Data Entry'!E88 | G9: ='EEM Data Entry'!G88 -> N/A | H9: ='EEM Data Entry'!F88 | I9: ='Individual Measure List'!F11 -> 0 | J9: =IF('Savings Summary'!D10=0,"",'Savings Summary'!D10) | K9: =IF('Savings Summary'!F10=0,"",'Savings Summary'!F10) | L9: =IF('Savings Summary'!H10=0,"",'Savings Summary'!H10) | M9: =IF('Savings Summary'!J10=0,"",'Savings Summary'!J10) | N9: ='Individual Measure List'!H11 -> #VALUE! | O9: ='Individual Measure List'!J11 -> #NUM! | P9: ='Individual Measure List'!K11 -> #VALUE! | R9: Discount Rate | S9: ='Interest Rate'!C14 -> 0.05 | U9: =C9 | V9: =D9 | W9: =E9 | X9: =I9 -> 0 | Y9: =J9 | Z9: =K9 | AA9: =L9 | AB9: =M9 | AC9: =N9 -> #VALUE! | AD9: =O9 -> #NUM! | AE9: =P9 -> #VALUE! | AP9: ='Individual Measure List'!G11 -> 0
A10: =SUM(B6:B10) -> 5 | B10: =IF(ISTEXT(D10)=TRUE,1,0) -> 1 | C10: ='Individual Measure List'!A12 | D10: ='Individual Measure List'!B12 | E10: ='EEM Data Entry'!D89 | F10: ='EEM Data Entry'!E89 | G10: ='EEM Data Entry'!G89 -> N/A | H10: ='EEM Data Entry'!F89 | I10: ='Individual Measure List'!F12 -> 0 | J10: =IF('Savings Summary'!D11=0,"",'Savings Summary'!D11) | K10: =IF('Savings Summary'!F11=0,"",'Savings Summary'!F11) | L10: =IF('Savings Summary'!H11=0,"",'Savings Summary'!H11) | M10: =IF('Savings Summary'!J11=0,"",'Savings Summary'!J11) | N10: ='Individual Measure List'!H12 -> #VALUE! | O10: ='Individual Measure List'!J12 -> #NUM! | P10: ='Individual Measure List'!K12 -> #VALUE! | R10: Adjusted Discount Rate | S10: ='Interest Rate'!B17 -> 0.05 | U10: =C10 | V10: =D10 | W10: =E10 | X10: =I10 -> 0 | Y10: =J10 | Z10: =K10 | AA10: =L10 | AB10: =M10 | AC10: =N10 -> #VALUE! | AD10: =O10 -> #NUM! | AE10: =P10 -> #VALUE! | AP10: ='Individual Measure List'!G12 -> 0
A11: =SUM(B6:B11) -> 6 | B11: =IF(ISTEXT(D11)=TRUE,1,0) -> 1 | C11: ='Individual Measure List'!A13 | D11: ='Individual Measure List'!B13 | E11: ='EEM Data Entry'!D90 | F11: ='EEM Data Entry'!E90 | G11: ='EEM Data Entry'!G90 -> N/A | H11: ='EEM Data Entry'!F90 | I11: ='Individual Measure List'!F13 -> 0 | J11: =IF('Savings Summary'!D12=0,"",'Savings Summary'!D12) | K11: =IF('Savings Summary'!F12=0,"",'Savings Summary'!F12) | L11: =IF('Savings Summary'!H12=0,"",'Savings Summary'!H12) | M11: =IF('Savings Summary'!J12=0,"",'Savings Summary'!J12) | N11: ='Individual Measure List'!H13 -> #VALUE! | O11: ='Individual Measure List'!J13 -> #NUM! | P11: ='Individual Measure List'!K13 -> #VALUE! | R11: *Calculated using the Nation Institute of Standards and Technology (NIST) Energy Escalation Rate Calculator | U11: =C11 | V11: =D11 | W11: =E11 | X11: =I11 -> 0 | Y11: =J11 | Z11: =K11 | AA11: =L11 | AB11: =M11 | AC11: =N11 -> #VALUE! | AD11: =O11 -> #NUM! | AE11: =P11 -> #VALUE! | AP11: ='Individual Measure List'!G13 -> 0
A12: =SUM(B6:B12) -> 7 | B12: =IF(ISTEXT(D12)=TRUE,1,0) -> 1 | C12: ='Individual Measure List'!A14 | D12: ='Individual Measure List'!B14 | E12: ='EEM Data Entry'!D91 | F12: ='EEM Data Entry'!E91 | G12: ='EEM Data Entry'!G91 -> N/A | H12: ='EEM Data Entry'!F91 | I12: ='Individual Measure List'!F14 -> 0 | J12: =IF('Savings Summary'!D13=0,"",'Savings Summary'!D13) | K12: =IF('Savings Summary'!F13=0,"",'Savings Summary'!F13) | L12: =IF('Savings Summary'!H13=0,"",'Savings Summary'!H13) | M12: =IF('Savings Summary'!J13=0,"",'Savings Summary'!J13) | N12: ='Individual Measure List'!H14 -> #VALUE! | O12: ='Individual Measure List'!J14 -> #NUM! | P12: ='Individual Measure List'!K14 -> #VALUE! | U12: =C12 | V12: =D12 | W12: =E12 | X12: =I12 -> 0 | Y12: =J12 | Z12: =K12 | AA12: =L12 | AB12: =M12 | AC12: =N12 -> #VALUE! | AD12: =O12 -> #NUM! | AE12: =P12 -> #VALUE! | AP12: ='Individual Measure List'!G14 -> 0
A13: =SUM(B6:B13) -> 8 | B13: =IF(ISTEXT(D13)=TRUE,1,0) -> 1 | C13: ='Individual Measure List'!A15 | D13: ='Individual Measure List'!B15 | E13: ='EEM Data Entry'!D92 | F13: ='EEM Data Entry'!E92 | G13: ='EEM Data Entry'!G92 -> N/A | H13: ='EEM Data Entry'!F92 | I13: ='Individual Measure List'!F15 -> 0 | J13: =IF('Savings Summary'!D14=0,"",'Savings Summary'!D14) | K13: =IF('Savings Summary'!F14=0,"",'Savings Summary'!F14) | L13: =IF('Savings Summary'!H14=0,"",'Savings Summary'!H14) | M13: =IF('Savings Summary'!J14=0,"",'Savings Summary'!J14) | N13: ='Individual Measure List'!H15 -> #VALUE! | O13: ='Individual Measure List'!J15 -> #NUM! | P13: ='Individual Measure List'!K15 -> #VALUE! | U13: =C13 | V13: =D13 | W13: =E13 | X13: =I13 -> 0 | Y13: =J13 | Z13: =K13 | AA13: =L13 | AB13: =M13 | AC13: =N13 -> #VALUE! | AD13: =O13 -> #NUM! | AE13: =P13 -> #VALUE! | AP13: ='Individual Measure List'!G15 -> 0
A14: =SUM(B6:B14) -> 9 | B14: =IF(ISTEXT(D14)=TRUE,1,0) -> 1 | C14: ='Individual Measure List'!A16 | D14: ='Individual Measure List'!B16 | E14: ='EEM Data Entry'!D93 | F14: ='EEM Data Entry'!E93 | G14: ='EEM Data Entry'!G93 -> N/A | H14: ='EEM Data Entry'!F93 | I14: ='Individual Measure List'!F16 -> 0 | J14: =IF('Savings Summary'!D15=0,"",'Savings Summary'!D15) | K14: =IF('Savings Summary'!F15=0,"",'Savings Summary'!F15) | L14: =IF('Savings Summary'!H15=0,"",'Savings Summary'!H15) | M14: =IF('Savings Summary'!J15=0,"",'Savings Summary'!J15) | N14: ='Individual Measure List'!H16 -> #VALUE! | O14: ='Individual Measure List'!J16 -> #NUM! | P14: ='Individual Measure List'!K16 -> #VALUE! | U14: =C14 | V14: =D14 | W14: =E14 | X14: =I14 -> 0 | Y14: =J14 | Z14: =K14 | AA14: =L14 | AB14: =M14 | AC14: =N14 -> #VALUE! | AD14: =O14 -> #NUM! | AE14: =P14 -> #VALUE! | AP14: ='Individual Measure List'!G16 -> 0
A15: =SUM(B6:B15) -> 10 | B15: =IF(ISTEXT(D15)=TRUE,1,0) -> 1 | C15: ='Individual Measure List'!A17 | D15: ='Individual Measure List'!B17 | E15: ='EEM Data Entry'!D94 | F15: ='EEM Data Entry'!E94 | G15: ='EEM Data Entry'!G94 -> N/A | H15: ='EEM Data Entry'!F94 | I15: ='Individual Measure List'!F17 -> 0 | J15: =IF('Savings Summary'!D16=0,"",'Savings Summary'!D16) | K15: =IF('Savings Summary'!F16=0,"",'Savings Summary'!F16) | L15: =IF('Savings Summary'!H16=0,"",'Savings Summary'!H16) | M15: =IF('Savings Summary'!J16=0,"",'Savings Summary'!J16) | N15: ='Individual Measure List'!H17 -> #VALUE! | O15: ='Individual Measure List'!J17 -> #NUM! | P15: ='Individual Measure List'!K17 -> #VALUE! | U15: =C15 | V15: =D15 | W15: =E15 | X15: =I15 -> 0 | Y15: =J15 | Z15: =K15 | AA15: =L15 | AB15: =M15 | AC15: =N15 -> #VALUE! | AD15: =O15 -> #NUM! | AE15: =P15 -> #VALUE! | AP15: ='Individual Measure List'!G17 -> 0
C16: *Please see "Note Regarding Incentives" on first page of financial modeling section | U16: *Please see "Note Regarding Incentives" on first page of financial modeling section
C18: MECHANICAL | U18: MECHANICAL
C20: EEM # | D20: Mechanical System Upgrades | E20: Capital Investment | F20: Estimated Incentive* | G20: Incentive Reference | H20: Estimated Net Cost | I20: Annual Energy Cost Savings | J20: Annual Electric Savings (kWh) | K20: Annual Oil Savings (Gal) | L20: Annual Nat. Gas Savings (Therms) | M20: Annual Propane Savings (Gal) | N20: Simple Payback (Years) | O20: IRR | P20: NPV | U20: =C20 -> EEM # | V20: =D20 -> Mechanical System Upgrades | W20: =E20 -> Capital Investment | X20: =I20 -> Annual Energy Cost Savings | Y20: =J20 -> Annual Electric Savings (kWh) | Z20: =K20 -> Annual Oil Savings (Gal) | AA20: =L20 -> Annual Nat. Gas Savings (Therms) | AB20: =M20 -> Annual Propane Savings (Gal) | AC20: =N20 -> Simple Payback (Years) | AD20: =O20 -> IRR | AE20: =P20 -> NPV | AP20: Annual kBTU Savings
A21: =SUM(B6:B21) -> 11 | B21: =IF(ISTEXT(D21)=TRUE,1,0) -> 1 | C21: ='Individual Measure List'!A33 | D21: ='Individual Measure List'!B33 | E21: ='EEM Data Entry'!D110 | F21: ='EEM Data Entry'!E110 | G21: ='EEM Data Entry'!G110 -> N/A | H21: ='EEM Data Entry'!F110 | I21: ='Individual Measure List'!F33 -> 0 | J21: =IF('Savings Summary'!D34=0,"",'Savings Summary'!D34) | K21: =IF('Savings Summary'!F34=0,"",'Savings Summary'!F34) | L21: =IF('Savings Summary'!H34=0,"",'Savings Summary'!H34) | M21: =IF('Savings Summary'!J34=0,"",'Savings Summary'!J34) | N21: ='Individual Measure List'!H33 -> #VALUE! | O21: ='Individual Measure List'!J33 -> #NUM! | P21: ='Individual Measure List'!K33 -> #VALUE! | U21: =C21 | V21: =D21 | W21: =E21 | X21: =I21 -> 0 | Y21: =J21 | Z21: =K21 | AA21: =L21 | AB21: =M21 | AC21: =N21 -> #VALUE! | AD21: =O21 -> #NUM! | AE21: =P21 -> #VALUE! | AP21: ='Individual Measure List'!G33 -> 0
A22: =SUM(B6:B22) -> 12 | B22: =IF(ISTEXT(D22)=TRUE,1,0) -> 1 | C22: ='Individual Measure List'!A34 | D22: ='Individual Measure List'!B34 | E22: ='EEM Data Entry'!D111 | F22: ='EEM Data Entry'!E111 | G22: ='EEM Data Entry'!G111 -> N/A | H22: ='EEM Data Entry'!F111 | I22: ='Individual Measure List'!F34 -> 0 | J22: =IF('Savings Summary'!D35=0,"",'Savings Summary'!D35) | K22: =IF('Savings Summary'!F35=0,"",'Savings Summary'!F35) | L22: =IF('Savings Summary'!H35=0,"",'Savings Summary'!H35) | M22: =IF('Savings Summary'!J35=0,"",'Savings Summary'!J35) | N22: ='Individual Measure List'!H34 -> #VALUE! | O22: ='Individual Measure List'!J34 -> #NUM! | P22: ='Individual Measure List'!K34 -> #VALUE! | U22: =C22 | V22: =D22 | W22: =E22 | X22: =I22 -> 0 | Y22: =J22 | Z22: =K22 | AA22: =L22 | AB22: =M22 | AC22: =N22 -> #VALUE! | AD22: =O22 -> #NUM! | AE22: =P22 -> #VALUE! | AP22: ='Individual Measure List'!G34 -> 0
A23: =SUM(B6:B23) -> 13 | B23: =IF(ISTEXT(D23)=TRUE,1,0) -> 1 | C23: ='Individual Measure List'!A35 | D23: ='Individual Measure List'!B35 | E23: ='EEM Data Entry'!D112 | F23: ='EEM Data Entry'!E112 | G23: ='EEM Data Entry'!G112 -> N/A | H23: ='EEM Data Entry'!F112 | I23: ='Individual Measure List'!F35 -> 0 | J23: =IF('Savings Summary'!D36=0,"",'Savings Summary'!D36) | K23: =IF('Savings Summary'!F36=0,"",'Savings Summary'!F36) | L23: =IF('Savings Summary'!H36=0,"",'Savings Summary'!H36) | M23: =IF('Savings Summary'!J36=0,"",'Savings Summary'!J36) | N23: ='Individual Measure List'!H35 -> #VALUE! | O23: ='Individual Measure List'!J35 -> #NUM! | P23: ='Individual Measure List'!K35 -> #VALUE! | U23: =C23 | V23: =D23 | W23: =E23 | X23: =I23 -> 0 | Y23: =J23 | Z23: =K23 | AA23: =L23 | AB23: =M23 | AC23: =N23 -> #VALUE! | AD23: =O23 -> #NUM! | AE23: =P23 -> #VALUE! | AP23: ='Individual Measure List'!G35 -> 0
A24: =SUM(B6:B24) -> 14 | B24: =IF(ISTEXT(D24)=TRUE,1,0) -> 1 | C24: ='Individual Measure List'!A36 | D24: ='Individual Measure List'!B36 | E24: ='EEM Data Entry'!D113 | F24: ='EEM Data Entry'!E113 | G24: ='EEM Data Entry'!G113 -> N/A | H24: ='EEM Data Entry'!F113 | I24: ='Individual Measure List'!F36 -> 0 | J24: =IF('Savings Summary'!D37=0,"",'Savings Summary'!D37) | K24: =IF('Savings Summary'!F37=0,"",'Savings Summary'!F37) | L24: =IF('Savings Summary'!H37=0,"",'Savings Summary'!H37) | M24: =IF('Savings Summary'!J37=0,"",'Savings Summary'!J37) | N24: ='Individual Measure List'!H36 -> #VALUE! | O24: ='Individual Measure List'!J36 -> #NUM! | P24: ='Individual Measure List'!K36 -> #VALUE! | U24: =C24 | V24: =D24 | W24: =E24 | X24: =I24 -> 0 | Y24: =J24 | Z24: =K24 | AA24: =L24 | AB24: =M24 | AC24: =N24 -> #VALUE! | AD24: =O24 -> #NUM! | AE24: =P24 -> #VALUE! | AP24: ='Individual Measure List'!G36 -> 0
A25: =SUM(B6:B25) -> 15 | B25: =IF(ISTEXT(D25)=TRUE,1,0) -> 1 | C25: ='Individual Measure List'!A37 | D25: ='Individual Measure List'!B37 | E25: ='EEM Data Entry'!D114 | F25: ='EEM Data Entry'!E114 | G25: ='EEM Data Entry'!G114 -> N/A | H25: ='EEM Data Entry'!F114 | I25: ='Individual Measure List'!F37 -> 0 | J25: =IF('Savings Summary'!D38=0,"",'Savings Summary'!D38) | K25: =IF('Savings Summary'!F38=0,"",'Savings Summary'!F38) | L25: =IF('Savings Summary'!H38=0,"",'Savings Summary'!H38) | M25: =IF('Savings Summary'!J38=0,"",'Savings Summary'!J38) | N25: ='Individual Measure List'!H37 -> #VALUE! | O25: ='Individual Measure List'!J37 -> #NUM! | P25: ='Individual Measure List'!K37 -> #VALUE! | U25: =C25 | V25: =D25 | W25: =E25 | X25: =I25 -> 0 | Y25: =J25 | Z25: =K25 | AA25: =L25 | AB25: =M25 | AC25: =N25 -> #VALUE! | AD25: =O25 -> #NUM! | AE25: =P25 -> #VALUE! | AP25: ='Individual Measure List'!G37 -> 0
A26: =SUM(B6:B26) -> 16 | B26: =IF(ISTEXT(D26)=TRUE,1,0) -> 1 | C26: ='Individual Measure List'!A38 | D26: ='Individual Measure List'!B38 | E26: ='EEM Data Entry'!D115 | F26: ='EEM Data Entry'!E115 | G26: ='EEM Data Entry'!G115 -> N/A | H26: ='EEM Data Entry'!F115 | I26: ='Individual Measure List'!F38 -> 0 | J26: =IF('Savings Summary'!D39=0,"",'Savings Summary'!D39) | K26: =IF('Savings Summary'!F39=0,"",'Savings Summary'!F39) | L26: =IF('Savings Summary'!H39=0,"",'Savings Summary'!H39) | M26: =IF('Savings Summary'!J39=0,"",'Savings Summary'!J39) | N26: ='Individual Measure List'!H38 -> #VALUE! | O26: ='Individual Measure List'!J38 -> #NUM! | P26: ='Individual Measure List'!K38 -> #VALUE! | U26: =C26 | V26: =D26 | W26: =E26 | X26: =I26 -> 0 | Y26: =J26 | Z26: =K26 | AA26: =L26 | AB26: =M26 | AC26: =N26 -> #VALUE! | AD26: =O26 -> #NUM! | AE26: =P26 -> #VALUE! | AP26: ='Individual Measure List'!G38 -> 0
A27: =SUM(B6:B27) -> 17 | B27: =IF(ISTEXT(D27)=TRUE,1,0) -> 1 | C27: ='Individual Measure List'!A39 | D27: ='Individual Measure List'!B39 | E27: ='EEM Data Entry'!D116 | F27: ='EEM Data Entry'!E116 | G27: ='EEM Data Entry'!G116 -> N/A | H27: ='EEM Data Entry'!F116 | I27: ='Individual Measure List'!F39 -> 0 | J27: =IF('Savings Summary'!D40=0,"",'Savings Summary'!D40) | K27: =IF('Savings Summary'!F40=0,"",'Savings Summary'!F40) | L27: =IF('Savings Summary'!H40=0,"",'Savings Summary'!H40) | M27: =IF('Savings Summary'!J40=0,"",'Savings Summary'!J40) | N27: ='Individual Measure List'!H39 -> #VALUE! | O27: ='Individual Measure List'!J39 -> #NUM! | P27: ='Individual Measure List'!K39 -> #VALUE! | U27: =C27 | V27: =D27 | W27: =E27 | X27: =I27 -> 0 | Y27: =J27 | Z27: =K27 | AA27: =L27 | AB27: =M27 | AC27: =N27 -> #VALUE! | AD27: =O27 -> #NUM! | AE27: =P27 -> #VALUE! | AP27: ='Individual Measure List'!G39 -> 0
A28: =SUM(B6:B28) -> 18 | B28: =IF(ISTEXT(D28)=TRUE,1,0) -> 1 | C28: ='Individual Measure List'!A40 | D28: ='Individual Measure List'!B40 | E28: ='EEM Data Entry'!D117 | F28: ='EEM Data Entry'!E117 | G28: ='EEM Data Entry'!G117 -> N/A | H28: ='EEM Data Entry'!F117 | I28: ='Individual Measure List'!F40 -> 0 | J28: =IF('Savings Summary'!D41=0,"",'Savings Summary'!D41) | K28: =IF('Savings Summary'!F41=0,"",'Savings Summary'!F41) | L28: =IF('Savings Summary'!H41=0,"",'Savings Summary'!H41) | M28: =IF('Savings Summary'!J41=0,"",'Savings Summary'!J41) | N28: ='Individual Measure List'!H40 -> #VALUE! | O28: ='Individual Measure List'!J40 -> #NUM! | P28: ='Individual Measure List'!K40 -> #VALUE! | U28: =C28 | V28: =D28 | W28: =E28 | X28: =I28 -> 0 | Y28: =J28 | Z28: =K28 | AA28: =L28 | AB28: =M28 | AC28: =N28 -> #VALUE! | AD28: =O28 -> #NUM! | AE28: =P28 -> #VALUE! | AP28: ='Individual Measure List'!G40 -> 0
A29: =SUM(B6:B29) -> 19 | B29: =IF(ISTEXT(D29)=TRUE,1,0) -> 1 | C29: ='Individual Measure List'!A41 | D29: ='Individual Measure List'!B41 | E29: ='EEM Data Entry'!D118 | F29: ='EEM Data Entry'!E118 | G29: ='EEM Data Entry'!G118 -> N/A | H29: ='EEM Data Entry'!F118 | I29: ='Individual Measure List'!F41 -> 0 | J29: =IF('Savings Summary'!D42=0,"",'Savings Summary'!D42) | K29: =IF('Savings Summary'!F42=0,"",'Savings Summary'!F42) | L29: =IF('Savings Summary'!H42=0,"",'Savings Summary'!H42) | M29: =IF('Savings Summary'!J42=0,"",'Savings Summary'!J42) | N29: ='Individual Measure List'!H41 -> #VALUE! | O29: ='Individual Measure List'!J41 -> #NUM! | P29: ='Individual Measure List'!K41 -> #VALUE! | U29: =C29 | V29: =D29 | W29: =E29 | X29: =I29 -> 0 | Y29: =J29 | Z29: =K29 | AA29: =L29 | AB29: =M29 | AC29: =N29 -> #VALUE! | AD29: =O29 -> #NUM! | AE29: =P29 -> #VALUE! | AP29: ='Individual Measure List'!G41 -> 0
A30: =SUM(B6:B30) -> 20 | B30: =IF(ISTEXT(D30)=TRUE,1,0) -> 1 | C30: ='Individual Measure List'!A42 | D30: ='Individual Measure List'!B42 | E30: ='EEM Data Entry'!D119 | F30: ='EEM Data Entry'!E119 | G30: ='EEM Data Entry'!G119 -> N/A | H30: ='EEM Data Entry'!F119 | I30: ='Individual Measure List'!F42 -> 0 | J30: =IF('Savings Summary'!D43=0,"",'Savings Summary'!D43) | K30: =IF('Savings Summary'!F43=0,"",'Savings Summary'!F43) | L30: =IF('Savings Summary'!H43=0,"",'Savings Summary'!H43) | M30: =IF('Savings Summary'!J43=0,"",'Savings Summary'!J43) | N30: ='Individual Measure List'!H42 -> #VALUE! | O30: ='Individual Measure List'!J42 -> #NUM! | P30: ='Individual Measure List'!K42 -> #VALUE! | U30: =C30 | V30: =D30 | W30: =E30 | X30: =I30 -> 0 | Y30: =J30 | Z30: =K30 | AA30: =L30 | AB30: =M30 | AC30: =N30 -> #VALUE! | AD30: =O30 -> #NUM! | AE30: =P30 -> #VALUE! | AP30: ='Individual Measure List'!G42 -> 0
C31: *Please see "Note Regarding Incentives" on first page of financial modeling section | U31: *Please see "Note Regarding Incentives" on first page of financial modeling section
C33: APPLIANCES & LIGHTING | U33: APPLIANCES & LIGHTING
C35: EEM # | D35: Appliances & Lighting Upgrades | E35: Capital Investment | F35: Estimated Incentive* | G35: Incentive Reference | H35: Estimated Net Cost | I35: Annual Energy Cost Savings | J35: Annual Electric Savings (kWh) | K35: Annual Oil Savings (Gal) | L35: Annual Nat. Gas Savings (Therms) | M35: Annual Propane Savings (Gal) | N35: Simple Payback (Years) | O35: IRR | P35: NPV | U35: =C35 -> EEM # | V35: =D35 -> Appliances & Lighting Upgrades | W35: =E35 -> Capital Investment | X35: =I35 -> Annual Energy Cost Savings | Y35: =J35 -> Annual Electric Savings (kWh) | Z35: =K35 -> Annual Oil Savings (Gal) | AA35: =L35 -> Annual Nat. Gas Savings (Therms) | AB35: =M35 -> Annual Propane Savings (Gal) | AC35: =N35 -> Simple Payback (Years) | AD35: =O35 -> IRR | AE35: =P35 -> NPV | AP35: Annual kBTU Savings
A36: =SUM(B6:B36) -> 21 | B36: =IF(ISTEXT(D36)=TRUE,1,0) -> 1 | C36: ='Individual Measure List'!A49 | D36: ='Individual Measure List'!B49 | E36: ='EEM Data Entry'!D125 | F36: ='EEM Data Entry'!E125 | G36: ='EEM Data Entry'!G125 -> N/A | H36: ='EEM Data Entry'!F125 | I36: ='Individual Measure List'!F49 -> 0 | J36: =IF('Savings Summary'!D51=0,"",'Savings Summary'!D51) | K36: =IF('Savings Summary'!F51=0,"",'Savings Summary'!F51) | L36: =IF('Savings Summary'!H51=0,"",'Savings Summary'!H51) | M36: =IF('Savings Summary'!J51=0,"",'Savings Summary'!J51) | N36: ='Individual Measure List'!H49 -> #VALUE! | O36: ='Individual Measure List'!J49 -> #NUM! | P36: ='Individual Measure List'!K49 -> #VALUE! | U36: =C36 | V36: =D36 | W36: =E36 | X36: =I36 -> 0 | Y36: =J36 | Z36: =K36 | AA36: =L36 | AB36: =M36 | AC36: =N36 -> #VALUE! | AD36: =O36 -> #NUM! | AE36: =P36 -> #VALUE! | AP36: ='Individual Measure List'!G49 -> 0
A37: =SUM(B6:B37) -> 22 | B37: =IF(ISTEXT(D37)=TRUE,1,0) -> 1 | C37: ='Individual Measure List'!A50 | D37: ='Individual Measure List'!B50 | E37: ='EEM Data Entry'!D126 | F37: ='EEM Data Entry'!E126 | G37: ='EEM Data Entry'!G126 -> N/A | H37: ='EEM Data Entry'!F126 | I37: ='Individual Measure List'!F50 -> 0 | J37: =IF('Savings Summary'!D52=0,"",'Savings Summary'!D52) | K37: =IF('Savings Summary'!F52=0,"",'Savings Summary'!F52) | L37: =IF('Savings Summary'!H52=0,"",'Savings Summary'!H52) | M37: =IF('Savings Summary'!J52=0,"",'Savings Summary'!J52) | N37: ='Individual Measure List'!H50 -> #VALUE! | O37: ='Individual Measure List'!J50 -> #NUM! | P37: ='Individual Measure List'!K50 -> #VALUE! | U37: =C37 | V37: =D37 | W37: =E37 | X37: =I37 -> 0 | Y37: =J37 | Z37: =K37 | AA37: =L37 | AB37: =M37 | AC37: =N37 -> #VALUE! | AD37: =O37 -> #NUM! | AE37: =P37 -> #VALUE! | AP37: ='Individual Measure List'!G50 -> 0
A38: =SUM(B6:B38) -> 23 | B38: =IF(ISTEXT(D38)=TRUE,1,0) -> 1 | C38: ='Individual Measure List'!A51 | D38: ='Individual Measure List'!B51 | E38: ='EEM Data Entry'!D127 | F38: ='EEM Data Entry'!E127 | G38: ='EEM Data Entry'!G127 -> N/A | H38: ='EEM Data Entry'!F127 | I38: ='Individual Measure List'!F51 -> 0 | J38: =IF('Savings Summary'!D53=0,"",'Savings Summary'!D53) | K38: =IF('Savings Summary'!F53=0,"",'Savings Summary'!F53) | L38: =IF('Savings Summary'!H53=0,"",'Savings Summary'!H53) | M38: =IF('Savings Summary'!J53=0,"",'Savings Summary'!J53) | N38: ='Individual Measure List'!H51 -> #VALUE! | O38: ='Individual Measure List'!J51 -> #NUM! | P38: ='Individual Measure List'!K51 -> #VALUE! | U38: =C38 | V38: =D38 | W38: =E38 | X38: =I38 -> 0 | Y38: =J38 | Z38: =K38 | AA38: =L38 | AB38: =M38 | AC38: =N38 -> #VALUE! | AD38: =O38 -> #NUM! | AE38: =P38 -> #VALUE! | AP38: ='Individual Measure List'!G51 -> 0
A39: =SUM(B6:B39) -> 24 | B39: =IF(ISTEXT(D39)=TRUE,1,0) -> 1 | C39: ='Individual Measure List'!A52 | D39: ='Individual Measure List'!B52 | E39: ='EEM Data Entry'!D128 | F39: ='EEM Data Entry'!E128 | G39: ='EEM Data Entry'!G128 -> N/A | H39: ='EEM Data Entry'!F128 | I39: ='Individual Measure List'!F52 -> 0 | J39: =IF('Savings Summary'!D54=0,"",'Savings Summary'!D54) | K39: =IF('Savings Summary'!F54=0,"",'Savings Summary'!F54) | L39: =IF('Savings Summary'!H54=0,"",'Savings Summary'!H54) | M39: =IF('Savings Summary'!J54=0,"",'Savings Summary'!J54) | N39: ='Individual Measure List'!H52 -> #VALUE! | O39: ='Individual Measure List'!J52 -> #NUM! | P39: ='Individual Measure List'!K52 -> #VALUE! | U39: =C39 | V39: =D39 | W39: =E39 | X39: =I39 -> 0 | Y39: =J39 | Z39: =K39 | AA39: =L39 | AB39: =M39 | AC39: =N39 -> #VALUE! | AD39: =O39 -> #NUM! | AE39: =P39 -> #VALUE! | AP39: ='Individual Measure List'!G52 -> 0
A40: =SUM(B6:B40) -> 25 | B40: =IF(ISTEXT(D40)=TRUE,1,0) -> 1 | C40: ='Individual Measure List'!A53 | D40: ='Individual Measure List'!B53 | E40: ='EEM Data Entry'!D129 | F40: ='EEM Data Entry'!E129 | G40: ='EEM Data Entry'!G129 -> N/A | H40: ='EEM Data Entry'!F129 | I40: ='Individual Measure List'!F53 -> 0 | J40: =IF('Savings Summary'!D55=0,"",'Savings Summary'!D55) | K40: =IF('Savings Summary'!F55=0,"",'Savings Summary'!F55) | L40: =IF('Savings Summary'!H55=0,"",'Savings Summary'!H55) | M40: =IF('Savings Summary'!J55=0,"",'Savings Summary'!J55) | N40: ='Individual Measure List'!H53 -> #VALUE! | O40: ='Individual Measure List'!J53 -> #NUM! | P40: ='Individual Measure List'!K53 -> #VALUE! | U40: =C40 | V40: =D40 | W40: =E40 | X40: =I40 -> 0 | Y40: =J40 | Z40: =K40 | AA40: =L40 | AB40: =M40 | AC40: =N40 -> #VALUE! | AD40: =O40 -> #NUM! | AE40: =P40 -> #VALUE! | AP40: ='Individual Measure List'!G53 -> 0
A41: =SUM(B6:B41) -> 26 | B41: =IF(ISTEXT(D41)=TRUE,1,0) -> 1 | C41: ='Individual Measure List'!A54 | D41: ='Individual Measure List'!B54 | E41: ='EEM Data Entry'!D130 | F41: ='EEM Data Entry'!E130 | G41: ='EEM Data Entry'!G130 -> N/A | H41: ='EEM Data Entry'!F130 | I41: ='Individual Measure List'!F54 -> 0 | J41: =IF('Savings Summary'!D56=0,"",'Savings Summary'!D56) | K41: =IF('Savings Summary'!F56=0,"",'Savings Summary'!F56) | L41: =IF('Savings Summary'!H56=0,"",'Savings Summary'!H56) | M41: =IF('Savings Summary'!J56=0,"",'Savings Summary'!J56) | N41: ='Individual Measure List'!H54 -> #VALUE! | O41: ='Individual Measure List'!J54 -> #NUM! | P41: ='Individual Measure List'!K54 -> #VALUE! | U41: =C41 | V41: =D41 | W41: =E41 | X41: =I41 -> 0 | Y41: =J41 | Z41: =K41 | AA41: =L41 | AB41: =M41 | AC41: =N41 -> #VALUE! | AD41: =O41 -> #NUM! | AE41: =P41 -> #VALUE! | AP41: ='Individual Measure List'!G54 -> 0
A42: =SUM(B6:B42) -> 27 | B42: =IF(ISTEXT(D42)=TRUE,1,0) -> 1 | C42: ='Individual Measure List'!A55 | D42: ='Individual Measure List'!B55 | E42: ='EEM Data Entry'!D131 | F42: ='EEM Data Entry'!E131 | G42: ='EEM Data Entry'!G131 -> N/A | H42: ='EEM Data Entry'!F131 | I42: ='Individual Measure List'!F55 -> 0 | J42: =IF('Savings Summary'!D57=0,"",'Savings Summary'!D57) | K42: =IF('Savings Summary'!F57=0,"",'Savings Summary'!F57) | L42: =IF('Savings Summary'!H57=0,"",'Savings Summary'!H57) | M42: =IF('Savings Summary'!J57=0,"",'Savings Summary'!J57) | N42: ='Individual Measure List'!H55 -> #VALUE! | O42: ='Individual Measure List'!J55 -> #NUM! | P42: ='Individual Measure List'!K55 -> #VALUE! | U42: =C42 | V42: =D42 | W42: =E42 | X42: =I42 -> 0 | Y42: =J42 | Z42: =K42 | AA42: =L42 | AB42: =M42 | AC42: =N42 -> #VALUE! | AD42: =O42 -> #NUM! | AE42: =P42 -> #VALUE! | AP42: ='Individual Measure List'!G55 -> 0
A43: =SUM(B6:B43) -> 28 | B43: =IF(ISTEXT(D43)=TRUE,1,0) -> 1 | C43: ='Individual Measure List'!A56 | D43: ='Individual Measure List'!B56 | E43: ='EEM Data Entry'!D132 | F43: ='EEM Data Entry'!E132 | G43: ='EEM Data Entry'!G132 -> N/A | H43: ='EEM Data Entry'!F132 | I43: ='Individual Measure List'!F56 -> 0 | J43: =IF('Savings Summary'!D58=0,"",'Savings Summary'!D58) | K43: =IF('Savings Summary'!F58=0,"",'Savings Summary'!F58) | L43: =IF('Savings Summary'!H58=0,"",'Savings Summary'!H58) | M43: =IF('Savings Summary'!J58=0,"",'Savings Summary'!J58) | N43: ='Individual Measure List'!H56 -> #VALUE! | O43: ='Individual Measure List'!J56 -> #NUM! | P43: ='Individual Measure List'!K56 -> #VALUE! | U43: =C43 | V43: =D43 | W43: =E43 | X43: =I43 -> 0 | Y43: =J43 | Z43: =K43 | AA43: =L43 | AB43: =M43 | AC43: =N43 -> #VALUE! | AD43: =O43 -> #NUM! | AE43: =P43 -> #VALUE! | AP43: ='Individual Measure List'!G56 -> 0
A44: =SUM(B6:B44) -> 29 | B44: =IF(ISTEXT(D44)=TRUE,1,0) -> 1 | C44: ='Individual Measure List'!A57 | D44: ='Individual Measure List'!B57 | E44: ='EEM Data Entry'!D133 | F44: ='EEM Data Entry'!E133 | G44: ='EEM Data Entry'!G133 -> N/A | H44: ='EEM Data Entry'!F133 | I44: ='Individual Measure List'!F57 -> 0 | J44: =IF('Savings Summary'!D59=0,"",'Savings Summary'!D59) | K44: =IF('Savings Summary'!F59=0,"",'Savings Summary'!F59) | L44: =IF('Savings Summary'!H59=0,"",'Savings Summary'!H59) | M44: =IF('Savings Summary'!J59=0,"",'Savings Summary'!J59) | N44: ='Individual Measure List'!H57 -> #VALUE! | O44: ='Individual Measure List'!J57 -> #NUM! | P44: ='Individual Measure List'!K57 -> #VALUE! | U44: =C44 | V44: =D44 | W44: =E44 | X44: =I44 -> 0 | Y44: =J44 | Z44: =K44 | AA44: =L44 | AB44: =M44 | AC44: =N44 -> #VALUE! | AD44: =O44 -> #NUM! | AE44: =P44 -> #VALUE! | AP44: ='Individual Measure List'!G57 -> 0
A45: =SUM(B6:B45) -> 30 | B45: =IF(ISTEXT(D45)=TRUE,1,0) -> 1 | C45: ='Individual Measure List'!A58 | D45: ='Individual Measure List'!B58 | E45: ='EEM Data Entry'!D134 | F45: ='EEM Data Entry'!E134 | G45: ='EEM Data Entry'!G134 -> N/A | H45: ='EEM Data Entry'!F134 | I45: ='Individual Measure List'!F58 -> 0 | J45: =IF('Savings Summary'!D60=0,"",'Savings Summary'!D60) | K45: =IF('Savings Summary'!F60=0,"",'Savings Summary'!F60) | L45: =IF('Savings Summary'!H60=0,"",'Savings Summary'!H60) | M45: =IF('Savings Summary'!J60=0,"",'Savings Summary'!J60) | N45: ='Individual Measure List'!H58 -> #VALUE! | O45: ='Individual Measure List'!J58 -> #NUM! | P45: ='Individual Measure List'!K58 -> #VALUE! | U45: =C45 | V45: =D45 | W45: =E45 | X45: =I45 -> 0 | Y45: =J45 | Z45: =K45 | AA45: =L45 | AB45: =M45 | AC45: =N45 -> #VALUE! | AD45: =O45 -> #NUM! | AE45: =P45 -> #VALUE! | AP45: ='Individual Measure List'!G58 -> 0
C46: *Please see "Note Regarding Incentives" on first page of financial modeling section | U46: *Please see "Note Regarding Incentives" on first page of financial modeling section
C48: RENEWABLE | U48: RENEWABLE
C50: EEM # | D50: Renewable System Upgrades | E50: Capital Investment | F50: Estimated Incentive* | G50: Incentive Reference | H50: Estimated Net Cost | I50: Annual Energy Cost Savings | J50: Annual Electric Savings (kWh) | K50: Annual Oil Savings (Gal) | L50: Annual Nat. Gas Savings (Therms) | M50: Annual Propane Savings (Gal) | N50: Simple Payback (Years) | O50: IRR | P50: NPV | U50: =C50 -> EEM # | V50: =D50 -> Renewable System Upgrades | W50: =E50 -> Capital Investment | X50: =I50 -> Annual Energy Cost Savings | Y50: =J50 -> Annual Electric Savings (kWh) | Z50: =K50 -> Annual Oil Savings (Gal) | AA50: =L50 -> Annual Nat. Gas Savings (Therms) | AB50: =M50 -> Annual Propane Savings (Gal) | AC50: =N50 -> Simple Payback (Years) | AD50: =O50 -> IRR | AE50: =P50 -> NPV | AP50: Annual kBTU Savings
A51: =SUM(B6:B51) -> 31 | B51: =IF(ISTEXT(D51)=TRUE,1,0) -> 1 | C51: ='Individual Measure List'!A66 | D51: ='Individual Measure List'!B66 | E51: ='EEM Data Entry'!D141 | F51: ='EEM Data Entry'!E141 | G51: ='EEM Data Entry'!G141 -> N/A | H51: ='EEM Data Entry'!F141 | I51: ='Individual Measure List'!F66 -> 0 | J51: =IF('Savings Summary'!D69=0,"",'Savings Summary'!D69) | K51: =IF('Savings Summary'!F69=0,"",'Savings Summary'!F69) | L51: =IF('Savings Summary'!H69=0,"",'Savings Summary'!H69) | M51: =IF('Savings Summary'!J69=0,"",'Savings Summary'!J69) | N51: ='Individual Measure List'!H66 -> #VALUE! | O51: ='Individual Measure List'!J66 -> #NUM! | P51: ='Individual Measure List'!K66 -> #VALUE! | U51: =C51 | V51: =D51 | W51: =E51 | X51: =I51 -> 0 | Y51: =J51 | Z51: =K51 | AA51: =L51 | AB51: =M51 | AC51: =N51 -> #VALUE! | AD51: =O51 -> #NUM! | AE51: =P51 -> #VALUE! | AP51: ='Individual Measure List'!G66 -> 0
A52: =SUM(B6:B52) -> 32 | B52: =IF(ISTEXT(D52)=TRUE,1,0) -> 1 | C52: ='Individual Measure List'!A67 | D52: ='Individual Measure List'!B67 | E52: ='EEM Data Entry'!D142 | F52: ='EEM Data Entry'!E142 | G52: ='EEM Data Entry'!G142 -> N/A | H52: ='EEM Data Entry'!F142 | I52: ='Individual Measure List'!F67 -> 0 | J52: =IF('Savings Summary'!D70=0,"",'Savings Summary'!D70) | K52: =IF('Savings Summary'!F70=0,"",'Savings Summary'!F70) | L52: =IF('Savings Summary'!H70=0,"",'Savings Summary'!H70) | M52: =IF('Savings Summary'!J70=0,"",'Savings Summary'!J70) | N52: ='Individual Measure List'!H67 -> #VALUE! | O52: ='Individual Measure List'!J67 -> #NUM! | P52: ='Individual Measure List'!K67 -> #VALUE! | U52: =C52 | V52: =D52 | W52: =E52 | X52: =I52 -> 0 | Y52: =J52 | Z52: =K52 | AA52: =L52 | AB52: =M52 | AC52: =N52 -> #VALUE! | AD52: =O52 -> #NUM! | AE52: =P52 -> #VALUE! | AP52: ='Individual Measure List'!G67 -> 0
A53: =SUM(B6:B53) -> 33 | B53: =IF(ISTEXT(D53)=TRUE,1,0) -> 1 | C53: ='Individual Measure List'!A68 | D53: ='Individual Measure List'!B68 | E53: ='EEM Data Entry'!D143 | F53: ='EEM Data Entry'!E143 | G53: ='EEM Data Entry'!G143 -> N/A | H53: ='EEM Data Entry'!F143 | I53: ='Individual Measure List'!F68 -> 0 | J53: =IF('Savings Summary'!D71=0,"",'Savings Summary'!D71) | K53: =IF('Savings Summary'!F71=0,"",'Savings Summary'!F71) | L53: =IF('Savings Summary'!H71=0,"",'Savings Summary'!H71) | M53: =IF('Savings Summary'!J71=0,"",'Savings Summary'!J71) | N53: ='Individual Measure List'!H68 -> #VALUE! | O53: ='Individual Measure List'!J68 -> #NUM! | P53: ='Individual Measure List'!K68 -> #VALUE! | U53: =C53 | V53: =D53 | W53: =E53 | X53: =I53 -> 0 | Y53: =J53 | Z53: =K53 | AA53: =L53 | AB53: =M53 | AC53: =N53 -> #VALUE! | AD53: =O53 -> #NUM! | AE53: =P53 -> #VALUE! | AP53: ='Individual Measure List'!G68 -> 0
A54: =SUM(B6:B54) -> 34 | B54: =IF(ISTEXT(D54)=TRUE,1,0) -> 1 | C54: ='Individual Measure List'!A69 | D54: ='Individual Measure List'!B69 | E54: ='EEM Data Entry'!D144 | F54: ='EEM Data Entry'!E144 | G54: ='EEM Data Entry'!G144 -> N/A | H54: ='EEM Data Entry'!F144 | I54: ='Individual Measure List'!F69 -> 0 | J54: =IF('Savings Summary'!D72=0,"",'Savings Summary'!D72) | K54: =IF('Savings Summary'!F72=0,"",'Savings Summary'!F72) | L54: =IF('Savings Summary'!H72=0,"",'Savings Summary'!H72) | M54: =IF('Savings Summary'!J72=0,"",'Savings Summary'!J72) | N54: ='Individual Measure List'!H69 -> #VALUE! | O54: ='Individual Measure List'!J69 -> #NUM! | P54: ='Individual Measure List'!K69 -> #VALUE! | U54: =C54 | V54: =D54 | W54: =E54 | X54: =I54 -> 0 | Y54: =J54 | Z54: =K54 | AA54: =L54 | AB54: =M54 | AC54: =N54 -> #VALUE! | AD54: =O54 -> #NUM! | AE54: =P54 -> #VALUE! | AP54: ='Individual Measure List'!G69 -> 0
A55: =SUM(B6:B55) -> 35 | B55: =IF(ISTEXT(D55)=TRUE,1,0) -> 1 | C55: ='Individual Measure List'!A70 | D55: ='Individual Measure List'!B70 | E55: ='EEM Data Entry'!D145 | F55: ='EEM Data Entry'!E145 | G55: ='EEM Data Entry'!G145 -> N/A | H55: ='EEM Data Entry'!F145 | I55: ='Individual Measure List'!F70 -> 0 | J55: =IF('Savings Summary'!D73=0,"",'Savings Summary'!D73) | K55: =IF('Savings Summary'!F73=0,"",'Savings Summary'!F73) | L55: =IF('Savings Summary'!H73=0,"",'Savings Summary'!H73) | M55: =IF('Savings Summary'!J73=0,"",'Savings Summary'!J73) | N55: ='Individual Measure List'!H70 -> #VALUE! | O55: ='Individual Measure List'!J70 -> #NUM! | P55: ='Individual Measure List'!K70 -> #VALUE! | U55: =C55 | V55: =D55 | W55: =E55 | X55: =I55 -> 0 | Y55: =J55 | Z55: =K55 | AA55: =L55 | AB55: =M55 | AC55: =N55 -> #VALUE! | AD55: =O55 -> #NUM! | AE55: =P55 -> #VALUE! | AP55: ='Individual Measure List'!G70 -> 0
A56: =SUM(B6:B56) -> 36 | B56: =IF(ISTEXT(D56)=TRUE,1,0) -> 1 | C56: ='Individual Measure List'!A71 | D56: ='Individual Measure List'!B71 | E56: ='EEM Data Entry'!D146 | F56: ='EEM Data Entry'!E146 | G56: ='EEM Data Entry'!G146 -> N/A | H56: ='EEM Data Entry'!F146 | I56: ='Individual Measure List'!F71 -> 0 | J56: =IF('Savings Summary'!D74=0,"",'Savings Summary'!D74) | K56: =IF('Savings Summary'!F74=0,"",'Savings Summary'!F74) | L56: =IF('Savings Summary'!H74=0,"",'Savings Summary'!H74) | M56: =IF('Savings Summary'!J74=0,"",'Savings Summary'!J74) | N56: ='Individual Measure List'!H71 -> #VALUE! | O56: ='Individual Measure List'!J71 -> #NUM! | P56: ='Individual Measure List'!K71 -> #VALUE! | U56: =C56 | V56: =D56 | W56: =E56 | X56: =I56 -> 0 | Y56: =J56 | Z56: =K56 | AA56: =L56 | AB56: =M56 | AC56: =N56 -> #VALUE! | AD56: =O56 -> #NUM! | AE56: =P56 -> #VALUE! | AP56: ='Individual Measure List'!G71 -> 0
A57: =SUM(B6:B57) -> 37 | B57: =IF(ISTEXT(D57)=TRUE,1,0) -> 1 | C57: ='Individual Measure List'!A72 | D57: ='Individual Measure List'!B72 | E57: ='EEM Data Entry'!D147 | F57: ='EEM Data Entry'!E147 | G57: ='EEM Data Entry'!G147 -> N/A | H57: ='EEM Data Entry'!F147 | I57: ='Individual Measure List'!F72 -> 0 | J57: =IF('Savings Summary'!D75=0,"",'Savings Summary'!D75) | K57: =IF('Savings Summary'!F75=0,"",'Savings Summary'!F75) | L57: =IF('Savings Summary'!H75=0,"",'Savings Summary'!H75) | M57: =IF('Savings Summary'!J75=0,"",'Savings Summary'!J75) | N57: ='Individual Measure List'!H72 -> #VALUE! | O57: ='Individual Measure List'!J72 -> #NUM! | P57: ='Individual Measure List'!K72 -> #VALUE! | U57: =C57 | V57: =D57 | W57: =E57 | X57: =I57 -> 0 | Y57: =J57 | Z57: =K57 | AA57: =L57 | AB57: =M57 | AC57: =N57 -> #VALUE! | AD57: =O57 -> #NUM! | AE57: =P57 -> #VALUE! | AP57: ='Individual Measure List'!G72 -> 0
A58: =SUM(B6:B58) -> 38 | B58: =IF(ISTEXT(D58)=TRUE,1,0) -> 1 | C58: ='Individual Measure List'!A73 | D58: ='Individual Measure List'!B73 | E58: ='EEM Data Entry'!D148 | F58: ='EEM Data Entry'!E148 | G58: ='EEM Data Entry'!G148 -> N/A | H58: ='EEM Data Entry'!F148 | I58: ='Individual Measure List'!F73 -> 0 | J58: =IF('Savings Summary'!D76=0,"",'Savings Summary'!D76) | K58: =IF('Savings Summary'!F76=0,"",'Savings Summary'!F76) | L58: =IF('Savings Summary'!H76=0,"",'Savings Summary'!H76) | M58: =IF('Savings Summary'!J76=0,"",'Savings Summary'!J76) | N58: ='Individual Measure List'!H73 -> #VALUE! | O58: ='Individual Measure List'!J73 -> #NUM! | P58: ='Individual Measure List'!K73 -> #VALUE! | U58: =C58 | V58: =D58 | W58: =E58 | X58: =I58 -> 0 | Y58: =J58 | Z58: =K58 | AA58: =L58 | AB58: =M58 | AC58: =N58 -> #VALUE! | AD58: =O58 -> #NUM! | AE58: =P58 -> #VALUE! | AP58: ='Individual Measure List'!G73 -> 0
A59: =SUM(B6:B59) -> 39 | B59: =IF(ISTEXT(D59)=TRUE,1,0) -> 1 | C59: ='Individual Measure List'!A74 | D59: ='Individual Measure List'!B74 | E59: ='EEM Data Entry'!D149 | F59: ='EEM Data Entry'!E149 | G59: ='EEM Data Entry'!G149 -> N/A | H59: ='EEM Data Entry'!F149 | I59: ='Individual Measure List'!F74 -> 0 | J59: =IF('Savings Summary'!D77=0,"",'Savings Summary'!D77) | K59: =IF('Savings Summary'!F77=0,"",'Savings Summary'!F77) | L59: =IF('Savings Summary'!H77=0,"",'Savings Summary'!H77) | M59: =IF('Savings Summary'!J77=0,"",'Savings Summary'!J77) | N59: ='Individual Measure List'!H74 -> #VALUE! | O59: ='Individual Measure List'!J74 -> #NUM! | P59: ='Individual Measure List'!K74 -> #VALUE! | U59: =C59 | V59: =D59 | W59: =E59 | X59: =I59 -> 0 | Y59: =J59 | Z59: =K59 | AA59: =L59 | AB59: =M59 | AC59: =N59 -> #VALUE! | AD59: =O59 -> #NUM! | AE59: =P59 -> #VALUE! | AP59: ='Individual Measure List'!G74 -> 0
A60: =SUM(B6:B60) -> 40 | B60: =IF(ISTEXT(D60)=TRUE,1,0) -> 1 | C60: ='Individual Measure List'!A75 | D60: ='Individual Measure List'!B75 | E60: ='EEM Data Entry'!D150 | F60: ='EEM Data Entry'!E150 | G60: ='EEM Data Entry'!G150 -> N/A | H60: ='EEM Data Entry'!F150 | I60: ='Individual Measure List'!F75 -> 0 | J60: =IF('Savings Summary'!D78=0,"",'Savings Summary'!D78) | K60: =IF('Savings Summary'!F78=0,"",'Savings Summary'!F78) | L60: =IF('Savings Summary'!H78=0,"",'Savings Summary'!H78) | M60: =IF('Savings Summary'!J78=0,"",'Savings Summary'!J78) | N60: ='Individual Measure List'!H75 -> #VALUE! | O60: ='Individual Measure List'!J75 -> #NUM! | P60: ='Individual Measure List'!K75 -> #VALUE! | U60: =C60 | V60: =D60 | W60: =E60 | X60: =I60 -> 0 | Y60: =J60 | Z60: =K60 | AA60: =L60 | AB60: =M60 | AC60: =N60 -> #VALUE! | AD60: =O60 -> #NUM! | AE60: =P60 -> #VALUE! | AP60: ='Individual Measure List'!G75 -> 0
C61: *Please see "Note Regarding Incentives" on first page of financial modeling section | U61: *Please see "Note Regarding Incentives" on first page of financial modeling section
C63: PACKAGE | U63: PACKAGE
E65: Capital Investment | F65: Estimated Incentive* | G65: Incentive Reference | H65: Estimated Net Cost | I65: Annual Energy Cost Savings | J65: Annual Electric Savings (kWh) | K65: Annual Oil Savings (Gal) | L65: Annual Nat. Gas Savings (Therms) | M65: Annual Propane Savings (Gal) | N65: Simple Payback (Years) | O65: IRR | P65: NPV | W65: =E65 -> Capital Investment | X65: =I65 -> Annual Energy Cost Savings | Y65: =J65 -> Annual Electric Savings (kWh) | Z65: =K65 -> Annual Oil Savings (Gal) | AA65: =L65 -> Annual Nat. Gas Savings (Therms) | AB65: =M65 -> Annual Propane Savings (Gal) | AC65: =N65 -> Simple Payback (Years) | AD65: =O65 -> IRR | AE65: =P65 -> NPV | AP65: Annual kBTU Savings
D66: ='Packaged EEMs'!B82 -> RECOMMENDED PACKAGE: Example | E66: =SUM('EEM Data Entry'!D85:D108,'EEM Data Entry'!D110:D123,'EEM Data Entry'!D125:D139,'EEM Data Entry'!D141:D154) -> 0 | F66: =SUM('EEM Data Entry'!E85:E108,'EEM Data Entry'!E110:E123,'EEM Data Entry'!E125:E139,'EEM Data Entry'!E141:E154) -> 0 | H66: =SUM('EEM Data Entry'!F85:F108,'EEM Data Entry'!F110:F123,'EEM Data Entry'!F125:F139,'EEM Data Entry'!F141:F154) -> 0 | I66: ='Packaged EEMs'!F82 -> 0 | J66: ='Cascading Savings'!D87 -> 0 | K66: ='Cascading Savings'!F87 -> 0 | L66: ='Cascading Savings'!H87 -> 0 | M66: ='Cascading Savings'!J87 -> 0 | N66: ='Packaged EEMs'!H82 -> #DIV/0! | O66: ='Packaged EEMs'!J82 -> #NUM! | P66: ='Packaged EEMs'!K82 -> 0 | V66: =D66 -> RECOMMENDED PACKAGE: Example | W66: =E66 -> 0 | X66: =I66 -> 0 | Y66: =J66 -> 0 | Z66: =K66 -> 0 | AA66: =L66 -> 0 | AB66: =M66 -> 0 | AC66: =N66 -> #DIV/0! | AD66: =O66 -> #NUM! | AE66: =P66 -> 0 | AP66: ='Packaged EEMs'!G82 -> 0
D67: *Please see "Note Regarding Incentives" on first page of financial modeling section | V67: =D67 -> *Please see "Note Regarding Incentives" on first page of financial modeling section | W67: =E67 -> 0 | X67: =I67 -> 0 | Y67: =J67 -> 0 | Z67: =K67 -> 0 | AA67: =L67 -> 0 | AB67: =M67 -> 0 | AC67: =N67 -> 0 | AD67: =O67 -> 0 | AE67: =P67 -> 0

Sheet RESULTS Eversource
A1: Measure | B1: Installation Cost1,2 | C1: Annual Electric Savings (kWh) | D1: Annual Gas Savings (CCF) | E1: Annual Cost Savings | F1: Simple Payback (years) | G1: Program Path3 | I1: Don't Edit
A2: =IFERROR(_xlfn.CONCAT("ECM-",'RESULTS Eversource'!$I2,": ",VLOOKUP($I2,'RESULTS by Fuel'!$A$6:$P$60,4,FALSE)),"") -> ECM-1: | B2: =IFERROR(VLOOKUP($I2,'RESULTS by Fuel'!$A$6:$P$60,8,FALSE),"") | C2: =IFERROR(VLOOKUP($I2,'RESULTS by Fuel'!$A$6:$P$60,10,FALSE),"") | D2: =IFERROR(VLOOKUP($I2,'RESULTS by Fuel'!$A$6:$P$60,12,FALSE),"") | E2: =IFERROR(VLOOKUP($I2,'RESULTS by Fuel'!$A$6:$P$60,9,FALSE),"") -> 0 | F2: =IFERROR(VLOOKUP($I2,'RESULTS by Fuel'!$A$6:$P$60,14,FALSE),"") | I2: 1
A3: =IFERROR(_xlfn.CONCAT("ECM-",'RESULTS Eversource'!$I3,": ",VLOOKUP($I3,'RESULTS by Fuel'!$A$6:$P$60,4,FALSE)),"") -> ECM-2: | B3: =IFERROR(VLOOKUP($I3,'RESULTS by Fuel'!$A$6:$P$60,8,FALSE),"") | C3: =IFERROR(VLOOKUP($I3,'RESULTS by Fuel'!$A$6:$P$60,10,FALSE),"") | D3: =IFERROR(VLOOKUP($I3,'RESULTS by Fuel'!$A$6:$P$60,12,FALSE),"") | E3: =IFERROR(VLOOKUP($I3,'RESULTS by Fuel'!$A$6:$P$60,9,FALSE),"") -> 0 | F3: =IFERROR(VLOOKUP($I3,'RESULTS by Fuel'!$A$6:$P$60,14,FALSE),"") | I3: 2
A4: =IFERROR(_xlfn.CONCAT("ECM-",'RESULTS Eversource'!$I4,": ",VLOOKUP($I4,'RESULTS by Fuel'!$A$6:$P$60,4,FALSE)),"") -> ECM-3: | B4: =IFERROR(VLOOKUP($I4,'RESULTS by Fuel'!$A$6:$P$60,8,FALSE),"") | C4: =IFERROR(VLOOKUP($I4,'RESULTS by Fuel'!$A$6:$P$60,10,FALSE),"") | D4: =IFERROR(VLOOKUP($I4,'RESULTS by Fuel'!$A$6:$P$60,12,FALSE),"") | E4: =IFERROR(VLOOKUP($I4,'RESULTS by Fuel'!$A$6:$P$60,9,FALSE),"") -> 0 | F4: =IFERROR(VLOOKUP($I4,'RESULTS by Fuel'!$A$6:$P$60,14,FALSE),"") | I4: 3
A5: =IFERROR(_xlfn.CONCAT("ECM-",'RESULTS Eversource'!$I5,": ",VLOOKUP($I5,'RESULTS by Fuel'!$A$6:$P$60,4,FALSE)),"") -> ECM-4: | B5: =IFERROR(VLOOKUP($I5,'RESULTS by Fuel'!$A$6:$P$60,8,FALSE),"") | C5: =IFERROR(VLOOKUP($I5,'RESULTS by Fuel'!$A$6:$P$60,10,FALSE),"") | D5: =IFERROR(VLOOKUP($I5,'RESULTS by Fuel'!$A$6:$P$60,12,FALSE),"") | E5: =IFERROR(VLOOKUP($I5,'RESULTS by Fuel'!$A$6:$P$60,9,FALSE),"") -> 0 | F5: =IFERROR(VLOOKUP($I5,'RESULTS by Fuel'!$A$6:$P$60,14,FALSE),"") | I5: 4
A6: =IFERROR(_xlfn.CONCAT("ECM-",'RESULTS Eversource'!$I6,": ",VLOOKUP($I6,'RESULTS by Fuel'!$A$6:$P$60,4,FALSE)),"") -> ECM-5: | B6: =IFERROR(VLOOKUP($I6,'RESULTS by Fuel'!$A$6:$P$60,8,FALSE),"") | C6: =IFERROR(VLOOKUP($I6,'RESULTS by Fuel'!$A$6:$P$60,10,FALSE),"") | D6: =IFERROR(VLOOKUP($I6,'RESULTS by Fuel'!$A$6:$P$60,12,FALSE),"") | E6: =IFERROR(VLOOKUP($I6,'RESULTS by Fuel'!$A$6:$P$60,9,FALSE),"") -> 0 | F6: =IFERROR(VLOOKUP($I6,'RESULTS by Fuel'!$A$6:$P$60,14,FALSE),"") | I6: 5
A7: Packaged Results | B7: =IFERROR('RESULTS by Fuel'!E66,"") -> 0 | C7: =IFERROR('RESULTS by Fuel'!J66,"") -> 0 | D7: =IFERROR('RESULTS by Fuel'!L66,"") -> 0 | E7: =IFERROR('RESULTS by Fuel'!I66,"") -> 0 | F7: =IFERROR('RESULTS by Fuel'!N66,"") | G7: ---
A8: 1 Budgetary costs provided by RBG.
A9: 2 Installation cost assumes each measure is a retrofit and the total cost is eligible unless end-of-life.
A10: 3 P: Prescriptive, C: Custom, CE: Custom Express, TA: Technical Assistance Study.
A11: 4 These measures are recommended when equipment fails or is nearing the end of useful life. Potential incentives would be based on the incremental cost difference between code-compliant and high efficiency equipment. Only high efficiency equipment is eligible for incentives.
A14: Measure | B14: Installation Cost1,2 | C14: Annual Electric Savings (kWh) | D14: Annual Gas Savings (CCF) | E14: Annual Cost Savings | F14: Simple Payback (years) | G14: Program Path3
A15: =A2 -> ECM-1: | B15: =B2 | C15: =C2 | D15: =D2 | E15: =E2 -> 0 | F15: =F2 | G15: =G2 -> 0
A16: =A3 -> ECM-2: | B16: =B3 | C16: =C3 | D16: =D3 | E16: =E3 -> 0 | F16: =F3 | G16: =G3 -> 0
A17: =A4 -> ECM-3: | B17: =B4 | C17: =C4 | D17: =D4 | E17: =E4 -> 0 | F17: =F4 | G17: =G4 -> 0
A18: =A5 -> ECM-4: | B18: =B5 | C18: =C5 | D18: =D5 | E18: =E5 -> 0 | F18: =F5 | G18: =G5 -> 0
A19: =A6 -> ECM-5: | B19: =B6 | C19: =C6 | D19: =D6 | E19: =E6 -> 0 | F19: =F6 | G19: =G6 -> 0
A20: =A7 -> Packaged Results | B20: =B7 -> 0 | C20: =C7 -> 0 | D20: =D7 -> 0 | E20: =E7 -> 0 | F20: =F7 | G20: =G7 -> ---
A21: 1 Budgetary costs provided by GDS.
A22: 2 Installation cost assumes each measure is a retrofit and the total cost is eligible unless end-of-life.
A23: 3 P: Prescriptive, C: Custom, CE: Custom Express, TA: Technical Assistance Study.
A24: 4 These measures are recommended when equipment fails or is nearing the end of useful life. Potential incentives would be based on the incremental cost difference between code-compliant and high efficiency equipment. Only high efficiency equipment is eligible for incentives.

Sheet Individual Measure List
C1: Assumptions : | D1: Electricity | F1: Fuel Oil | H1: Natural Gas | J1: Propane | L1: District Steam | Q1: Wood Pellets | S1: Wood Chips | U1: Water/Sewer | W1: Total Energy
C2: Baseline Energy Usage: | D2: ='Savings Summary'!D3 -> 0 | E2: ='Savings Summary'!E3 -> kWH | F2: ='Savings Summary'!F3 -> 0 | G2: ='Savings Summary'!G3 -> Gallons | H2: ='Savings Summary'!H3 -> 0 | I2: ='Savings Summary'!I3 -> Therms | J2: ='Savings Summary'!J3 -> 0 | K2: ='Savings Summary'!K3 -> gallons | ... M2: ='Savings Summary'!M3 -> kPounds | Q2: ='Savings Summary'!N3 -> 0 | R2: ='Savings Summary'!O3 -> tons | S2: ='Savings Summary'!P3 -> 0 | T2: ='Savings Summary'!Q3 -> tons | U2: ='Savings Summary'!R3 -> 0 | V2: ='Savings Summary'!S3 -> kGallons | W2: ='Savings Summary'!T3 -> 0 | X2: ='Savings Summary'!U3 -> kBTU
C3: Baseline Energy Cost: | D3: ='Savings Summary'!D4 -> 0 | E3: ='Savings Summary'!E4 -> (elect.) | F3: ='Savings Summary'!F4 -> 0 | G3: ='Savings Summary'!G4 -> 0 | H3: ='Savings Summary'!H4 -> 0 | I3: ='Savings Summary'!I4 -> 0 | J3: ='Savings Summary'!J4 -> 0 | K3: ='Savings Summary'!K4 -> 0 | ... M3: ='Savings Summary'!M4 -> 0 | Q3: ='Savings Summary'!N4 -> 0 | R3: ='Savings Summary'!O4 -> 0 | S3: ='Savings Summary'!P4 -> 0 | T3: ='Savings Summary'!Q4 -> 0 | U3: ='Savings Summary'!R4 -> 0 | V3: ='Savings Summary'!S4 -> 0 | W3: ='Savings Summary'!T4 -> 0 | X3: Cost
C4: Baseline Unit Cost: | D4: ='Savings Summary'!D5 -> 0 | E4: ='Savings Summary'!E5 -> ($/kWh) | F4: ='Savings Summary'!F5 -> 0 | G4: ='Savings Summary'!G5 -> ($/gal.) | H4: ='Savings Summary'!H5 -> 0 | I4: ='Savings Summary'!I5 -> ($/therm) | J4: ='Savings Summary'!J5 -> 0 | K4: ='Savings Summary'!K5 -> ($/gal.) | ... M4: ='Savings Summary'!M5 -> ($/kLbs..) | Q4: ='Savings Summary'!N5 -> 0 | R4: ='Savings Summary'!O5 -> ($/ton) | S4: ='Savings Summary'!P5 -> 0 | T4: ='Savings Summary'!Q5 -> ($/ton) | U4: ='Savings Summary'!R5 -> 0 | V4: ='Savings Summary'!S5 -> ($/gal.) | W4: ='Savings Summary'!T5 -> 0 | X4: ='Savings Summary'!U5 -> 0
A6: Financial Analysis
A7: EEM # | B7: BUILDING ENVELOPE UPGRADES | C7: CAPITAL INVESTMENT | D7: END-OF-LIFE | E7: ENERGY INVESTMENT | F7: ANNUAL ENERGY COST SAVINGS | G7: ANNUAL ENERGY SAVINGS kBTU | H7: SIMPLE PAYBACK | I7: RECO-MMEND | J7: IRR | K7: NPV | L7: LIFETIME | M7: ROI | Q7: Cost | R7: 1 | S7: 2 | T7: 3 | U7: 4 | V7: 5 | W7: 6 | X7: 7 | Y7: 8 | Z7: 9 | AA7: 10 | AB7: 11 | AC7: 12 | AD7: 13 | AE7: 14 | AF7: 15 | AG7: 16 | AH7: 17 | AI7: 18 | AJ7: 19 | AK7: 20 | AL7: 21 | AM7: 22 | AN7: 23 | AO7: 24 | AP7: 25 | AQ7: 26 | AR7: 27 | AS7: 28 | AT7: 29 | AU7: 30 | AV7: 31 | AW7: 32 | AX7: 33 | AY7: 34 | AZ7: 35 | BA7: 36 | BB7: 37 | BC7: 38 | BD7: 39 | BE7: 40 | BF7: 41 | BG7: 42 | BH7: 43 | BI7: 44 | BJ7: 45 | BK7: 46 | BL7: 47 | BM7: 48 | BN7: 49 | BO7: 50 | BP7: 51 | BQ7: 52 | BR7: 53 | BS7: 54 | BT7: 55 | BU7: 56 | BV7: 57 | BW7: 58 | BX7: 59 | BY7: 60 | BZ7: 61 | CA7: 62 | CB7: 63 | CC7: 64 | CD7: 65 | CE7: 66 | CF7: 67 | CG7: 68 | CH7: 69 | CI7: 70 | CJ7: 71 | CK7: 72 | CL7: 73 | CM7: 74 | CN7: 75 | CO7: 76 | CP7: 77 | CQ7: 78 | CR7: 79 | CS7: 80 | CT7: 81 | CU7: 82 | CV7: 83 | CW7: 84 | CX7: 85 | CY7: 86 | CZ7: 87 | DA7: 88 | DB7: 89 | DC7: 90 | DD7: 91 | DE7: 92 | DF7: 93 | DG7: 94 | DH7: 95 | DI7: 96 | DJ7: 97 | DK7: 98 | DL7: 99 | DM7: 100
A8: ='EEM Data Entry'!A85 | B8: ='EEM Data Entry'!B85 | C8: ='EEM Data Entry'!F85 | D8: 0 | E8: =C8-D8 -> #VALUE! | F8: =('Savings Summary'!D7*'Savings Summary'!D$5)+('Savings Summary'!F7*'Savings Summary'!F$5)+('Savings Summary'!H7*'Savings Summary'!H$5)+('Savings Summary'!J7*'Savings Summary'!J$5)+('Savings Summary'!L7*'Savings Summary'!L$5)+('Savings Summary'!N7*'Savings Summary'!N$5)+('Savings Summary'!P7*'Savings Summary'!P$5)+('Savings Summary'!R7*'Savings Summary'!R$5) -> 0 | G8: ='Savings Summary'!T7 -> 0 | H8: =IF(C8=0,"n/a",E8/F8) -> #VALUE! | I8: =IF(H8=0, "n/a", IF(H8>100, "no",IF(H8<0, "no", "yes"))) -> #VALUE! | J8: =IRR(Q8:DM8,0.1) -> #NUM! | K8: =PV('Interest Rate'!$B$17,Table6[[#This Row],[LIFETIME]],-Table6[[#This Row],[ANNUAL ENERGY COST SAVINGS]],Table6[[#This Row],[END-OF-LIFE]],0)-Table6[[#This Row],[CAPITAL INVESTMENT]] -> #VALUE! | L8: ='EEM Data Entry'!C85 | M8: =Table6[[#This Row],[ANNUAL ENERGY COST SAVINGS]]/Table6[[#This Row],[CAPITAL INVESTMENT]] -> #VALUE! | N8: =Table6[[#This Row],[LIFETIME]] | Q8: =IF(ISNUMBER(E8)=TRUE,-E8,"") | R8: =F8 -> 0 | S8: =IF(S$7>$N8,0,R8*(1-'Interest Rate'!$B$17)) -> 0 | T8: =IF(T$7>$N8,0,S8*(1-'Interest Rate'!$B$17)) -> 0 | U8: =IF(U$7>$N8,0,T8*(1-'Interest Rate'!$B$17)) -> 0 | V8: =IF(V$7>$N8,0,U8*(1-'Interest Rate'!$B$17)) -> 0 | W8: =IF(W$7>$N8,0,V8*(1-'Interest Rate'!$B$17)) -> 0 | X8: =IF(X$7>$N8,0,W8*(1-'Interest Rate'!$B$17)) -> 0 | Y8: =IF(Y$7>$N8,0,X8*(1-'Interest Rate'!$B$17)) -> 0 | Z8: =IF(Z$7>$N8,0,Y8*(1-'Interest Rate'!$B$17)) -> 0 | ... DM8: =IF(DM$7>$N8,0,DL8*(1-'Interest Rate'!$B$17)) -> 0
A9: ='EEM Data Entry'!A86 | B9: ='EEM Data Entry'!B86 | C9: ='EEM Data Entry'!F86 | D9: 0 | E9: =C9-D9 -> #VALUE! | F9: =('Savings Summary'!D8*'Savings Summary'!D$5)+('Savings Summary'!F8*'Savings Summary'!F$5)+('Savings Summary'!H8*'Savings Summary'!H$5)+('Savings Summary'!J8*'Savings Summary'!J$5)+('Savings Summary'!L8*'Savings Summary'!L$5)+('Savings Summary'!N8*'Savings Summary'!N$5)+('Savings Summary'!P8*'Savings Summary'!P$5)+('Savings Summary'!R8*'Savings Summary'!R$5) -> 0 | G9: ='Savings Summary'!T8 -> 0 | H9: =IF(C9=0,"n/a",E9/F9) -> #VALUE! | I9: =IF(H9=0, "n/a", IF(H9>100, "no",IF(H9<0, "no", "yes"))) -> #VALUE! | J9: =IRR(Q9:DM9,0.1) -> #NUM! | K9: =PV('Interest Rate'!$B$17,Table6[[#This Row],[LIFETIME]],-Table6[[#This Row],[ANNUAL ENERGY COST SAVINGS]],Table6[[#This Row],[END-OF-LIFE]],0)-Table6[[#This Row],[CAPITAL INVESTMENT]] -> #VALUE! | L9: ='EEM Data Entry'!C86 | M9: =Table6[[#This Row],[ANNUAL ENERGY COST SAVINGS]]/Table6[[#This Row],[CAPITAL INVESTMENT]] -> #VALUE! | N9: =Table6[[#This Row],[LIFETIME]] | Q9: =IF(ISNUMBER(E9)=TRUE,-E9,"") | R9: =F9 -> 0 | S9: =IF(S$7>$N9,0,R9*(1-'Interest Rate'!$B$17)) -> 0 | T9: =IF(T$7>$N9,0,S9*(1-'Interest Rate'!$B$17)) -> 0 | U9: =IF(U$7>$N9,0,T9*(1-'Interest Rate'!$B$17)) -> 0 | V9: =IF(V$7>$N9,0,U9*(1-'Interest Rate'!$B$17)) -> 0 | W9: =IF(W$7>$N9,0,V9*(1-'Interest Rate'!$B$17)) -> 0 | X9: =IF(X$7>$N9,0,W9*(1-'Interest Rate'!$B$17)) -> 0 | Y9: =IF(Y$7>$N9,0,X9*(1-'Interest Rate'!$B$17)) -> 0 | Z9: =IF(Z$7>$N9,0,Y9*(1-'Interest Rate'!$B$17)) -> 0 | ... DM9: =IF(DM$7>$N9,0,DL9*(1-'Interest Rate'!$B$17)) -> 0
A10: ='EEM Data Entry'!A87 | B10: ='EEM Data Entry'!B87 | C10: ='EEM Data Entry'!F87 | D10: 0 | E10: =C10-D10 -> #VALUE! | F10: =('Savings Summary'!D9*'Savings Summary'!D$5)+('Savings Summary'!F9*'Savings Summary'!F$5)+('Savings Summary'!H9*'Savings Summary'!H$5)+('Savings Summary'!J9*'Savings Summary'!J$5)+('Savings Summary'!L9*'Savings Summary'!L$5)+('Savings Summary'!N9*'Savings Summary'!N$5)+('Savings Summary'!P9*'Savings Summary'!P$5)+('Savings Summary'!R9*'Savings Summary'!R$5) -> 0 | G10: ='Savings Summary'!T9 -> 0 | H10: =IF(C10=0,"n/a",E10/F10) -> #VALUE! | I10: =IF(H10=0, "n/a", IF(H10>100, "no",IF(H10<0, "no", "yes"))) -> #VALUE! | J10: =IRR(Q10:DM10,0.1) -> #NUM! | K10: =PV('Interest Rate'!$B$17,Table6[[#This Row],[LIFETIME]],-Table6[[#This Row],[ANNUAL ENERGY COST SAVINGS]],Table6[[#This Row],[END-OF-LIFE]],0)-Table6[[#This Row],[CAPITAL INVESTMENT]] -> #VALUE! | L10: ='EEM Data Entry'!C87 | M10: =Table6[[#This Row],[ANNUAL ENERGY COST SAVINGS]]/Table6[[#This Row],[CAPITAL INVESTMENT]] -> #VALUE! | N10: =Table6[[#This Row],[LIFETIME]] | Q10: =IF(ISNUMBER(E10)=TRUE,-E10,"") | R10: =F10 -> 0 | S10: =IF(S$7>$N10,0,R10*(1-'Interest Rate'!$B$17)) -> 0 | T10: =IF(T$7>$N10,0,S10*(1-'Interest Rate'!$B$17)) -> 0 | U10: =IF(U$7>$N10,0,T10*(1-'Interest Rate'!$B$17)) -> 0 | V10: =IF(V$7>$N10,0,U10*(1-'Interest Rate'!$B$17)) -> 0 | W10: =IF(W$7>$N10,0,V10*(1-'Interest Rate'!$B$17)) -> 0 | X10: =IF(X$7>$N10,0,W10*(1-'Interest Rate'!$B$17)) -> 0 | Y10: =IF(Y$7>$N10,0,X10*(1-'Interest Rate'!$B$17)) -> 0 | Z10: =IF(Z$7>$N10,0,Y10*(1-'Interest Rate'!$B$17)) -> 0 | ... DM10: =IF(DM$7>$N10,0,DL10*(1-'Interest Rate'!$B$17)) -> 0
A11: ='EEM Data Entry'!A88 | B11: ='EEM Data Entry'!B88 | C11: ='EEM Data Entry'!F88 | D11: 0 | E11: =C11-D11 -> #VALUE! | F11: =('Savings Summary'!D10*'Savings Summary'!D$5)+('Savings Summary'!F10*'Savings Summary'!F$5)+('Savings Summary'!H10*'Savings Summary'!H$5)+('Savings Summary'!J10*'Savings Summary'!J$5)+('Savings Summary'!L10*'Savings Summary'!L$5)+('Savings Summary'!N10*'Savings Summary'!N$5)+('Savings Summary'!P10*'Savings Summary'!P$5)+('Savings Summary'!R10*'Savings Summary'!R$5) -> 0 | G11: ='Savings Summary'!T10 -> 0 | H11: =IF(C11=0,"n/a",E11/F11) -> #VALUE! | I11: =IF(H11=0, "n/a", IF(H11>100, "no",IF(H11<0, "no", "yes"))) -> #VALUE! | J11: =IRR(Q11:DM11,0.1) -> #NUM! | K11: =PV('Interest Rate'!$B$17,Table6[[#This Row],[LIFETIME]],-Table6[[#This Row],[ANNUAL ENERGY COST SAVINGS]],Table6[[#This Row],[END-OF-LIFE]],0)-Table6[[#This Row],[CAPITAL INVESTMENT]] -> #VALUE! | L11: ='EEM Data Entry'!C88 | M11: =Table6[[#This Row],[ANNUAL ENERGY COST SAVINGS]]/Table6[[#This Row],[CAPITAL INVESTMENT]] -> #VALUE! | N11: =Table6[[#This Row],[LIFETIME]] | Q11: =IF(ISNUMBER(E11)=TRUE,-E11,"") | R11: =F11 -> 0 | S11: =IF(S$7>$N11,0,R11*(1-'Interest Rate'!$B$17)) -> 0 | T11: =IF(T$7>$N11,0,S11*(1-'Interest Rate'!$B$17)) -> 0 | U11: =IF(U$7>$N11,0,T11*(1-'Interest Rate'!$B$17)) -> 0 | V11: =IF(V$7>$N11,0,U11*(1-'Interest Rate'!$B$17)) -> 0 | W11: =IF(W$7>$N11,0,V11*(1-'Interest Rate'!$B$17)) -> 0 | X11: =IF(X$7>$N11,0,W11*(1-'Interest Rate'!$B$17)) -> 0 | Y11: =IF(Y$7>$N11,0,X11*(1-'Interest Rate'!$B$17)) -> 0 | Z11: =IF(Z$7>$N11,0,Y11*(1-'Interest Rate'!$B$17)) -> 0 | ... DM11: =IF(DM$7>$N11,0,DL11*(1-'Interest Rate'!$B$17)) -> 0
A12: ='EEM Data Entry'!A89 | B12: ='EEM Data Entry'!B89 | C12: ='EEM Data Entry'!F89 | D12: 0 | E12: =C12-D12 -> #VALUE! | F12: =('Savings Summary'!D11*'Savings Summary'!D$5)+('Savings Summary'!F11*'Savings Summary'!F$5)+('Savings Summary'!H11*'Savings Summary'!H$5)+('Savings Summary'!J11*'Savings Summary'!J$5)+('Savings Summary'!L11*'Savings Summary'!L$5)+('Savings Summary'!N11*'Savings Summary'!N$5)+('Savings Summary'!P11*'Savings Summary'!P$5)+('Savings Summary'!R11*'Savings Summary'!R$5) -> 0 | G12: ='Savings Summary'!T11 -> 0 | H12: =IF(C12=0,"n/a",E12/F12) -> #VALUE! | I12: =IF(H12=0, "n/a", IF(H12>100, "no",IF(H12<0, "no", "yes"))) -> #VALUE! | J12: =IRR(Q12:DM12,0.1) -> #NUM! | K12: =PV('Interest Rate'!$B$17,Table6[[#This Row],[LIFETIME]],-Table6[[#This Row],[ANNUAL ENERGY COST SAVINGS]],Table6[[#This Row],[END-OF-LIFE]],0)-Table6[[#This Row],[CAPITAL INVESTMENT]] -> #VALUE! | L12: ='EEM Data Entry'!C89 | M12: =Table6[[#This Row],[ANNUAL ENERGY COST SAVINGS]]/Table6[[#This Row],[CAPITAL INVESTMENT]] -> #VALUE! | N12: =Table6[[#This Row],[LIFETIME]] | Q12: =IF(ISNUMBER(E12)=TRUE,-E12,"") | R12: =F12 -> 0 | S12: =IF(S$7>$N12,0,R12*(1-'Interest Rate'!$B$17)) -> 0 | T12: =IF(T$7>$N12,0,S12*(1-'Interest Rate'!$B$17)) -> 0 | U12: =IF(U$7>$N12,0,T12*(1-'Interest Rate'!$B$17)) -> 0 | V12: =IF(V$7>$N12,0,U12*(1-'Interest Rate'!$B$17)) -> 0 | W12: =IF(W$7>$N12,0,V12*(1-'Interest Rate'!$B$17)) -> 0 | X12: =IF(X$7>$N12,0,W12*(1-'Interest Rate'!$B$17)) -> 0 | Y12: =IF(Y$7>$N12,0,X12*(1-'Interest Rate'!$B$17)) -> 0 | Z12: =IF(Z$7>$N12,0,Y12*(1-'Interest Rate'!$B$17)) -> 0 | ... DM12: =IF(DM$7>$N12,0,DL12*(1-'Interest Rate'!$B$17)) -> 0
A13: ='EEM Data Entry'!A90 | B13: ='EEM Data Entry'!B90 | C13: ='EEM Data Entry'!F90 | D13: 0 | E13: =C13-D13 -> #VALUE! | F13: =('Savings Summary'!D12*'Savings Summary'!D$5)+('Savings Summary'!F12*'Savings Summary'!F$5)+('Savings Summary'!H12*'Savings Summary'!H$5)+('Savings Summary'!J12*'Savings Summary'!J$5)+('Savings Summary'!L12*'Savings Summary'!L$5)+('Savings Summary'!N12*'Savings Summary'!N$5)+('Savings Summary'!P12*'Savings Summary'!P$5)+('Savings Summary'!R12*'Savings Summary'!R$5) -> 0 | G13: ='Savings Summary'!T12 -> 0 | H13: =IF(C13=0,"n/a",E13/F13) -> #VALUE! | I13: =IF(H13=0, "n/a", IF(H13>100, "no",IF(H13<0, "no", "yes"))) -> #VALUE! | J13: =IRR(Q13:DM13,0.1) -> #NUM! | K13: =PV('Interest Rate'!$B$17,Table6[[#This Row],[LIFETIME]],-Table6[[#This Row],[ANNUAL ENERGY COST SAVINGS]],Table6[[#This Row],[END-OF-LIFE]],0)-Table6[[#This Row],[CAPITAL INVESTMENT]] -> #VALUE! | L13: ='EEM Data Entry'!C90 | M13: =Table6[[#This Row],[ANNUAL ENERGY COST SAVINGS]]/Table6[[#This Row],[CAPITAL INVESTMENT]] -> #VALUE! | N13: =Table6[[#This Row],[LIFETIME]] | Q13: =IF(ISNUMBER(E13)=TRUE,-E13,"") | R13: =F13 -> 0 | S13: =IF(S$7>$N13,0,R13*(1-'Interest Rate'!$B$17)) -> 0 | T13: =IF(T$7>$N13,0,S13*(1-'Interest Rate'!$B$17)) -> 0 | U13: =IF(U$7>$N13,0,T13*(1-'Interest Rate'!$B$17)) -> 0 | V13: =IF(V$7>$N13,0,U13*(1-'Interest Rate'!$B$17)) -> 0 | W13: =IF(W$7>$N13,0,V13*(1-'Interest Rate'!$B$17)) -> 0 | X13: =IF(X$7>$N13,0,W13*(1-'Interest Rate'!$B$17)) -> 0 | Y13: =IF(Y$7>$N13,0,X13*(1-'Interest Rate'!$B$17)) -> 0 | Z13: =IF(Z$7>$N13,0,Y13*(1-'Interest Rate'!$B$17)) -> 0 | ... DM13: =IF(DM$7>$N13,0,DL13*(1-'Interest Rate'!$B$17)) -> 0
A14: ='EEM Data Entry'!A91 | B14: ='EEM Data Entry'!B91 | C14: ='EEM Data Entry'!F91 | D14: 0 | E14: =C14-D14 -> #VALUE! | F14: =('Savings Summary'!D13*'Savings Summary'!D$5)+('Savings Summary'!F13*'Savings Summary'!F$5)+('Savings Summary'!H13*'Savings Summary'!H$5)+('Savings Summary'!J13*'Savings Summary'!J$5)+('Savings Summary'!L13*'Savings Summary'!L$5)+('Savings Summary'!N13*'Savings Summary'!N$5)+('Savings Summary'!P13*'Savings Summary'!P$5)+('Savings Summary'!R13*'Savings Summary'!R$5) -> 0 | G14: ='Savings Summary'!T13 -> 0 | H14: =IF(C14=0,"n/a",E14/F14) -> #VALUE! | I14: =IF(H14=0, "n/a", IF(H14>100, "no",IF(H14<0, "no", "yes"))) -> #VALUE! | J14: =IRR(Q14:DM14,0.1) -> #NUM! | K14: =PV('Interest Rate'!$B$17,Table6[[#This Row],[LIFETIME]],-Table6[[#This Row],[ANNUAL ENERGY COST SAVINGS]],Table6[[#This Row],[END-OF-LIFE]],0)-Table6[[#This Row],[CAPITAL INVESTMENT]] -> #VALUE! | L14: ='EEM Data Entry'!C91 | M14: =Table6[[#This Row],[ANNUAL ENERGY COST SAVINGS]]/Table6[[#This Row],[CAPITAL INVESTMENT]] -> #VALUE! | N14: =Table6[[#This Row],[LIFETIME]] | Q14: =IF(ISNUMBER(E14)=TRUE,-E14,"") | R14: =F14 -> 0 | S14: =IF(S$7>$N14,0,R14*(1-'Interest Rate'!$B$17)) -> 0 | T14: =IF(T$7>$N14,0,S14*(1-'Interest Rate'!$B$17)) -> 0 | U14: =IF(U$7>$N14,0,T14*(1-'Interest Rate'!$B$17)) -> 0 | V14: =IF(V$7>$N14,0,U14*(1-'Interest Rate'!$B$17)) -> 0 | W14: =IF(W$7>$N14,0,V14*(1-'Interest Rate'!$B$17)) -> 0 | X14: =IF(X$7>$N14,0,W14*(1-'Interest Rate'!$B$17)) -> 0 | Y14: =IF(Y$7>$N14,0,X14*(1-'Interest Rate'!$B$17)) -> 0 | Z14: =IF(Z$7>$N14,0,Y14*(1-'Interest Rate'!$B$17)) -> 0 | ... DM14: =IF(DM$7>$N14,0,DL14*(1-'Interest Rate'!$B$17)) -> 0
A15: ='EEM Data Entry'!A92 | B15: ='EEM Data Entry'!B92 | C15: ='EEM Data Entry'!F92 | D15: 0 | E15: =C15-D15 -> #VALUE! | F15: =('Savings Summary'!D14*'Savings Summary'!D$5)+('Savings Summary'!F14*'Savings Summary'!F$5)+('Savings Summary'!H14*'Savings Summary'!H$5)+('Savings Summary'!J14*'Savings Summary'!J$5)+('Savings Summary'!L14*'Savings Summary'!L$5)+('Savings Summary'!N14*'Savings Summary'!N$5)+('Savings Summary'!P14*'Savings Summary'!P$5)+('Savings Summary'!R14*'Savings Summary'!R$5) -> 0 | G15: ='Savings Summary'!T14 -> 0 | H15: =IF(C15=0,"n/a",E15/F15) -> #VALUE! | I15: =IF(H15=0, "n/a", IF(H15>100, "no",IF(H15<0, "no", "yes"))) -> #VALUE! | J15: =IRR(Q15:DM15,0.1) -> #NUM! | K15: =PV('Interest Rate'!$B$17,Table6[[#This Row],[LIFETIME]],-Table6[[#This Row],[ANNUAL ENERGY COST SAVINGS]],Table6[[#This Row],[END-OF-LIFE]],0)-Table6[[#This Row],[CAPITAL INVESTMENT]] -> #VALUE! | L15: ='EEM Data Entry'!C92 | M15: =Table6[[#This Row],[ANNUAL ENERGY COST SAVINGS]]/Table6[[#This Row],[CAPITAL INVESTMENT]] -> #VALUE! | N15: =Table6[[#This Row],[LIFETIME]] | Q15: =IF(ISNUMBER(E15)=TRUE,-E15,"") | R15: =F15 -> 0 | S15: =IF(S$7>$N15,0,R15*(1-'Interest Rate'!$B$17)) -> 0 | T15: =IF(T$7>$N15,0,S15*(1-'Interest Rate'!$B$17)) -> 0 | U15: =IF(U$7>$N15,0,T15*(1-'Interest Rate'!$B$17)) -> 0 | V15: =IF(V$7>$N15,0,U15*(1-'Interest Rate'!$B$17)) -> 0 | W15: =IF(W$7>$N15,0,V15*(1-'Interest Rate'!$B$17)) -> 0 | X15: =IF(X$7>$N15,0,W15*(1-'Interest Rate'!$B$17)) -> 0 | Y15: =IF(Y$7>$N15,0,X15*(1-'Interest Rate'!$B$17)) -> 0 | Z15: =IF(Z$7>$N15,0,Y15*(1-'Interest Rate'!$B$17)) -> 0 | ... DM15: =IF(DM$7>$N15,0,DL15*(1-'Interest Rate'!$B$17)) -> 0
A16: ='EEM Data Entry'!A93 | B16: ='EEM Data Entry'!B93 | C16: ='EEM Data Entry'!F93 | D16: 0 | E16: =C16-D16 -> #VALUE! | F16: =('Savings Summary'!D15*'Savings Summary'!D$5)+('Savings Summary'!F15*'Savings Summary'!F$5)+('Savings Summary'!H15*'Savings Summary'!H$5)+('Savings Summary'!J15*'Savings Summary'!J$5)+('Savings Summary'!L15*'Savings Summary'!L$5)+('Savings Summary'!N15*'Savings Summary'!N$5)+('Savings Summary'!P15*'Savings Summary'!P$5)+('Savings Summary'!R15*'Savings Summary'!R$5) -> 0 | G16: ='Savings Summary'!T15 -> 0 | H16: =IF(C16=0,"n/a",E16/F16) -> #VALUE! | I16: =IF(H16=0, "n/a", IF(H16>100, "no",IF(H16<0, "no", "yes"))) -> #VALUE! | J16: =IRR(Q16:DM16,0.1) -> #NUM! | K16: =PV('Interest Rate'!$B$17,Table6[[#This Row],[LIFETIME]],-Table6[[#This Row],[ANNUAL ENERGY COST SAVINGS]],Table6[[#This Row],[END-OF-LIFE]],0)-Table6[[#This Row],[CAPITAL INVESTMENT]] -> #VALUE! | L16: ='EEM Data Entry'!C93 | M16: =Table6[[#This Row],[ANNUAL ENERGY COST SAVINGS]]/Table6[[#This Row],[CAPITAL INVESTMENT]] -> #VALUE! | N16: =Table6[[#This Row],[LIFETIME]] | Q16: =IF(ISNUMBER(E16)=TRUE,-E16,"") | R16: =F16 -> 0 | S16: =IF(S$7>$N16,0,R16*(1-'Interest Rate'!$B$17)) -> 0 | T16: =IF(T$7>$N16,0,S16*(1-'Interest Rate'!$B$17)) -> 0 | U16: =IF(U$7>$N16,0,T16*(1-'Interest Rate'!$B$17)) -> 0 | V16: =IF(V$7>$N16,0,U16*(1-'Interest Rate'!$B$17)) -> 0 | W16: =IF(W$7>$N16,0,V16*(1-'Interest Rate'!$B$17)) -> 0 | X16: =IF(X$7>$N16,0,W16*(1-'Interest Rate'!$B$17)) -> 0 | Y16: =IF(Y$7>$N16,0,X16*(1-'Interest Rate'!$B$17)) -> 0 | Z16: =IF(Z$7>$N16,0,Y16*(1-'Interest Rate'!$B$17)) -> 0 | ... DM16: =IF(DM$7>$N16,0,DL16*(1-'Interest Rate'!$B$17)) -> 0
A17: ='EEM Data Entry'!A94 | B17: ='EEM Data Entry'!B94 | C17: ='EEM Data Entry'!F94 | D17: 0 | E17: =C17-D17 -> #VALUE! | F17: =('Savings Summary'!D16*'Savings Summary'!D$5)+('Savings Summary'!F16*'Savings Summary'!F$5)+('Savings Summary'!H16*'Savings Summary'!H$5)+('Savings Summary'!J16*'Savings Summary'!J$5)+('Savings Summary'!L16*'Savings Summary'!L$5)+('Savings Summary'!N16*'Savings Summary'!N$5)+('Savings Summary'!P16*'Savings Summary'!P$5)+('Savings Summary'!R16*'Savings Summary'!R$5) -> 0 | G17: ='Savings Summary'!T16 -> 0 | H17: =IF(C17=0,"n/a",E17/F17) -> #VALUE! | I17: =IF(H17=0, "n/a", IF(H17>100, "no",IF(H17<0, "no", "yes"))) -> #VALUE! | J17: =IRR(Q17:DM17,0.1) -> #NUM! | K17: =PV('Interest Rate'!$B$17,Table6[[#This Row],[LIFETIME]],-Table6[[#This Row],[ANNUAL ENERGY COST SAVINGS]],Table6[[#This Row],[END-OF-LIFE]],0)-Table6[[#This Row],[CAPITAL INVESTMENT]] -> #VALUE! | L17: ='EEM Data Entry'!C94 | M17: =Table6[[#This Row],[ANNUAL ENERGY COST SAVINGS]]/Table6[[#This Row],[CAPITAL INVESTMENT]] -> #VALUE! | N17: =Table6[[#This Row],[LIFETIME]] | Q17: =IF(ISNUMBER(E17)=TRUE,-E17,"") | R17: =F17 -> 0 | S17: =IF(S$7>$N17,0,R17*(1-'Interest Rate'!$B$17)) -> 0 | T17: =IF(T$7>$N17,0,S17*(1-'Interest Rate'!$B$17)) -> 0 | U17: =IF(U$7>$N17,0,T17*(1-'Interest Rate'!$B$17)) -> 0 | V17: =IF(V$7>$N17,0,U17*(1-'Interest Rate'!$B$17)) -> 0 | W17: =IF(W$7>$N17,0,V17*(1-'Interest Rate'!$B$17)) -> 0 | X17: =IF(X$7>$N17,0,W17*(1-'Interest Rate'!$B$17)) -> 0 | Y17: =IF(Y$7>$N17,0,X17*(1-'Interest Rate'!$B$17)) -> 0 | Z17: =IF(Z$7>$N17,0,Y17*(1-'Interest Rate'!$B$17)) -> 0 | ... DM17: =IF(DM$7>$N17,0,DL17*(1-'Interest Rate'!$B$17)) -> 0
A18: ='EEM Data Entry'!A95 | B18: ='EEM Data Entry'!B95 | C18: ='EEM Data Entry'!F95 | D18: 0 | E18: =C18-D18 -> #VALUE! | F18: =('Savings Summary'!D17*'Savings Summary'!D$5)+('Savings Summary'!F17*'Savings Summary'!F$5)+('Savings Summary'!H17*'Savings Summary'!H$5)+('Savings Summary'!J17*'Savings Summary'!J$5)+('Savings Summary'!L17*'Savings Summary'!L$5)+('Savings Summary'!N17*'Savings Summary'!N$5)+('Savings Summary'!P17*'Savings Summary'!P$5)+('Savings Summary'!R17*'Savings Summary'!R$5) -> 0 | G18: ='Savings Summary'!T17 -> 0 | H18: =IF(C18=0,"n/a",E18/F18) -> #VALUE! | I18: =IF(H18=0, "n/a", IF(H18>100, "no",IF(H18<0, "no", "yes"))) -> #VALUE! | J18: =IRR(Q18:DM18,0.1) -> #NUM! | K18: =PV('Interest Rate'!$B$17,Table6[[#This Row],[LIFETIME]],-Table6[[#This Row],[ANNUAL ENERGY COST SAVINGS]],Table6[[#This Row],[END-OF-LIFE]],0)-Table6[[#This Row],[CAPITAL INVESTMENT]] -> #VALUE! | L18: ='EEM Data Entry'!C95 | M18: =Table6[[#This Row],[ANNUAL ENERGY COST SAVINGS]]/Table6[[#This Row],[CAPITAL INVESTMENT]] -> #VALUE! | N18: =Table6[[#This Row],[LIFETIME]] | Q18: =IF(ISNUMBER(E18)=TRUE,-E18,"") | R18: =F18 -> 0 | S18: =IF(S$7>$N18,0,R18*(1-'Interest Rate'!$B$17)) -> 0 | T18: =IF(T$7>$N18,0,S18*(1-'Interest Rate'!$B$17)) -> 0 | U18: =IF(U$7>$N18,0,T18*(1-'Interest Rate'!$B$17)) -> 0 | V18: =IF(V$7>$N18,0,U18*(1-'Interest Rate'!$B$17)) -> 0 | W18: =IF(W$7>$N18,0,V18*(1-'Interest Rate'!$B$17)) -> 0 | X18: =IF(X$7>$N18,0,W18*(1-'Interest Rate'!$B$17)) -> 0 | Y18: =IF(Y$7>$N18,0,X18*(1-'Interest Rate'!$B$17)) -> 0 | Z18: =IF(Z$7>$N18,0,Y18*(1-'Interest Rate'!$B$17)) -> 0 | ... DM18: =IF(DM$7>$N18,0,DL18*(1-'Interest Rate'!$B$17)) -> 0
A19: ='EEM Data Entry'!A96 | B19: ='EEM Data Entry'!B96 | C19: ='EEM Data Entry'!F96 | D19: 0 | E19: =C19-D19 -> #VALUE! | F19: =('Savings Summary'!D18*'Savings Summary'!D$5)+('Savings Summary'!F18*'Savings Summary'!F$5)+('Savings Summary'!H18*'Savings Summary'!H$5)+('Savings Summary'!J18*'Savings Summary'!J$5)+('Savings Summary'!L18*'Savings Summary'!L$5)+('Savings Summary'!N18*'Savings Summary'!N$5)+('Savings Summary'!P18*'Savings Summary'!P$5)+('Savings Summary'!R18*'Savings Summary'!R$5) -> 0 | G19: ='Savings Summary'!T18 -> 0 | H19: =IF(C19=0,"n/a",E19/F19) -> #VALUE! | I19: =IF(H19=0, "n/a", IF(H19>100, "no",IF(H19<0, "no", "yes"))) -> #VALUE! | J19: =IRR(Q19:DM19,0.1) -> #NUM! | K19: =PV('Interest Rate'!$B$17,Table6[[#This Row],[LIFETIME]],-Table6[[#This Row],[ANNUAL ENERGY COST SAVINGS]],Table6[[#This Row],[END-OF-LIFE]],0)-Table6[[#This Row],[CAPITAL INVESTMENT]] -> #VALUE! | L19: ='EEM Data Entry'!C96 | M19: =Table6[[#This Row],[ANNUAL ENERGY COST SAVINGS]]/Table6[[#This Row],[CAPITAL INVESTMENT]] -> #VALUE! | N19: =Table6[[#This Row],[LIFETIME]] | Q19: =IF(ISNUMBER(E19)=TRUE,-E19,"") | R19: =F19 -> 0 | S19: =IF(S$7>$N19,0,R19*(1-'Interest Rate'!$B$17)) -> 0 | T19: =IF(T$7>$N19,0,S19*(1-'Interest Rate'!$B$17)) -> 0 | U19: =IF(U$7>$N19,0,T19*(1-'Interest Rate'!$B$17)) -> 0 | V19: =IF(V$7>$N19,0,U19*(1-'Interest Rate'!$B$17)) -> 0 | W19: =IF(W$7>$N19,0,V19*(1-'Interest Rate'!$B$17)) -> 0 | X19: =IF(X$7>$N19,0,W19*(1-'Interest Rate'!$B$17)) -> 0 | Y19: =IF(Y$7>$N19,0,X19*(1-'Interest Rate'!$B$17)) -> 0 | Z19: =IF(Z$7>$N19,0,Y19*(1-'Interest Rate'!$B$17)) -> 0 | ... DM19: =IF(DM$7>$N19,0,DL19*(1-'Interest Rate'!$B$17)) -> 0
A20: ='EEM Data Entry'!A97 | B20: ='EEM Data Entry'!B97 | C20: ='EEM Data Entry'!F97 | D20: 0 | E20: =C20-D20 -> #VALUE! | F20: =('Savings Summary'!D19*'Savings Summary'!D$5)+('Savings Summary'!F19*'Savings Summary'!F$5)+('Savings Summary'!H19*'Savings Summary'!H$5)+('Savings Summary'!J19*'Savings Summary'!J$5)+('Savings Summary'!L19*'Savings Summary'!L$5)+('Savings Summary'!N19*'Savings Summary'!N$5)+('Savings Summary'!P19*'Savings Summary'!P$5)+('Savings Summary'!R19*'Savings Summary'!R$5) -> 0 | G20: ='Savings Summary'!T19 -> 0 | H20: =IF(C20=0,"n/a",E20/F20) -> #VALUE! | I20: =IF(H20=0, "n/a", IF(H20>100, "no",IF(H20<0, "no", "yes"))) -> #VALUE! | J20: =IRR(Q20:DM20,0.1) -> #NUM! | K20: =PV('Interest Rate'!$B$17,Table6[[#This Row],[LIFETIME]],-Table6[[#This Row],[ANNUAL ENERGY COST SAVINGS]],Table6[[#This Row],[END-OF-LIFE]],0)-Table6[[#This Row],[CAPITAL INVESTMENT]] -> #VALUE! | L20: ='EEM Data Entry'!C97 | M20: =Table6[[#This Row],[ANNUAL ENERGY COST SAVINGS]]/Table6[[#This Row],[CAPITAL INVESTMENT]] -> #VALUE! | N20: =Table6[[#This Row],[LIFETIME]] | Q20: =IF(ISNUMBER(E20)=TRUE,-E20,"") | R20: =F20 -> 0 | S20: =IF(S$7>$N20,0,R20*(1-'Interest Rate'!$B$17)) -> 0 | T20: =IF(T$7>$N20,0,S20*(1-'Interest Rate'!$B$17)) -> 0 | U20: =IF(U$7>$N20,0,T20*(1-'Interest Rate'!$B$17)) -> 0 | V20: =IF(V$7>$N20,0,U20*(1-'Interest Rate'!$B$17)) -> 0 | W20: =IF(W$7>$N20,0,V20*(1-'Interest Rate'!$B$17)) -> 0 | X20: =IF(X$7>$N20,0,W20*(1-'Interest Rate'!$B$17)) -> 0 | Y20: =IF(Y$7>$N20,0,X20*(1-'Interest Rate'!$B$17)) -> 0 | Z20: =IF(Z$7>$N20,0,Y20*(1-'Interest Rate'!$B$17)) -> 0 | ... DM20: =IF(DM$7>$N20,0,DL20*(1-'Interest Rate'!$B$17)) -> 0
A21: ='EEM Data Entry'!A98 | B21: ='EEM Data Entry'!B98 | C21: ='EEM Data Entry'!F98 | D21: 0 | E21: =C21-D21 -> #VALUE! | F21: =('Savings Summary'!D20*'Savings Summary'!D$5)+('Savings Summary'!F20*'Savings Summary'!F$5)+('Savings Summary'!H20*'Savings Summary'!H$5)+('Savings Summary'!J20*'Savings Summary'!J$5)+('Savings Summary'!L20*'Savings Summary'!L$5)+('Savings Summary'!N20*'Savings Summary'!N$5)+('Savings Summary'!P20*'Savings Summary'!P$5)+('Savings Summary'!R20*'Savings Summary'!R$5) -> 0 | G21: ='Savings Summary'!T20 -> 0 | H21: =IF(C21=0,"n/a",E21/F21) -> #VALUE! | I21: =IF(H21=0, "n/a", IF(H21>100, "no",IF(H21<0, "no", "yes"))) -> #VALUE! | J21: =IRR(Q21:DM21,0.1) -> #NUM! | K21: =PV('Interest Rate'!$B$17,Table6[[#This Row],[LIFETIME]],-Table6[[#This Row],[ANNUAL ENERGY COST SAVINGS]],Table6[[#This Row],[END-OF-LIFE]],0)-Table6[[#This Row],[CAPITAL INVESTMENT]] -> #VALUE! | L21: ='EEM Data Entry'!C97 | M21: =Table6[[#This Row],[ANNUAL ENERGY COST SAVINGS]]/Table6[[#This Row],[CAPITAL INVESTMENT]] -> #VALUE! | N21: =Table6[[#This Row],[LIFETIME]] | Q21: =IF(ISNUMBER(E21)=TRUE,-E21,"") | R21: =F21 -> 0 | S21: =IF(S$7>$N21,0,R21*(1-'Interest Rate'!$B$17)) -> 0 | T21: =IF(T$7>$N21,0,S21*(1-'Interest Rate'!$B$17)) -> 0 | U21: =IF(U$7>$N21,0,T21*(1-'Interest Rate'!$B$17)) -> 0 | V21: =IF(V$7>$N21,0,U21*(1-'Interest Rate'!$B$17)) -> 0 | W21: =IF(W$7>$N21,0,V21*(1-'Interest Rate'!$B$17)) -> 0 | X21: =IF(X$7>$N21,0,W21*(1-'Interest Rate'!$B$17)) -> 0 | Y21: =IF(Y$7>$N21,0,X21*(1-'Interest Rate'!$B$17)) -> 0 | Z21: =IF(Z$7>$N21,0,Y21*(1-'Interest Rate'!$B$17)) -> 0 | ... DM21: =IF(DM$7>$N21,0,DL21*(1-'Interest Rate'!$B$17)) -> 0
A22: ='EEM Data Entry'!A99 | B22: ='EEM Data Entry'!B99 | C22: ='EEM Data Entry'!F99 | D22: 0 | E22: =C22-D22 -> #VALUE! | F22: =('Savings Summary'!D21*'Savings Summary'!D$5)+('Savings Summary'!F21*'Savings Summary'!F$5)+('Savings Summary'!H21*'Savings Summary'!H$5)+('Savings Summary'!J21*'Savings Summary'!J$5)+('Savings Summary'!L21*'Savings Summary'!L$5)+('Savings Summary'!N21*'Savings Summary'!N$5)+('Savings Summary'!P21*'Savings Summary'!P$5)+('Savings Summary'!R21*'Savings Summary'!R$5) -> 0 | G22: ='Savings Summary'!T21 -> 0 | H22: =IF(C22=0,"n/a",E22/F22) -> #VALUE! | I22: =IF(H22=0, "n/a", IF(H22>100, "no",IF(H22<0, "no", "yes"))) -> #VALUE! | J22: =IRR(Q22:DM22,0.1) -> #NUM! | K22: =PV('Interest Rate'!$B$17,Table6[[#This Row],[LIFETIME]],-Table6[[#This Row],[ANNUAL ENERGY COST SAVINGS]],Table6[[#This Row],[END-OF-LIFE]],0)-Table6[[#This Row],[CAPITAL INVESTMENT]] -> #VALUE! | L22: ='EEM Data Entry'!C97 | M22: =Table6[[#This Row],[ANNUAL ENERGY COST SAVINGS]]/Table6[[#This Row],[CAPITAL INVESTMENT]] -> #VALUE! | N22: =Table6[[#This Row],[LIFETIME]] | Q22: =IF(ISNUMBER(E22)=TRUE,-E22,"") | R22: =F22 -> 0 | S22: =IF(S$7>$N22,0,R22*(1-'Interest Rate'!$B$17)) -> 0 | T22: =IF(T$7>$N22,0,S22*(1-'Interest Rate'!$B$17)) -> 0 | U22: =IF(U$7>$N22,0,T22*(1-'Interest Rate'!$B$17)) -> 0 | V22: =IF(V$7>$N22,0,U22*(1-'Interest Rate'!$B$17)) -> 0 | W22: =IF(W$7>$N22,0,V22*(1-'Interest Rate'!$B$17)) -> 0 | X22: =IF(X$7>$N22,0,W22*(1-'Interest Rate'!$B$17)) -> 0 | Y22: =IF(Y$7>$N22,0,X22*(1-'Interest Rate'!$B$17)) -> 0 | Z22: =IF(Z$7>$N22,0,Y22*(1-'Interest Rate'!$B$17)) -> 0 | ... DM22: =IF(DM$7>$N22,0,DL22*(1-'Interest Rate'!$B$17)) -> 0
A23: ='EEM Data Entry'!A100 | B23: ='EEM Data Entry'!B100 | C23: ='EEM Data Entry'!F100 | D23: 0 | E23: =C23-D23 -> #VALUE! | F23: =('Savings Summary'!D22*'Savings Summary'!D$5)+('Savings Summary'!F22*'Savings Summary'!F$5)+('Savings Summary'!H22*'Savings Summary'!H$5)+('Savings Summary'!J22*'Savings Summary'!J$5)+('Savings Summary'!L22*'Savings Summary'!L$5)+('Savings Summary'!N22*'Savings Summary'!N$5)+('Savings Summary'!P22*'Savings Summary'!P$5)+('Savings Summary'!R22*'Savings Summary'!R$5) -> 0 | G23: ='Savings Summary'!T22 -> 0 | H23: =IF(C23=0,"n/a",E23/F23) -> #VALUE! | I23: =IF(H23=0, "n/a", IF(H23>100, "no",IF(H23<0, "no", "yes"))) -> #VALUE! | J23: =IRR(Q23:DM23,0.1) -> #NUM! | K23: =PV('Interest Rate'!$B$17,Table6[[#This Row],[LIFETIME]],-Table6[[#This Row],[ANNUAL ENERGY COST SAVINGS]],Table6[[#This Row],[END-OF-LIFE]],0)-Table6[[#This Row],[CAPITAL INVESTMENT]] -> #VALUE! | L23: ='EEM Data Entry'!C97 | M23: =Table6[[#This Row],[ANNUAL ENERGY COST SAVINGS]]/Table6[[#This Row],[CAPITAL INVESTMENT]] -> #VALUE! | N23: =Table6[[#This Row],[LIFETIME]] | Q23: =IF(ISNUMBER(E23)=TRUE,-E23,"") | R23: =F23 -> 0 | S23: =IF(S$7>$N23,0,R23*(1-'Interest Rate'!$B$17)) -> 0 | T23: =IF(T$7>$N23,0,S23*(1-'Interest Rate'!$B$17)) -> 0 | U23: =IF(U$7>$N23,0,T23*(1-'Interest Rate'!$B$17)) -> 0 | V23: =IF(V$7>$N23,0,U23*(1-'Interest Rate'!$B$17)) -> 0 | W23: =IF(W$7>$N23,0,V23*(1-'Interest Rate'!$B$17)) -> 0 | X23: =IF(X$7>$N23,0,W23*(1-'Interest Rate'!$B$17)) -> 0 | Y23: =IF(Y$7>$N23,0,X23*(1-'Interest Rate'!$B$17)) -> 0 | Z23: =IF(Z$7>$N23,0,Y23*(1-'Interest Rate'!$B$17)) -> 0 | ... DM23: =IF(DM$7>$N23,0,DL23*(1-'Interest Rate'!$B$17)) -> 0
A24: ='EEM Data Entry'!A101 | B24: ='EEM Data Entry'!B101 | C24: ='EEM Data Entry'!F101 | D24: 0 | E24: =C24-D24 -> #VALUE! | F24: =('Savings Summary'!D23*'Savings Summary'!D$5)+('Savings Summary'!F23*'Savings Summary'!F$5)+('Savings Summary'!H23*'Savings Summary'!H$5)+('Savings Summary'!J23*'Savings Summary'!J$5)+('Savings Summary'!L23*'Savings Summary'!L$5)+('Savings Summary'!N23*'Savings Summary'!N$5)+('Savings Summary'!P23*'Savings Summary'!P$5)+('Savings Summary'!R23*'Savings Summary'!R$5) -> 0 | G24: ='Savings Summary'!T23 -> 0 | H24: =IF(C24=0,"n/a",E24/F24) -> #VALUE! | I24: =IF(H24=0, "n/a", IF(H24>100, "no",IF(H24<0, "no", "yes"))) -> #VALUE! | J24: =IRR(Q24:DM24,0.1) -> #NUM! | K24: =PV('Interest Rate'!$B$17,Table6[[#This Row],[LIFETIME]],-Table6[[#This Row],[ANNUAL ENERGY COST SAVINGS]],Table6[[#This Row],[END-OF-LIFE]],0)-Table6[[#This Row],[CAPITAL INVESTMENT]] -> #VALUE! | L24: ='EEM Data Entry'!C101 | M24: =Table6[[#This Row],[ANNUAL ENERGY COST SAVINGS]]/Table6[[#This Row],[CAPITAL INVESTMENT]] -> #VALUE! | N24: =Table6[[#This Row],[LIFETIME]] | Q24: =IF(ISNUMBER(E24)=TRUE,-E24,"") | R24: =F24 -> 0 | S24: =IF(S$7>$N24,0,R24*(1-'Interest Rate'!$B$17)) -> 0 | T24: =IF(T$7>$N24,0,S24*(1-'Interest Rate'!$B$17)) -> 0 | U24: =IF(U$7>$N24,0,T24*(1-'Interest Rate'!$B$17)) -> 0 | V24: =IF(V$7>$N24,0,U24*(1-'Interest Rate'!$B$17)) -> 0 | W24: =IF(W$7>$N24,0,V24*(1-'Interest Rate'!$B$17)) -> 0 | X24: =IF(X$7>$N24,0,W24*(1-'Interest Rate'!$B$17)) -> 0 | Y24: =IF(Y$7>$N24,0,X24*(1-'Interest Rate'!$B$17)) -> 0 | Z24: =IF(Z$7>$N24,0,Y24*(1-'Interest Rate'!$B$17)) -> 0 | ... DM24: =IF(DM$7>$N24,0,DL24*(1-'Interest Rate'!$B$17)) -> 0
