Workbook

Sheet ALL
A1: CSV PARAMETER | B1: DESCRIPTION | C1: SAMPLE (taken from different sites)
A2: BUILDING_REFERENCE_NUMBER | B2: Unique 10-digit identifier for the property, generated by the SEPCR to enable the EPC lodgement process even where there is no current matching UPRN for the assessed property extents (building or building unit). Not the same as the Unique Property Reference Number available from the One Scotland Gazetteer. | C2: 1001829059
A3: OSG_REFERENCE_NUMBER | B3: Unique 9-12-digit property reference number assigned to a building by local authority data custodians and recorded centrally on the One Scotland Gazetteer: Energy Performance of Buildings Data England and Wales (opendatacommunities.org). | C3: 122009928
A4: ADDRESS1 | B4: First line of the building address | C4: 11 CULCREUCH AVENUE
A5: ADDRESS2 | B5: Second line of the building address | C5: FINTRY
A6: ADDRESS3 | B6: Third line of the building address. Note that ADDRESS3 is assigned as POST_TOWN | C6: GLASGOW
A7: POSTCODE | B7: The postcode of the property | C7: G63 0YB
A8: LATITUDE | B8: Latitude of site (aquired with Google Maps API) | C8: 56.05605329999999
A9: LONGITUDE | B9: Longitude of site (aquired with Google Maps API) | C9: -4.2246704
A10: INSPECTION_DATE | B10: Date on which assessment of the energy performance of the building was undertaken | C10: 45798
A11: TYPE_OF_ASSESSMENT | B11: Tool used (SAP, RdSAP) and whether assessment is for new or existing dwelling. | C11: RdSAP, existing dwelling
A12: LODGEMENT_DATE | B12: Date on which the data from the energy performance assessment was lodged to the Scottish EPC Register | C12: 45800
A13: ENERGY_CONSUMPTION_CURRENT | B13: Reports Primary Energy - the amount of energy required at source, before conversion and transmission, to meet the calculated energy demand of the dwelling (Units: kWh/m²/year). | C13: 271
A14: TOTAL_FLOOR_AREA | B14: The total floor area of the dwelling. This excludes any unheated ancillary buildings. (Units: m²) | C14: 93
A15: 3_YR_ENERGY_COST_CURRENT | B15: Calculation illustrating the total energy cost for heating, cooling, lighting, and ventilating the building. Based on standardised occupancy patterns and fuel costs. (Units: £) | C15: 6237
A16: 3_YR_ENERGY_SAVINGS_POTENTIAL | B16: Calculation illustrating the energy cost saving that may be achieved if the listed improvement measures are carried out. Based on standardised occupancy patterns and fuel costs. (Units: £) | C16: 1311
A17: CURRENT_ENERGY_EFFICIENCY | B17: Current energy cost rating (EER or ‘SAP rating’) for the building which is calculated using both the energy efficiency of the building and the cost of fuels used. | C17: 63
A18: CURRENT_ENERGY_RATING | B18: Current Energy Efficiency Rating expressed on a Scale of G to A, with A being the highest (best) rating band. | C18: D
A19: POTENTIAL_ENERGY_EFFICIENCY | B19: Potential energy cost rating for the building, after application of the listed improvement measures, which is again calculated using both the energy efficiency of the improved building and the cost of fuels used. | C19: 81
A20: POTENTIAL_ENERGY_RATING | B20: Potential Energy Efficiency Rating expressed on a Scale of G to A, with A being the highest (best) rating band. | C20: B
A21: ENVIRONMENT_IMPACT_CURRENT | B21: Current environmental impact for the building which is calculated using the emissions associated with the energy use of the building. | C21: 53
A22: CURRENT_ENVIRONMENTAL_RATING | B22: Current Environmental Impact Rating expressed on a Scale of G to A, with A being the highest (best) rating band. | C22: E
A23: ENVIRONMENT_IMPACT_POTENTIAL | B23: Potential environmental impact for the building, after application of the listed improvement measures, which is again calculated using the emissions associated with the energy use of the building. | C23: 72
A24: POTENTIAL_ENVIRONMENTAL_RATING | B24: Potential Environmental Impact Rating expressed on a Scale of G to A, with A being the highest (best) rating band. | C24: C
A25: CO2_EMISS_CURR_PER_FLOOR_AREA | B25: Annual CO2 equivalent emissions per square metre of floor area (units: kg.CO2e/m²/yr) | C25: 59
A26: IMPROVEMENTS | B26: A list of the improvement measures identified as relevant to the building at the date of assessment. These measures are drawn from the list of measures published in Appendix T of the current SAP 2012 October 2013 with RdSAP 19 Dec 2014 specification. Improvement measures are listed sequentially under a single data entry in the following format: ‘Description; Typical saving; Energy Rating after improvement; Environmental Rating after improvement; Green Deal eligible.’ Each measure reported is separated by a vertical line [ “|” - ASCII (decimal) 124] | C26: ; Indicative Cost: ¬£300 - ¬£600; Typical Saving: 77; Energy Rating after improvement: D 64; Environmental Rating after improvement: D 55; Green Deal Eligible: Y | Description: Solar photovoltaic panels, 2.5 kWp; Indicative Cost: ¬£3,500 - ¬£5,500; Typical Saving: 389; Energy Rating after improvement: B 81; Environmental Rating after improvement: C 72; Green Deal Eligible: Y | Description: Floor insulation (solid floor); Indicative Cost: ¬£4,000 - ¬£6,000; Typical Saving: 186; Energy Rating after improvement: D 67; Environmental Rating after improvement: D 59; Green Deal Eligible: Y | Description: Solar water heating; Indicative Cost: ¬£4,000 - ¬£6,000; Typical Saving: 173; Energy Rating after improvement: C 71; Environmental Rating after improvement: D 64; Green Deal Eligible: Y |
A27: WALL_DESCRIPTION | B27: Summary of the performance of this building element, reported in the following format: ‘Description; Energy Efficiency Rating; Environmental Efficiency Rating.’ Both ratings elements are reported on a scale of 1 to 5 (very poor, poor, average, good, very good). Note: where a dwelling has more than one type of this element, multiple elements can be reported. Each element reported is separated by “|” [ASCII (decimal) 124] | C27: System built, with external insulation
A28: WALL_ENERGY_EFF | B28: Summary of the performance of this building element, reported in the following format: ‘Description; Energy Efficiency Rating; Environmental Efficiency Rating.’ Both ratings elements are reported on a scale of 1 to 5 (very poor, poor, average, good, very good). Note: where a dwelling has more than one type of this element, multiple elements can be reported. Each element reported is separated by “|” [ASCII (decimal) 124] | C28: Good
A29: WALL_ENV_EFF | B29: Summary of the performance of this building element, reported in the following format: ‘Description; Energy Efficiency Rating; Environmental Efficiency Rating.’ Both ratings elements are reported on a scale of 1 to 5 (very poor, poor, average, good, very good). Note: where a dwelling has more than one type of this element, multiple elements can be reported. Each element reported is separated by “|” [ASCII (decimal) 124] | C29: Good
A30: ROOF_DESCRIPTION | B30: Summary of the performance of this building element, reported in the following format: ‘Description; Energy Efficiency Rating; Environmental Efficiency Rating.’ Both ratings elements are reported on a scale of 1 to 5 (very poor, poor, average, good, very good). Note: where a dwelling has more than one type of this element, multiple elements can be reported. Each element reported is separated by “|” [ASCII (decimal) 124] | C30: Pitched, 250 mm loft insulation
A31: ROOF_ENERGY_EFF | B31: Summary of the performance of this building element, reported in the following format: ‘Description; Energy Efficiency Rating; Environmental Efficiency Rating.’ Both ratings elements are reported on a scale of 1 to 5 (very poor, poor, average, good, very good). Note: where a dwelling has more than one type of this element, multiple elements can be reported. Each element reported is separated by “|” [ASCII (decimal) 124] | C31: Good
A32: ROOF_ENV_EFF | B32: Summary of the performance of this building element, reported in the following format: ‘Description; Energy Efficiency Rating; Environmental Efficiency Rating.’ Both ratings elements are reported on a scale of 1 to 5 (very poor, poor, average, good, very good). Note: where a dwelling has more than one type of this element, multiple elements can be reported. Each element reported is separated by “|” [ASCII (decimal) 124] | C32: Good
A33: FLOOR_DESCRIPTION | B33: Summary of the performance of this building element, reported in the following format: ‘Description; Energy Efficiency Rating; Environmental Efficiency Rating.’ Both ratings elements are reported on a scale of 1 to 5 (very poor, poor, average, good, very good). Note: where a dwelling has more than one type of this element, multiple elements can be reported. Each element reported is separated by “|” [ASCII (decimal) 124] | C33: Solid, no insulation (assumed)
A34: FLOOR_ENERGY_EFF | B34: Summary of the performance of this building element, reported in the following format: ‘Description; Energy Efficiency Rating; Environmental Efficiency Rating.’ Both ratings elements are reported on a scale of 1 to 5 (very poor, poor, average, good, very good). Note: where a dwelling has more than one type of this element, multiple elements can be reported. Each element reported is separated by “|” [ASCII (decimal) 124] | C34: N/A
A35: FLOOR_ENV_EFF | B35: Summary of the performance of this building element, reported in the following format: ‘Description; Energy Efficiency Rating; Environmental Efficiency Rating.’ Both ratings elements are reported on a scale of 1 to 5 (very poor, poor, average, good, very good). Note: where a dwelling has more than one type of this element, multiple elements can be reported. Each element reported is separated by “|” [ASCII (decimal) 124] | C35: N/A
A36: WINDOWS_DESCRIPTION | B36: Summary of the performance of this building element, reported in the following format: ‘Description; Energy Efficiency Rating; Environmental Efficiency Rating.’ Both ratings elements are reported on a scale of 1 to 5 (very poor, poor, average, good, very good). Note: where a dwelling has more than one type of this element, multiple elements can be reported. Each element reported is separated by “|” [ASCII (decimal) 124] | C36: Description: Fully double glazed
A37: WINDOWS_ENERGY_EFF | B37: Summary of the performance of this building element, reported in the following format: ‘Description; Energy Efficiency Rating; Environmental Efficiency Rating.’ Both ratings elements are reported on a scale of 1 to 5 (very poor, poor, average, good, very good). Note: where a dwelling has more than one type of this element, multiple elements can be reported. Each element reported is separated by “|” [ASCII (decimal) 124] | C37: Average
... A56: AIR_TIGHTNESS_ENV_EFF | B56: Summary of the performance of this building element, reported in the following format: ‘Description; Energy Efficiency Rating; Environmental Efficiency Rating.’ Both ratings elements are reported on a scale of 1 to 5 (very poor, poor, average, good, very good). Note: where a dwelling has more than one type of this element, multiple elements can be reported. Each element reported is separated by “|” [ASCII (decimal) 124] | C56: Good
A57: CO2_EMISSIONS_CURRENT | B57: The total annual emissions reduction for the building based upon the calculated energy demand for heating, cooling, lighting, and ventilating the building. (Units: tonnes per year) | C57: 5.5
A58: CO2_EMISSIONS_POTENTIAL | B58: Calculation illustrating the total annual emissions reduction for the building if the identified improvement measures are carried out. (Units: tonnes per year) | C58: 2
A59: HEATING_COST_CURRENT | B59: Calculation illustrating the total energy cost for heating over the stated period. Based on standardised occupancy patterns and fuel costs. (Units: £) | C59: 4533
A60: HEATING_COST_POTENTIAL | B60: Calculation illustrating the total energy cost for heating over the stated period if recommended improvement measures are carried out. Based on standardised occupancy patterns and fuel costs. (Units: £) | C60: 3921
A61: HOT_WATER_COST_CURRENT | B61: Calculation illustrating the total energy cost for hot water over the stated period. Based on standardised occupancy patterns and fuel costs. (Units: £) | C61: 1419
A62: HOT_WATER_COST_POTENTIAL | B62: Calculation illustrating the total energy cost for hot water over the stated period if recommended improvement measures are carried out. Based on standardised occupancy patterns and fuel costs. (Units: £) | C62: 720
A63: LIGHTING_COST_CURRENT | B63: Calculation illustrating the total energy cost for lighting over the stated period. Based on standardised occupancy patterns and fuel costs. (Units: £) | C63: 285
A64: LIGHTING_COST_POTENTIAL | B64: Calculation illustrating the total energy cost for lighting over the stated period if recommended improvement measures are carried out. Based on standardised occupancy patterns and fuel costs. (Units: £) | C64: 285
A65: ALTERNATIVE_IMPROVEMENTS | B65: List of further improvements to the building that can be considered. Note that these measures are not used in calculation of potential ratings or savings (description only). Note: multiple measures can be reported. Each measure reported is separated by a vertical line [ “|” - ASCII (decimal) 124] | C65: Description: Biomass boiler (Exempted Appliance if in Smoke Control Area) | Description: Air or ground source heat pump |
A66: LZC_ENERGY_SOURCES | B66: Recorded where a low or zero carbon technology (equipment that either generates or otherwise provides energy with no or little resulting emissions) is present in the dwelling. Examples include photovoltaic panels, solar thermal panels, and wind turbines. | C66: Description: Biomass secondary heating |
A67: SPACE_HEATING_DEMAND | B67: Reports the calculated heat demand for space heating in the current dwelling. Based upon the levels of insulation present and how this limits heat loss. (Units: kWh per year) | C67: 10523
A68: WATER_HEATING_DEMAND | B68: Reports the calculated heat demand for provision of hot water in the current dwelling. Based upon the efficiency of the water heating system. (Units: kWh per year) | C68: 3377
A69: IMPACT_LOFT_INSULATION | B69: (if applicable) Reports the potential reduction in calculated heat demand for space heating if the dwelling loft is insulated. (Units: kWh per year) | C69: 8848
A70: IMPACT_CAVITY_WALL_INSULATION | B70: (if applicable) Reports the potential reduction in calculated heat demand for space heating if the dwelling cavity walls are insulated. (Units: kWh per year) | C70: 5875
A71: IMPACT_SOLID_WALL_INSULATION | B71: (if applicable) Reports the potential reduction in calculated heat demand for space heating if external or internal insulation applied to the dwelling walls. (Units: kWh per year) | C71: 10395
A72: ADDENDUM_TEXT | B72: Used to record a range of specific observations about the dwelling construction that are relevant to the assessment. Current valid options are listed in Section S15 in Appendix S of the current SAP 2012 October 2013 with RdSAP 19 Dec 2014 specification.
A73: CONSTRUCTION_AGE_BAND | B73: Age band when building part constructed. For Scotland, one of: before 1919; 1919-1929; 1930-1949; 1950-1964; 1965-1975; 1976-1983; 1984-1991; 1992-1998; 1999-2002; 2003-2007; 2008- 2011; 2012 onwards. | C73: 1950-1964
A74: FLOOR_HEIGHT | B74: Average height of the lowest storey of the dwelling (Units: m) | C74: 2.39
A75: DATA_ZONE | B75: Data Zone code and name - Data zones are the key geography for the dissemination of small area statistics in Scotland. | C75: S01006074 (Strathendrick)
A76: ENERGY_CONSUMPTION_POTENTIAL | B76: Reports Primary Energy - the amount of energy required at source, before conversion and transmission, to meet the calculated energy demand of the dwelling, if recommended improvement measures are carried out (Units: kWh/m²/year). | C76: 161
A77: EXTENSION_COUNT | B77: The number of extensions added to the property. Between 0 and 4 can be reported. | C77: 0
A78: FIXED_LIGHTING_OUTLETS_COUNT | B78: The number of fixed lighting outlets in the dwelling. | C78: 12
A79: LOW_ENERGY_FIXED_LIGHT_COUNT | B79: The number of low-energy fixed lighting outlets. | C79: 12
A80: LOW_ENERGY_LIGHTING | B80: The percentage of low energy lighting present in the property as a percentage of the total fixed lights in the property. 0% indicates that no low-energy lighting is present. | C80: 100
A81: FLOOR_LEVEL | B81: Floor level relative to the lowest level of the building | C81: top floor
A82: FLAT_TOP_STOREY | B82: The number of storeys in the flatted block. | C82: 1
A83: GLAZED_AREA | B83: Ranged estimate of the total glazed area of the Habitable Area: 0 – New dwelling 1 – Typical glazing 2 – More than typical 3 – Less than typical 4 – Much more than typical 5 – Much less than typical | C83: 1
A84: NUMBER_HABITABLE_ROOMS | B84: Habitable rooms include any living room, sitting room, dining room, bedroom, study and similar. Excludes any room used solely as a kitchen, utility room, sanitary accommodation and any hallway, stairs, or landing; and also any conservatory or room without a window. | C84: 4
A85: HEAT_LOSS_CORRIDOOR | B85: Flats and maisonettes only. Indicates that the flat contains a corridor through which heat is lost. Heat loss corridor, one of: no corridor; heated corridor; unheated corridor
A86: NUMBER_HEATED_ROOMS | B86: The number of heated habitable rooms in the property. | C86: 4
A87: LOCAL_AUTHORITY_LABEL | B87: The name of the local authority area in which the building is located. | C87: Stirling
A88: MAINS_GAS_FLAG | B88: Whether mains gas is available. Yes means that there is a gas meter or a gas-burning appliance in the dwelling
A89: MAIN_HEATING_CATEGORY | B89: Reports the type of main heating system present in the dwelling. Lists both heat source and heat emitters (e.g. gas boiler and radiators). | C89: boiler with radiators or underfloor heating
A90: MAIN_FUEL | B90: Reports the fuel type used by the main heating system present in the dwelling. | C90: dual fuel - mineral + wood
A91: MAIN_HEATING_CONTROLS | B91: Type of main heating controls. Includes both main heating systems if there are two. | C91: 2111
A92: MECHANICAL_VENTILATION | B92: Identifies the type of mechanical ventilation the property has. | C92: natural
A93: ENERGY_TARIFF | B93: Type of electricity tariff for the property (by meter type), e.g. single. | C93: Single
A94: MULTI_GLAZE_PROPORTION | B94: The estimated banded range (e.g. 0% - 10%) of the total glazed area of the Property that is multiple glazed. | C94: 100
A95: GLAZED_TYPE | B95: The type of glazing. From British Fenestration Rating Council or manufacturer declaration, one of; single; double; triple. | C95: double glazing installed before 2002
A96: NUMBER_OPEN_FIREPLACES | B96: The number of Open Fireplaces in the Property. An Open Fireplace is a fireplace that still allows air to pass between the inside of the Property and the outside. | C96: 0
A97: PHOTO_SUPPLY | B97: Photovoltaic area as a percentage of total roof area. 0% indicates that a Photovoltaic Supply is not present in the property. Note: multiple arrays can be reported. Each array reported is separated by a vertical line [ “|” - ASCII (decimal) 124] | C97: Array: Roof Area: 0%; Connection: not applicable (FGHRS or no PV); |
A98: SOLAR_WATER_HEATING_FLAG | B98: Indicates whether the water heating in the property is served by solar thermal panels. | C98: FALSE
A99: TENURE | B99: Describes the tenure type of the property. One of: Owner- occupied; Rented (social); Rented (private); Unknown | C99: owner-occupied
A100: TRANSACTION_TYPE | B100: Type of transaction or purpose that triggered EPC assessment. One of: - new dwelling; marketed sale; non-marketed sale; rental; not sale or rental; assessment for Green Deal; following Green Deal; FIT application; RHI application; ECO assessment; none of the above. Where the reason for the assessment is unknown by the energy assessor the transaction type will be recorded as 'none of the above'. | C100: marketed sale
A101: UNHEATED_CORRIDOR_LENGTH | B101: The total length of unheated corridor in the flat. Only populated if flat or maisonette contains unheated corridor. If unheated corridor, length of sheltered wall (m²). | C101: 8.3
A102: CONSTITUENCY | B102: Code for Parliamentary constituency in which the building is located. Scottish area defined as 'Ward', not 'constituency' | C102: 00RGMB
A103: CONSTITUENCY_LABEL | B103: Name of Parliamentary constituency in which the building is located. Scottish area defined as 'Ward', not 'constituency' | C103: Forth and Endrick
A104: WIND_TURBINE_COUNT | B104: Number of wind turbines; 0 if none. | C104: 0
A105: BUILT_FORM | B105: The building type of the Property e.g. Detached, Semi-Detached, Terrace etc. Together with the Property Type, the Build Form produces a structured description of the property | C105: Semi-Detached
A106: PROPERTY_TYPE | B106: Describes the type of property such as House, Flat, Maisonette etc. This is the type differentiator for dwellings. | C106: House
A107: DATA_ZONE_2011 | C107: S01013015 (Kippen and Fintry - 01)
A108: CREATED_AT | B108: The date and time that the certificate was lodged on the register. | C108: 45800.497
A109: REPORT_REFERENCE_NUMBER | B109: Unique, auto-generated number produced on the lodgement of an EPC to the SEPCR. | C109: 2899-1018-5205-0295-2200
A110: dwelling_id | C110: 11 CULCREUCH AVENUE | G63 0YB
A111: IMPROVEMENTS_PARSED | B111: This variable contains a structured representation of the EPC-recommended energy efficiency improvements for each dwelling. The original semi-structured text field is parsed into individual measures, each including the improvement description, indicative cost range, estimated annual savings, expected post-improvement energy and environmental ratings, and Green Deal eligibility. Multiple recommended measures are stored as a list for each property. | C111: [{'description': None, 'cost_min': 300, 'cost_max': 600, 'typical_saving': 77, 'energy_rating': 'D 64', 'env_rating': 'D 55', 'green_deal': 'Y'}, {'description': 'Solar photovoltaic panels, 2.5 kWp', 'cost_min': 3500, 'cost_max': 5500, 'typical_saving': 389, 'energy_rating': 'B 81', 'env_rating': 'C 72', 'green_deal': 'Y'}, {'description': 'Floor insulation (solid floor)', 'cost_min': 4000, 'cost_max': 6000, 'typical_saving': 186, 'energy_rating': 'D 67', 'env_rating': 'D 59', 'green_deal': 'Y'}, {'description': 'Solar water heating', 'cost_min': 4000, 'cost_max': 6000, 'typical_saving': 173, 'energy_rating': 'C 71', 'env_rating': 'D 64', 'green_deal': 'Y'}, {'description': None, 'cost_min': None, 'cost_max': None, 'typical_saving': None, 'energy_rating': None, 'env_rating': None, 'green_deal': None}]
A112: WALL_DESCRIPTION_PARSED | B112: This variable provides a structured representation of the dwelling’s external wall construction and associated EPC performance ratings. The parsed data captures the wall type (e.g., cavity wall, solid wall, insulated wall) along with the corresponding EPC energy efficiency and environmental impact ratings. | C112: [{'description': 'System built, with external insulation', 'energy_rating': 'Good', 'env_rating': 'Good'}]
A113: ROOF_DESCRIPTION_PARSED | B113: This variable contains a structured representation of the roof construction and insulation characteristics reported in the EPC. Each entry includes the roof description and the associated EPC energy and environmental performance ratings. | C113: [{'description': 'Pitched, 250 mm loft insulation', 'energy_rating': 'Good', 'env_rating': 'Good'}]
A114: FLOOR_DESCRIPTION_PARSED | B114: This variable represents the dwelling’s floor construction and insulation properties as described in the EPC. The parsed data includes the floor description (e.g., solid floor, suspended timber floor) along with its EPC energy and environmental ratings. | C114: [{'description': 'Solid, no insulation (assumed)', 'energy_rating': 'N/A', 'env_rating': 'N/A'}]
A115: WINDOWS_DESCRIPTION_PARSED | B115: This variable captures the glazing type and window performance characteristics of the dwelling. The parsed structure includes the EPC description of the windows (e.g., single glazing, double glazing, secondary glazing) and the corresponding energy and environmental ratings. | C115: [{'description': 'Description: Fully double glazed', 'energy_rating': 'Average', 'env_rating': 'Average'}]
A116: MAINHEAT_DESCRIPTION_PARSED | B116: This variable contains a structured representation of the dwelling’s primary space heating system as described in the EPC. The parsed entries include the heating system type (e.g., boiler, electric storage heaters, heat pump) and the associated energy and environmental efficiency ratings. | C116: [{'description': 'Boiler and radiators, dual fuel (mineral and wood)', 'energy_rating': 'Average', 'env_rating': 'Average'}]
A117: MAINHEATCONT_DESCRIPTION_PARSED | B117: This variable represents the heating control systems associated with the primary heating system. The parsed data includes descriptions of controls such as thermostats, programmers, or zone controls along with the EPC energy and environmental ratings. | C117: [{'description': 'TRVs and bypass', 'energy_rating': 'Average', 'env_rating': 'Average'}]
A118: SECONDHEAT_DESCRIPTION_PARSED | B118: This variable describes any secondary heating systems present in the dwelling, such as open fireplaces or room heaters. The parsed structure includes the system description and the corresponding EPC energy and environmental ratings. | C118: [{'description': 'Room heaters, dual fuel (mineral and wood)', 'energy_rating': 'N/A', 'env_rating': 'N/A'}]
...

Sheet Categorical For Modeling
A1: CSV PARAMETER | B1: DESCRIPTION | C1: SAMPLE (taken from different sites) | D1: Categorical Values (complete list)
A2: BUILDING_REFERENCE_NUMBER | B2: Unique 10-digit identifier for the property, generated by the SEPCR to enable the EPC lodgement process even where there is no current matching UPRN for the assessed property extents (building or building unit). Not the same as the Unique Property Reference Number available from the One Scotland Gazetteer. | C2: 1001829059 | D2: =IFERROR(VLOOKUP(A2,'Unique Values'!$A$2:$B$57,2,FALSE),"")
A3: OSG_REFERENCE_NUMBER | B3: Unique 9-12-digit property reference number assigned to a building by local authority data custodians and recorded centrally on the One Scotland Gazetteer: Energy Performance of Buildings Data England and Wales (opendatacommunities.org). | C3: 122009928 | D3: =IFERROR(VLOOKUP(A3,'Unique Values'!$A$2:$B$57,2,FALSE),"")
A4: ADDRESS1 | B4: First line of the building address | C4: 11 CULCREUCH AVENUE | D4: =IFERROR(VLOOKUP(A4,'Unique Values'!$A$2:$B$57,2,FALSE),"")
A5: ADDRESS2 | B5: Second line of the building address | C5: FINTRY | D5: =IFERROR(VLOOKUP(A5,'Unique Values'!$A$2:$B$57,2,FALSE),"")
A6: ADDRESS3 | B6: Third line of the building address. Note that ADDRESS3 is assigned as POST_TOWN | C6: GLASGOW | D6: =IFERROR(VLOOKUP(A6,'Unique Values'!$A$2:$B$57,2,FALSE),"")
A7: POSTCODE | B7: The postcode of the property | C7: G63 0YB | D7: =IFERROR(VLOOKUP(A7,'Unique Values'!$A$2:$B$57,2,FALSE),"")
A8: LATITUDE | B8: Latitude of site (aquired with Google Maps API) | C8: 56.05605329999999 | D8: =IFERROR(VLOOKUP(A8,'Unique Values'!$A$2:$B$57,2,FALSE),"")
A9: LONGITUDE | B9: Longitude of site (aquired with Google Maps API) | C9: -4.2246704 | D9: =IFERROR(VLOOKUP(A9,'Unique Values'!$A$2:$B$57,2,FALSE),"")
A10: INSPECTION_DATE | B10: Date on which assessment of the energy performance of the building was undertaken | C10: 45798 | D10: =IFERROR(VLOOKUP(A10,'Unique Values'!$A$2:$B$57,2,FALSE),"")
A11: TYPE_OF_ASSESSMENT | B11: Tool used (SAP, RdSAP) and whether assessment is for new or existing dwelling. | C11: RdSAP, existing dwelling | D11: =IFERROR(VLOOKUP(A11,'Unique Values'!$A$2:$B$57,2,FALSE),"")
A12: LODGEMENT_DATE | B12: Date on which the data from the energy performance assessment was lodged to the Scottish EPC Register | C12: 45800 | D12: =IFERROR(VLOOKUP(A12,'Unique Values'!$A$2:$B$57,2,FALSE),"")
A13: ENERGY_CONSUMPTION_CURRENT | B13: Reports Primary Energy - the amount of energy required at source, before conversion and transmission, to meet the calculated energy demand of the dwelling (Units: kWh/m²/year). | C13: 271 | D13: =IFERROR(VLOOKUP(A13,'Unique Values'!$A$2:$B$57,2,FALSE),"")
A14: TOTAL_FLOOR_AREA | B14: The total floor area of the dwelling. This excludes any unheated ancillary buildings. (Units: m²) | C14: 93 | D14: =IFERROR(VLOOKUP(A14,'Unique Values'!$A$2:$B$57,2,FALSE),"")
A15: 3_YR_ENERGY_COST_CURRENT | B15: Calculation illustrating the total energy cost for heating, cooling, lighting, and ventilating the building. Based on standardised occupancy patterns and fuel costs. (Units: £) | C15: 6237 | D15: =IFERROR(VLOOKUP(A15,'Unique Values'!$A$2:$B$57,2,FALSE),"")
A16: 3_YR_ENERGY_SAVINGS_POTENTIAL | B16: Calculation illustrating the energy cost saving that may be achieved if the listed improvement measures are carried out. Based on standardised occupancy patterns and fuel costs. (Units: £) | C16: 1311 | D16: =IFERROR(VLOOKUP(A16,'Unique Values'!$A$2:$B$57,2,FALSE),"")
A17: CURRENT_ENERGY_EFFICIENCY | B17: Current energy cost rating (EER or ‘SAP rating’) for the building which is calculated using both the energy efficiency of the building and the cost of fuels used. | C17: 63 | D17: =IFERROR(VLOOKUP(A17,'Unique Values'!$A$2:$B$57,2,FALSE),"")
A18: CURRENT_ENERGY_RATING | B18: Current Energy Efficiency Rating expressed on a Scale of G to A, with A being the highest (best) rating band. | C18: D | D18: =IFERROR(VLOOKUP(A18,'Unique Values'!$A$2:$B$57,2,FALSE),"") -> A; B; C; D; E; F; G
A19: POTENTIAL_ENERGY_EFFICIENCY | B19: Potential energy cost rating for the building, after application of the listed improvement measures, which is again calculated using both the energy efficiency of the improved building and the cost of fuels used. | C19: 81 | D19: =IFERROR(VLOOKUP(A19,'Unique Values'!$A$2:$B$57,2,FALSE),"")
A20: POTENTIAL_ENERGY_RATING | B20: Potential Energy Efficiency Rating expressed on a Scale of G to A, with A being the highest (best) rating band. | C20: B | D20: =IFERROR(VLOOKUP(A20,'Unique Values'!$A$2:$B$57,2,FALSE),"") -> A; B; C; D; E
A21: ENVIRONMENT_IMPACT_CURRENT | B21: Current environmental impact for the building which is calculated using the emissions associated with the energy use of the building. | C21: 53 | D21: =IFERROR(VLOOKUP(A21,'Unique Values'!$A$2:$B$57,2,FALSE),"")
A22: CURRENT_ENVIRONMENTAL_RATING | B22: Current Environmental Impact Rating expressed on a Scale of G to A, with A being the highest (best) rating band. | C22: E | D22: =IFERROR(VLOOKUP(A22,'Unique Values'!$A$2:$B$57,2,FALSE),"") -> A; B; C; D; E; F; G
A23: ENVIRONMENT_IMPACT_POTENTIAL | B23: Potential environmental impact for the building, after application of the listed improvement measures, which is again calculated using the emissions associated with the energy use of the building. | C23: 72 | D23: =IFERROR(VLOOKUP(A23,'Unique Values'!$A$2:$B$57,2,FALSE),"")
A24: POTENTIAL_ENVIRONMENTAL_RATING | B24: Potential Environmental Impact Rating expressed on a Scale of G to A, with A being the highest (best) rating band. | C24: C | D24: =IFERROR(VLOOKUP(A24,'Unique Values'!$A$2:$B$57,2,FALSE),"") -> A; B; C; D; E
A25: CO2_EMISS_CURR_PER_FLOOR_AREA | B25: Annual CO2 equivalent emissions per square metre of floor area (units: kg.CO2e/m²/yr) | C25: 59 | D25: =IFERROR(VLOOKUP(A25,'Unique Values'!$A$2:$B$57,2,FALSE),"")
A26: IMPROVEMENTS | B26: A list of the improvement measures identified as relevant to the building at the date of assessment. These measures are drawn from the list of measures published in Appendix T of the current SAP 2012 October 2013 with RdSAP 19 Dec 2014 specification. Improvement measures are listed sequentially under a single data entry in the following format: ‘Description; Typical saving; Energy Rating after improvement; Environmental Rating after improvement; Green Deal eligible.’ Each measure reported is separated by a vertical line [ “|” - ASCII (decimal) 124] | C26: ; Indicative Cost: ¬£300 - ¬£600; Typical Saving: 77; Energy Rating after improvement: D 64; Environmental Rating after improvement: D 55; Green Deal Eligible: Y | Description: Solar photovoltaic panels, 2.5 kWp; Indicative Cost: ¬£3,500 - ¬£5,500; Typical Saving: 389; Energy Rating after improvement: B 81; Environmental Rating after improvement: C 72; Green Deal Eligible: Y | Description: Floor insulation (solid floor); Indicative Cost: ¬£4,000 - ¬£6,000; Typical Saving: 186; Energy Rating after improvement: D 67; Environmental Rating after improvement: D 59; Green Deal Eligible: Y | Description: Solar water heating; Indicative Cost: ¬£4,000 - ¬£6,000; Typical Saving: 173; Energy Rating after improvement: C 71; Environmental Rating after improvement: D 64; Green Deal Eligible: Y | | D26: =IFERROR(VLOOKUP(A26,'Unique Values'!$A$2:$B$57,2,FALSE),"")
A27: WALL_DESCRIPTION | B27: Summary of the performance of this building element, reported in the following format: ‘Description; Energy Efficiency Rating; Environmental Efficiency Rating.’ Both ratings elements are reported on a scale of 1 to 5 (very poor, poor, average, good, very good). Note: where a dwelling has more than one type of this element, multiple elements can be reported. Each element reported is separated by “|” [ASCII (decimal) 124] | C27: System built, with external insulation | D27: =IFERROR(VLOOKUP(A27,'Unique Values'!$A$2:$B$57,2,FALSE),"") -> Average thermal transmittance 0.12 W/m¬≤K; Average thermal transmittance 0.13 W/m¬≤K; Average thermal transmittance 0.21 W/m¬≤K; Cavity wall, as built, insulated (assumed); Cavity wall, as built, no insulation (assumed); Cavity wall, as built, partial insulation (assumed); Cavity wall, filled cavity; Cavity wall, with external insulation; Granite or whinstone, as built, insulated (assumed); Granite or whinstone, as built, no insulation (assumed); Granite or whinstone, with internal insulation; Park home wall, as built; Park home wall, with external insulation; Sandstone or limestone, as built, insulated (assumed); Sandstone or limestone, as built, no insulation (assumed); Sandstone or limestone, with internal insulation; Solid brick, as built, no insulation (assumed); System built, as built, insulated (assumed); System built, as built, no insulation (assumed); System built, with external insulation; Timber frame, as built, insulated (assumed); Timber frame, as built, partial insulation (assumed); Timber frame, with additional insulation
A28: WALL_ENERGY_EFF | B28: Summary of the performance of this building element, reported in the following format: ‘Description; Energy Efficiency Rating; Environmental Efficiency Rating.’ Both ratings elements are reported on a scale of 1 to 5 (very poor, poor, average, good, very good). Note: where a dwelling has more than one type of this element, multiple elements can be reported. Each element reported is separated by “|” [ASCII (decimal) 124] | C28: Good | D28: =IFERROR(VLOOKUP(A28,'Unique Values'!$A$2:$B$57,2,FALSE),"") -> Average; Good; Poor; Very Good; Very Poor
A29: WALL_ENV_EFF | B29: Summary of the performance of this building element, reported in the following format: ‘Description; Energy Efficiency Rating; Environmental Efficiency Rating.’ Both ratings elements are reported on a scale of 1 to 5 (very poor, poor, average, good, very good). Note: where a dwelling has more than one type of this element, multiple elements can be reported. Each element reported is separated by “|” [ASCII (decimal) 124] | C29: Good | D29: =IFERROR(VLOOKUP(A29,'Unique Values'!$A$2:$B$57,2,FALSE),"") -> Average; Good; Poor; Very Good; Very Poor
A30: ROOF_DESCRIPTION | B30: Summary of the performance of this building element, reported in the following format: ‘Description; Energy Efficiency Rating; Environmental Efficiency Rating.’ Both ratings elements are reported on a scale of 1 to 5 (very poor, poor, average, good, very good). Note: where a dwelling has more than one type of this element, multiple elements can be reported. Each element reported is separated by “|” [ASCII (decimal) 124] | C30: Pitched, 250 mm loft insulation | D30: =IFERROR(VLOOKUP(A30,'Unique Values'!$A$2:$B$57,2,FALSE),"") -> (another dwelling above); Average thermal transmittance 0.10 W/m¬≤K; Average thermal transmittance 0.13 W/m¬≤K; Average thermal transmittance 0.15 W/m¬≤K; Flat, insulated; Flat, insulated (assumed); Flat, limited insulation (assumed); Flat, no insulation (assumed); Pitched, 100 mm loft insulation; Pitched, 150 mm loft insulation; Pitched, 200 mm loft insulation; Pitched, 250 mm loft insulation; Pitched, 270 mm loft insulation; Pitched, 300 mm loft insulation; Pitched, 350 mm loft insulation; Pitched, 400+ mm loft insulation; Pitched, insulated (assumed); Pitched, insulated at rafters; Pitched, limited insulation (assumed); Pitched, no insulation; Pitched, no insulation (assumed); Roof room(s), ceiling insulated; Roof room(s), insulated; Roof room(s), insulated (assumed); Roof room(s), limited insulation (assumed); Roof room(s), no insulation (assumed)
A31: ROOF_ENERGY_EFF | B31: Summary of the performance of this building element, reported in the following format: ‘Description; Energy Efficiency Rating; Environmental Efficiency Rating.’ Both ratings elements are reported on a scale of 1 to 5 (very poor, poor, average, good, very good). Note: where a dwelling has more than one type of this element, multiple elements can be reported. Each element reported is separated by “|” [ASCII (decimal) 124] | C31: Good | D31: =IFERROR(VLOOKUP(A31,'Unique Values'!$A$2:$B$57,2,FALSE),"") -> Average; Good; N/A; Poor; Very Good; Very Poor
A32: ROOF_ENV_EFF | B32: Summary of the performance of this building element, reported in the following format: ‘Description; Energy Efficiency Rating; Environmental Efficiency Rating.’ Both ratings elements are reported on a scale of 1 to 5 (very poor, poor, average, good, very good). Note: where a dwelling has more than one type of this element, multiple elements can be reported. Each element reported is separated by “|” [ASCII (decimal) 124] | C32: Good | D32: =IFERROR(VLOOKUP(A32,'Unique Values'!$A$2:$B$57,2,FALSE),"") -> Average; Good; N/A; Poor; Very Good; Very Poor
A33: FLOOR_DESCRIPTION | B33: Summary of the performance of this building element, reported in the following format: ‘Description; Energy Efficiency Rating; Environmental Efficiency Rating.’ Both ratings elements are reported on a scale of 1 to 5 (very poor, poor, average, good, very good). Note: where a dwelling has more than one type of this element, multiple elements can be reported. Each element reported is separated by “|” [ASCII (decimal) 124] | C33: Solid, no insulation (assumed) | D33: =IFERROR(VLOOKUP(A33,'Unique Values'!$A$2:$B$57,2,FALSE),"") -> (another dwelling below); Average thermal transmittance 0.12 W/m¬≤K; Average thermal transmittance 0.14 W/m¬≤K; Average thermal transmittance 0.15 W/m¬≤K; Solid, insulated; Solid, insulated (assumed); Solid, no insulation (assumed); Suspended, insulated; Suspended, insulated (assumed); Suspended, limited insulation (assumed); Suspended, no insulation (assumed); To unheated space, insulated (assumed); To unheated space, no insulation (assumed)
A34: FLOOR_ENERGY_EFF | B34: Summary of the performance of this building element, reported in the following format: ‘Description; Energy Efficiency Rating; Environmental Efficiency Rating.’ Both ratings elements are reported on a scale of 1 to 5 (very poor, poor, average, good, very good). Note: where a dwelling has more than one type of this element, multiple elements can be reported. Each element reported is separated by “|” [ASCII (decimal) 124] | C34: N/A | D34: =IFERROR(VLOOKUP(A34,'Unique Values'!$A$2:$B$57,2,FALSE),"") -> N/A; Very Good
A35: FLOOR_ENV_EFF | B35: Summary of the performance of this building element, reported in the following format: ‘Description; Energy Efficiency Rating; Environmental Efficiency Rating.’ Both ratings elements are reported on a scale of 1 to 5 (very poor, poor, average, good, very good). Note: where a dwelling has more than one type of this element, multiple elements can be reported. Each element reported is separated by “|” [ASCII (decimal) 124] | C35: N/A | D35: =IFERROR(VLOOKUP(A35,'Unique Values'!$A$2:$B$57,2,FALSE),"") -> N/A; Very Good
A36: WINDOWS_DESCRIPTION | B36: Summary of the performance of this building element, reported in the following format: ‘Description; Energy Efficiency Rating; Environmental Efficiency Rating.’ Both ratings elements are reported on a scale of 1 to 5 (very poor, poor, average, good, very good). Note: where a dwelling has more than one type of this element, multiple elements can be reported. Each element reported is separated by “|” [ASCII (decimal) 124] | C36: Description: Fully double glazed | D36: =IFERROR(VLOOKUP(A36,'Unique Values'!$A$2:$B$57,2,FALSE),"") -> Description: Fully double glazed; Description: Fully triple glazed; Description: High performance glazing; Description: Mostly double glazing; Description: Partial double glazing; Description: Some double glazing
A37: WINDOWS_ENERGY_EFF | B37: Summary of the performance of this building element, reported in the following format: ‘Description; Energy Efficiency Rating; Environmental Efficiency Rating.’ Both ratings elements are reported on a scale of 1 to 5 (very poor, poor, average, good, very good). Note: where a dwelling has more than one type of this element, multiple elements can be reported. Each element reported is separated by “|” [ASCII (decimal) 124] | C37: Average | D37: =IFERROR(VLOOKUP(A37,'Unique Values'!$A$2:$B$57,2,FALSE),"") -> Average; Good; Poor; Very Good; Very Poor
... A56: AIR_TIGHTNESS_ENV_EFF | B56: Summary of the performance of this building element, reported in the following format: ‘Description; Energy Efficiency Rating; Environmental Efficiency Rating.’ Both ratings elements are reported on a scale of 1 to 5 (very poor, poor, average, good, very good). Note: where a dwelling has more than one type of this element, multiple elements can be reported. Each element reported is separated by “|” [ASCII (decimal) 124] | C56: Good | D56: =IFERROR(VLOOKUP(A56,'Unique Values'!$A$2:$B$57,2,FALSE),"") -> Average; Good; Very Good
A57: CO2_EMISSIONS_CURRENT | B57: The total annual emissions reduction for the building based upon the calculated energy demand for heating, cooling, lighting, and ventilating the building. (Units: tonnes per year) | C57: 5.5 | D57: =IFERROR(VLOOKUP(A57,'Unique Values'!$A$2:$B$57,2,FALSE),"")
A58: CO2_EMISSIONS_POTENTIAL | B58: Calculation illustrating the total annual emissions reduction for the building if the identified improvement measures are carried out. (Units: tonnes per year) | C58: 2 | D58: =IFERROR(VLOOKUP(A58,'Unique Values'!$A$2:$B$57,2,FALSE),"")
A59: HEATING_COST_CURRENT | B59: Calculation illustrating the total energy cost for heating over the stated period. Based on standardised occupancy patterns and fuel costs. (Units: £) | C59: 4533 | D59: =IFERROR(VLOOKUP(A59,'Unique Values'!$A$2:$B$57,2,FALSE),"")
A60: HEATING_COST_POTENTIAL | B60: Calculation illustrating the total energy cost for heating over the stated period if recommended improvement measures are carried out. Based on standardised occupancy patterns and fuel costs. (Units: £) | C60: 3921 | D60: =IFERROR(VLOOKUP(A60,'Unique Values'!$A$2:$B$57,2,FALSE),"")
A61: HOT_WATER_COST_CURRENT | B61: Calculation illustrating the total energy cost for hot water over the stated period. Based on standardised occupancy patterns and fuel costs. (Units: £) | C61: 1419 | D61: =IFERROR(VLOOKUP(A61,'Unique Values'!$A$2:$B$57,2,FALSE),"")
A62: HOT_WATER_COST_POTENTIAL | B62: Calculation illustrating the total energy cost for hot water over the stated period if recommended improvement measures are carried out. Based on standardised occupancy patterns and fuel costs. (Units: £) | C62: 720 | D62: =IFERROR(VLOOKUP(A62,'Unique Values'!$A$2:$B$57,2,FALSE),"")
A63: LIGHTING_COST_CURRENT | B63: Calculation illustrating the total energy cost for lighting over the stated period. Based on standardised occupancy patterns and fuel costs. (Units: £) | C63: 285 | D63: =IFERROR(VLOOKUP(A63,'Unique Values'!$A$2:$B$57,2,FALSE),"")
A64: LIGHTING_COST_POTENTIAL | B64: Calculation illustrating the total energy cost for lighting over the stated period if recommended improvement measures are carried out. Based on standardised occupancy patterns and fuel costs. (Units: £) | C64: 285 | D64: =IFERROR(VLOOKUP(A64,'Unique Values'!$A$2:$B$57,2,FALSE),"")
A65: ALTERNATIVE_IMPROVEMENTS | B65: List of further improvements to the building that can be considered. Note that these measures are not used in calculation of potential ratings or savings (description only). Note: multiple measures can be reported. Each measure reported is separated by a vertical line [ “|” - ASCII (decimal) 124] | C65: Description: Biomass boiler (Exempted Appliance if in Smoke Control Area) | Description: Air or ground source heat pump | | D65: =IFERROR(VLOOKUP(A65,'Unique Values'!$A$2:$B$57,2,FALSE),"")
A66: LZC_ENERGY_SOURCES | B66: Recorded where a low or zero carbon technology (equipment that either generates or otherwise provides energy with no or little resulting emissions) is present in the dwelling. Examples include photovoltaic panels, solar thermal panels, and wind turbines. | C66: Description: Biomass secondary heating | | D66: =IFERROR(VLOOKUP(A66,'Unique Values'!$A$2:$B$57,2,FALSE),"") -> ; Description: Air source heat pump; Description: Biomass community heating; Description: Biomass community heating for some of heat generation; Description: Biomass main heating; Description: Biomass secondary heating; Description: Ground source heat pump; Description: Solar photovoltaics
A67: SPACE_HEATING_DEMAND | B67: Reports the calculated heat demand for space heating in the current dwelling. Based upon the levels of insulation present and how this limits heat loss. (Units: kWh per year) | C67: 10523 | D67: =IFERROR(VLOOKUP(A67,'Unique Values'!$A$2:$B$57,2,FALSE),"")
A68: WATER_HEATING_DEMAND | B68: Reports the calculated heat demand for provision of hot water in the current dwelling. Based upon the efficiency of the water heating system. (Units: kWh per year) | C68: 3377 | D68: =IFERROR(VLOOKUP(A68,'Unique Values'!$A$2:$B$57,2,FALSE),"")
A69: IMPACT_LOFT_INSULATION | B69: (if applicable) Reports the potential reduction in calculated heat demand for space heating if the dwelling loft is insulated. (Units: kWh per year) | C69: 8848 | D69: =IFERROR(VLOOKUP(A69,'Unique Values'!$A$2:$B$57,2,FALSE),"")
A70: IMPACT_CAVITY_WALL_INSULATION | B70: (if applicable) Reports the potential reduction in calculated heat demand for space heating if the dwelling cavity walls are insulated. (Units: kWh per year) | C70: 5875 | D70: =IFERROR(VLOOKUP(A70,'Unique Values'!$A$2:$B$57,2,FALSE),"")
A71: IMPACT_SOLID_WALL_INSULATION | B71: (if applicable) Reports the potential reduction in calculated heat demand for space heating if external or internal insulation applied to the dwelling walls. (Units: kWh per year) | C71: 10395 | D71: =IFERROR(VLOOKUP(A71,'Unique Values'!$A$2:$B$57,2,FALSE),"")
A72: ADDENDUM_TEXT | B72: Used to record a range of specific observations about the dwelling construction that are relevant to the assessment. Current valid options are listed in Section S15 in Appendix S of the current SAP 2012 October 2013 with RdSAP 19 Dec 2014 specification. | D72: =IFERROR(VLOOKUP(A72,'Unique Values'!$A$2:$B$57,2,FALSE),"")
A73: CONSTRUCTION_AGE_BAND | B73: Age band when building part constructed. For Scotland, one of: before 1919; 1919-1929; 1930-1949; 1950-1964; 1965-1975; 1976-1983; 1984-1991; 1992-1998; 1999-2002; 2003-2007; 2008- 2011; 2012 onwards. | C73: 1950-1964 | D73: =IFERROR(VLOOKUP(A73,'Unique Values'!$A$2:$B$57,2,FALSE),"") -> 1930-1949; 1950-1964; 1965-1975; 1976-1983; 1984-1991; 1992-1998; 1999-2002; 2003-2007; 2008 onwards; before 1919
A74: FLOOR_HEIGHT | B74: Average height of the lowest storey of the dwelling (Units: m) | C74: 2.39 | D74: =IFERROR(VLOOKUP(A74,'Unique Values'!$A$2:$B$57,2,FALSE),"")
A75: DATA_ZONE | B75: Data Zone code and name - Data zones are the key geography for the dissemination of small area statistics in Scotland. | C75: S01006074 (Strathendrick) | D75: =IFERROR(VLOOKUP(A75,'Unique Values'!$A$2:$B$57,2,FALSE),"")
A76: ENERGY_CONSUMPTION_POTENTIAL | B76: Reports Primary Energy - the amount of energy required at source, before conversion and transmission, to meet the calculated energy demand of the dwelling, if recommended improvement measures are carried out (Units: kWh/m²/year). | C76: 161 | D76: =IFERROR(VLOOKUP(A76,'Unique Values'!$A$2:$B$57,2,FALSE),"")
A77: EXTENSION_COUNT | B77: The number of extensions added to the property. Between 0 and 4 can be reported. | C77: 0 | D77: =IFERROR(VLOOKUP(A77,'Unique Values'!$A$2:$B$57,2,FALSE),"") -> 0; 1; 2; 3; 4
A78: FIXED_LIGHTING_OUTLETS_COUNT | B78: The number of fixed lighting outlets in the dwelling. | C78: 12 | D78: =IFERROR(VLOOKUP(A78,'Unique Values'!$A$2:$B$57,2,FALSE),"")
A79: LOW_ENERGY_FIXED_LIGHT_COUNT | B79: The number of low-energy fixed lighting outlets. | C79: 12 | D79: =IFERROR(VLOOKUP(A79,'Unique Values'!$A$2:$B$57,2,FALSE),"")
A80: LOW_ENERGY_LIGHTING | B80: The percentage of low energy lighting present in the property as a percentage of the total fixed lights in the property. 0% indicates that no low-energy lighting is present. | C80: 100 | D80: =IFERROR(VLOOKUP(A80,'Unique Values'!$A$2:$B$57,2,FALSE),"")
A81: FLOOR_LEVEL | B81: Floor level relative to the lowest level of the building | C81: top floor | D81: =IFERROR(VLOOKUP(A81,'Unique Values'!$A$2:$B$57,2,FALSE),"") -> ground floor; top floor
A82: FLAT_TOP_STOREY | B82: The number of storeys in the flatted block. | C82: 1 | D82: =IFERROR(VLOOKUP(A82,'Unique Values'!$A$2:$B$57,2,FALSE),"") -> 0.0; 1.0
A83: GLAZED_AREA | B83: Ranged estimate of the total glazed area of the Habitable Area: 0 – New dwelling 1 – Typical glazing 2 – More than typical 3 – Less than typical 4 – Much more than typical 5 – Much less than typical | C83: 1 | D83: =IFERROR(VLOOKUP(A83,'Unique Values'!$A$2:$B$57,2,FALSE),"") -> 0; 1; 2; 4
A84: NUMBER_HABITABLE_ROOMS | B84: Habitable rooms include any living room, sitting room, dining room, bedroom, study and similar. Excludes any room used solely as a kitchen, utility room, sanitary accommodation and any hallway, stairs, or landing; and also any conservatory or room without a window. | C84: 4 | D84: =IFERROR(VLOOKUP(A84,'Unique Values'!$A$2:$B$57,2,FALSE),"") -> 0; 10; 15; 2; 3; 4; 5; 6; 7; 8
A85: HEAT_LOSS_CORRIDOOR | B85: Flats and maisonettes only. Indicates that the flat contains a corridor through which heat is lost. Heat loss corridor, one of: no corridor; heated corridor; unheated corridor | D85: =IFERROR(VLOOKUP(A85,'Unique Values'!$A$2:$B$57,2,FALSE),"") -> no corridor; unheated corridor
A86: NUMBER_HEATED_ROOMS | B86: The number of heated habitable rooms in the property. | C86: 4 | D86: =IFERROR(VLOOKUP(A86,'Unique Values'!$A$2:$B$57,2,FALSE),"") -> 0; 15; 2; 3; 4; 5; 6; 7; 8; 9
A87: LOCAL_AUTHORITY_LABEL | B87: The name of the local authority area in which the building is located. | C87: Stirling | D87: =IFERROR(VLOOKUP(A87,'Unique Values'!$A$2:$B$57,2,FALSE),"") -> Stirling
A88: MAINS_GAS_FLAG | B88: Whether mains gas is available. Yes means that there is a gas meter or a gas-burning appliance in the dwelling | D88: =IFERROR(VLOOKUP(A88,'Unique Values'!$A$2:$B$57,2,FALSE),"") -> 0
A89: MAIN_HEATING_CATEGORY | B89: Reports the type of main heating system present in the dwelling. Lists both heat source and heat emitters (e.g. gas boiler and radiators). | C89: boiler with radiators or underfloor heating | D89: =IFERROR(VLOOKUP(A89,'Unique Values'!$A$2:$B$57,2,FALSE),"") -> boiler with radiators or underfloor heating; community heating system; electric storage heaters; heat pump with radiators or underfloor heating; none; room heaters
A90: MAIN_FUEL | B90: Reports the fuel type used by the main heating system present in the dwelling. | C90: dual fuel - mineral + wood | D90: =IFERROR(VLOOKUP(A90,'Unique Values'!$A$2:$B$57,2,FALSE),"") -> biomass; bottled lpg; bulk wood pellets; dual fuel - mineral + wood; electricity; electricity: electricity, unspecified tariff; lpg; mains gas; no heating/hot-water system or data is from a community network; oil
A91: MAIN_HEATING_CONTROLS | B91: Type of main heating controls (shown as an ID number for the type of controls. Includes both main heating systems if there are two. | C91: 2111 | D91: =IFERROR(VLOOKUP(A91,'Unique Values'!$A$2:$B$57,2,FALSE),"") -> 2102.0; 2104.0; 2106.0; 2107.0; 2111.0; 2204.0; 2205.0; 2206.0; 2207.0; 2302.0; 2303.0; 2304.0; 2305.0; 2306.0; 2309.0; 2312.0; 2401.0; 2402.0; 2404.0; 2601.0; 2602.0; 2603.0; 2605.0; 2699.0
A92: MECHANICAL_VENTILATION | B92: Identifies the type of mechanical ventilation the property has. | C92: natural | D92: =IFERROR(VLOOKUP(A92,'Unique Values'!$A$2:$B$57,2,FALSE),"") -> mechanical, extract only; mechanical, supply and extract; natural
A93: ENERGY_TARIFF | B93: Type of electricity tariff for the property (by meter type), e.g. single. | C93: Single | D93: =IFERROR(VLOOKUP(A93,'Unique Values'!$A$2:$B$57,2,FALSE),"") -> Single; Unknown; dual; dual (24 hour)
A94: MULTI_GLAZE_PROPORTION | B94: The estimated banded range (e.g. 0% - 10%) of the total glazed area of the Property that is multiple glazed. | C94: 100 | D94: =IFERROR(VLOOKUP(A94,'Unique Values'!$A$2:$B$57,2,FALSE),"")
A95: GLAZED_TYPE | B95: The type of glazing. From British Fenestration Rating Council or manufacturer declaration, one of; single; double; triple. | C95: double glazing installed before 2002 | D95: =IFERROR(VLOOKUP(A95,'Unique Values'!$A$2:$B$57,2,FALSE),"") -> double glazing installed before 2002; double glazing installed during or after 2002; double glazing, unknown install date; not defined; triple glazing
A96: NUMBER_OPEN_FIREPLACES | B96: The number of Open Fireplaces in the Property. An Open Fireplace is a fireplace that still allows air to pass between the inside of the Property and the outside. | C96: 0 | D96: =IFERROR(VLOOKUP(A96,'Unique Values'!$A$2:$B$57,2,FALSE),"")
A97: PHOTO_SUPPLY | B97: Photovoltaic area as a percentage of total roof area. 0% indicates that a Photovoltaic Supply is not present in the property. Note: multiple arrays can be reported. Each array reported is separated by a vertical line [ “|” - ASCII (decimal) 124] | C97: Array: Roof Area: 0%; Connection: not applicable (FGHRS or no PV); | | D97: =IFERROR(VLOOKUP(A97,'Unique Values'!$A$2:$B$57,2,FALSE),"")
A98: SOLAR_WATER_HEATING_FLAG | B98: Indicates whether the water heating in the property is served by solar thermal panels. | C98: FALSE | D98: =IFERROR(VLOOKUP(A98,'Unique Values'!$A$2:$B$57,2,FALSE),"") -> FALSE
A99: TENURE | B99: Describes the tenure type of the property. One of: Owner- occupied; Rented (social); Rented (private); Unknown | C99: owner-occupied | D99: =IFERROR(VLOOKUP(A99,'Unique Values'!$A$2:$B$57,2,FALSE),"") -> owner-occupied; rented (private); rented (social); unknown
A100: TRANSACTION_TYPE | B100: Type of transaction or purpose that triggered EPC assessment. One of: - new dwelling; marketed sale; non-marketed sale; rental; not sale or rental; assessment for Green Deal; following Green Deal; FIT application; RHI application; ECO assessment; none of the above. Where the reason for the assessment is unknown by the energy assessor the transaction type will be recorded as 'none of the above'. | C100: marketed sale | D100: =IFERROR(VLOOKUP(A100,'Unique Values'!$A$2:$B$57,2,FALSE),"") -> ECO assessment; FiT application; RHI application; marketed sale; new dwelling; non marketed sale; none of the above; rental
A101: UNHEATED_CORRIDOR_LENGTH | B101: The total length of unheated corridor in the flat. Only populated if flat or maisonette contains unheated corridor. If unheated corridor, length of sheltered wall (m²). | C101: 8.3 | D101: =IFERROR(VLOOKUP(A101,'Unique Values'!$A$2:$B$57,2,FALSE),"")
A102: CONSTITUENCY | B102: Code for Parliamentary constituency in which the building is located. Scottish area defined as 'Ward', not 'constituency' | C102: 00RGMB | D102: =IFERROR(VLOOKUP(A102,'Unique Values'!$A$2:$B$57,2,FALSE),"")
A103: CONSTITUENCY_LABEL | B103: Name of Parliamentary constituency in which the building is located. Scottish area defined as 'Ward', not 'constituency' | C103: Forth and Endrick | D103: =IFERROR(VLOOKUP(A103,'Unique Values'!$A$2:$B$57,2,FALSE),"")
A104: WIND_TURBINE_COUNT | B104: Number of wind turbines; 0 if none. | C104: 0 | D104: =IFERROR(VLOOKUP(A104,'Unique Values'!$A$2:$B$57,2,FALSE),"")
A105: BUILT_FORM | B105: The building type of the Property e.g. Detached, Semi-Detached, Terrace etc. Together with the Property Type, the Build Form produces a structured description of the property | C105: Semi-Detached | D105: =IFERROR(VLOOKUP(A105,'Unique Values'!$A$2:$B$57,2,FALSE),"") -> Detached; Enclosed End-Terrace; End-Terrace; Mid-Terrace; Semi-Detached
A106: PROPERTY_TYPE | B106: Describes the type of property such as House, Flat, Maisonette etc. This is the type differentiator for dwellings. | C106: House | D106: =IFERROR(VLOOKUP(A106,'Unique Values'!$A$2:$B$57,2,FALSE),"") -> Bungalow; Flat; House; Park home
A107: DATA_ZONE_2011 | C107: S01013015 (Kippen and Fintry - 01) | D107: =IFERROR(VLOOKUP(A107,'Unique Values'!$A$2:$B$57,2,FALSE),"")
A108: CREATED_AT | B108: The date and time that the certificate was lodged on the register. | C108: 45800.497 | D108: =IFERROR(VLOOKUP(A108,'Unique Values'!$A$2:$B$57,2,FALSE),"")
A109: REPORT_REFERENCE_NUMBER | B109: Unique, auto-generated number produced on the lodgement of an EPC to the SEPCR. | C109: 2899-1018-5205-0295-2200 | D109: =IFERROR(VLOOKUP(A109,'Unique Values'!$A$2:$B$57,2,FALSE),"")
A110: dwelling_id | C110: 11 CULCREUCH AVENUE | G63 0YB | D110: =IFERROR(VLOOKUP(A110,'Unique Values'!$A$2:$B$57,2,FALSE),"")
A111: IMPROVEMENTS_PARSED | B111: This variable contains a structured representation of the EPC-recommended energy efficiency improvements for each dwelling. The original semi-structured text field is parsed into individual measures, each including the improvement description, indicative cost range, estimated annual savings, expected post-improvement energy and environmental ratings, and Green Deal eligibility. Multiple recommended measures are stored as a list for each property. | C111: [{'description': None, 'cost_min': 300, 'cost_max': 600, 'typical_saving': 77, 'energy_rating': 'D 64', 'env_rating': 'D 55', 'green_deal': 'Y'}, {'description': 'Solar photovoltaic panels, 2.5 kWp', 'cost_min': 3500, 'cost_max': 5500, 'typical_saving': 389, 'energy_rating': 'B 81', 'env_rating': 'C 72', 'green_deal': 'Y'}, {'description': 'Floor insulation (solid floor)', 'cost_min': 4000, 'cost_max': 6000, 'typical_saving': 186, 'energy_rating': 'D 67', 'env_rating': 'D 59', 'green_deal': 'Y'}, {'description': 'Solar water heating', 'cost_min': 4000, 'cost_max': 6000, 'typical_saving': 173, 'energy_rating': 'C 71', 'env_rating': 'D 64', 'green_deal': 'Y'}, {'description': None, 'cost_min': None, 'cost_max': None, 'typical_saving': None, 'energy_rating': None, 'env_rating': None, 'green_deal': None}] | D111: =IFERROR(VLOOKUP(A111,'Unique Values'!$A$2:$B$57,2,FALSE),"")
A112: WALL_DESCRIPTION_PARSED | B112: This variable provides a structured representation of the dwelling’s external wall construction and associated EPC performance ratings. The parsed data captures the wall type (e.g., cavity wall, solid wall, insulated wall) along with the corresponding EPC energy efficiency and environmental impact ratings. | C112: [{'description': 'System built, with external insulation', 'energy_rating': 'Good', 'env_rating': 'Good'}] | D112: =IFERROR(VLOOKUP(A112,'Unique Values'!$A$2:$B$57,2,FALSE),"")
A113: ROOF_DESCRIPTION_PARSED | B113: This variable contains a structured representation of the roof construction and insulation characteristics reported in the EPC. Each entry includes the roof description and the associated EPC energy and environmental performance ratings. | C113: [{'description': 'Pitched, 250 mm loft insulation', 'energy_rating': 'Good', 'env_rating': 'Good'}] | D113: =IFERROR(VLOOKUP(A113,'Unique Values'!$A$2:$B$57,2,FALSE),"")
A114: FLOOR_DESCRIPTION_PARSED | B114: This variable represents the dwelling’s floor construction and insulation properties as described in the EPC. The parsed data includes the floor description (e.g., solid floor, suspended timber floor) along with its EPC energy and environmental ratings. | C114: [{'description': 'Solid, no insulation (assumed)', 'energy_rating': 'N/A', 'env_rating': 'N/A'}] | D114: =IFERROR(VLOOKUP(A114,'Unique Values'!$A$2:$B$57,2,FALSE),"")
A115: WINDOWS_DESCRIPTION_PARSED | B115: This variable captures the glazing type and window performance characteristics of the dwelling. The parsed structure includes the EPC description of the windows (e.g., single glazing, double glazing, secondary glazing) and the corresponding energy and environmental ratings. | C115: [{'description': 'Description: Fully double glazed', 'energy_rating': 'Average', 'env_rating': 'Average'}] | D115: =IFERROR(VLOOKUP(A115,'Unique Values'!$A$2:$B$57,2,FALSE),"")
A116: MAINHEAT_DESCRIPTION_PARSED | B116: This variable contains a structured representation of the dwelling’s primary space heating system as described in the EPC. The parsed entries include the heating system type (e.g., boiler, electric storage heaters, heat pump) and the associated energy and environmental efficiency ratings. | C116: [{'description': 'Boiler and radiators, dual fuel (mineral and wood)', 'energy_rating': 'Average', 'env_rating': 'Average'}] | D116: =IFERROR(VLOOKUP(A116,'Unique Values'!$A$2:$B$57,2,FALSE),"")
A117: MAINHEATCONT_DESCRIPTION_PARSED | B117: This variable represents the heating control systems associated with the primary heating system. The parsed data includes descriptions of controls such as thermostats, programmers, or zone controls along with the EPC energy and environmental ratings. | C117: [{'description': 'TRVs and bypass', 'energy_rating': 'Average', 'env_rating': 'Average'}] | D117: =IFERROR(VLOOKUP(A117,'Unique Values'!$A$2:$B$57,2,FALSE),"")
A118: SECONDHEAT_DESCRIPTION_PARSED | B118: This variable describes any secondary heating systems present in the dwelling, such as open fireplaces or room heaters. The parsed structure includes the system description and the corresponding EPC energy and environmental ratings. | C118: [{'description': 'Room heaters, dual fuel (mineral and wood)', 'energy_rating': 'N/A', 'env_rating': 'N/A'}] | D118: =IFERROR(VLOOKUP(A118,'Unique Values'!$A$2:$B$57,2,FALSE),"")
...

Sheet Unique Values
A1: Parameter | B1: Unique_Values
A2: CURRENT_ENERGY_RATING | B2: A; B; C; D; E; F; G
A3: POTENTIAL_ENERGY_RATING | B3: A; B; C; D; E
A4: CURRENT_ENVIRONMENTAL_RATING | B4: A; B; C; D; E; F; G
A5: POTENTIAL_ENVIRONMENTAL_RATING | B5: A; B; C; D; E
A6: WALL_DESCRIPTION | B6: Average thermal transmittance 0.12 W/m¬≤K; Average thermal transmittance 0.13 W/m¬≤K; Average thermal transmittance 0.21 W/m¬≤K; Cavity wall, as built, insulated (assumed); Cavity wall, as built, no insulation (assumed); Cavity wall, as built, partial insulation (assumed); Cavity wall, filled cavity; Cavity wall, with external insulation; Granite or whinstone, as built, insulated (assumed); Granite or whinstone, as built, no insulation (assumed); Granite or whinstone, with internal insulation; Park home wall, as built; Park home wall, with external insulation; Sandstone or limestone, as built, insulated (assumed); Sandstone or limestone, as built, no insulation (assumed); Sandstone or limestone, with internal insulation; Solid brick, as built, no insulation (assumed); System built, as built, insulated (assumed); System built, as built, no insulation (assumed); System built, with external insulation; Timber frame, as built, insulated (assumed); Timber frame, as built, partial insulation (assumed); Timber frame, with additional insulation
A7: WALL_ENERGY_EFF | B7: Average; Good; Poor; Very Good; Very Poor
A8: WALL_ENV_EFF | B8: Average; Good; Poor; Very Good; Very Poor
A9: ROOF_DESCRIPTION | B9: (another dwelling above); Average thermal transmittance 0.10 W/m¬≤K; Average thermal transmittance 0.13 W/m¬≤K; Average thermal transmittance 0.15 W/m¬≤K; Flat, insulated; Flat, insulated (assumed); Flat, limited insulation (assumed); Flat, no insulation (assumed); Pitched, 100 mm loft insulation; Pitched, 150 mm loft insulation; Pitched, 200 mm loft insulation; Pitched, 250 mm loft insulation; Pitched, 270 mm loft insulation; Pitched, 300 mm loft insulation; Pitched, 350 mm loft insulation; Pitched, 400+ mm loft insulation; Pitched, insulated (assumed); Pitched, insulated at rafters; Pitched, limited insulation (assumed); Pitched, no insulation; Pitched, no insulation (assumed); Roof room(s), ceiling insulated; Roof room(s), insulated; Roof room(s), insulated (assumed); Roof room(s), limited insulation (assumed); Roof room(s), no insulation (assumed)
A10: ROOF_ENERGY_EFF | B10: Average; Good; N/A; Poor; Very Good; Very Poor
A11: ROOF_ENV_EFF | B11: Average; Good; N/A; Poor; Very Good; Very Poor
A12: FLOOR_DESCRIPTION | B12: (another dwelling below); Average thermal transmittance 0.12 W/m¬≤K; Average thermal transmittance 0.14 W/m¬≤K; Average thermal transmittance 0.15 W/m¬≤K; Solid, insulated; Solid, insulated (assumed); Solid, no insulation (assumed); Suspended, insulated; Suspended, insulated (assumed); Suspended, limited insulation (assumed); Suspended, no insulation (assumed); To unheated space, insulated (assumed); To unheated space, no insulation (assumed)
... A45: LOCAL_AUTHORITY_LABEL | B45: Stirling
A46: MAINS_GAS_FLAG
A47: MAIN_HEATING_CATEGORY | B47: boiler with radiators or underfloor heating; community heating system; electric storage heaters; heat pump with radiators or underfloor heating; none; room heaters
A48: MAIN_FUEL | B48: biomass; bottled lpg; bulk wood pellets; dual fuel - mineral + wood; electricity; electricity: electricity, unspecified tariff; lpg; mains gas; no heating/hot-water system or data is from a community network; oil
A49: MAIN_HEATING_CONTROLS | B49: 2102.0; 2104.0; 2106.0; 2107.0; 2111.0; 2204.0; 2205.0; 2206.0; 2207.0; 2302.0; 2303.0; 2304.0; 2305.0; 2306.0; 2309.0; 2312.0; 2401.0; 2402.0; 2404.0; 2601.0; 2602.0; 2603.0; 2605.0; 2699.0
A50: MECHANICAL_VENTILATION | B50: mechanical, extract only; mechanical, supply and extract; natural
A51: ENERGY_TARIFF | B51: Single; Unknown; dual; dual (24 hour)
A52: GLAZED_TYPE | B52: double glazing installed before 2002; double glazing installed during or after 2002; double glazing, unknown install date; not defined; triple glazing
A53: SOLAR_WATER_HEATING_FLAG | B53: FALSE
A54: TENURE | B54: owner-occupied; rented (private); rented (social); unknown
A55: TRANSACTION_TYPE | B55: ECO assessment; FiT application; RHI application; marketed sale; new dwelling; non marketed sale; none of the above; rental
A56: BUILT_FORM | B56: Detached; Enclosed End-Terrace; End-Terrace; Mid-Terrace; Semi-Detached
A57: PROPERTY_TYPE | B57: Bungalow; Flat; House; Park home
